Workbook
Name A: #REF!
Name A: #REF!
Name A: #REF!
Name ActualNumberOfPayments: IFERROR(IF(LoanIsGood,IF(PaymentsPerYear=1,1,MATCH(0.01,Mortgage!End_Bal,-1)+1)),"")
Name B: #REF!
Name B: #REF!
Name B: #REF!
Name Beg_Bal: #REF!
Name Beg_Bal: #REF!
Name Beg_Bal: #REF!
Name Categories: OFFSET('[1]Archived Categories Sheet'!$J$7,0,0,COUNTIF('[1]Archived Categories Sheet'!$J$7:$J$44,"<>"&"--"),1)
Name CategoryIdentifiers: #REF!
Name CategoryNames: Monthly!$C$9:$C$193
Name ColumnTitle1: PaymentSchedule[[#Headers],[PMT NO]]
Name Data: #REF!
Name Data: #REF!
Name Data: #REF!
Name ddf: #REF!
Name eb: #REF!
Name eb: #REF!
Name eb: #REF!
Name End_Bal: PaymentSchedule[ENDING BALANCE]
Name End_Bal: #REF!
Name End_Bal: #REF!
Name End_Bal: #REF!
Name ep: #REF!
Name ep: #REF!
Name ep: #REF!
Name Extra_Pay: #REF!
Name Extra_Pay: #REF!
Name Extra_Pay: #REF!
Name ExtraPayments: Mortgage!$E$8
Name ff: #REF!
Name Full_Print: #REF!
Name Full_Print: #REF!
Name Full_Print: #REF!
Name h: IF([2]Fixed!Values_Entered,[2]Fixed!Header_Row+[2]Fixed!Number_of_Payments,[2]Fixed!Header_Row)
Name h: IF([2]Fixed!Values_Entered,[2]Fixed!Header_Row+[2]Fixed!Number_of_Payments,[2]Fixed!Header_Row)
Name h: IF([2]Fixed!Values_Entered,[2]Fixed!Header_Row+[2]Fixed!Number_of_Payments,[2]Fixed!Header_Row)
Name Header_Row: ROW(#REF!)
Name Header_Row: ROW(#REF!)
Name Header_Row: ROW(#REF!)
Name HiddenCategoriesCategoryNames: _xlfn.ANCHORARRAY([1]HiddenCategories!$B$2)
Name Int: #REF!
Name Int: #REF!
Name Int: #REF!
Name Interest_Rate: #REF!
Name Interest_Rate: #REF!
Name Interest_Rate: #REF!
Name InterestRate: Mortgage!$E$3
Name Last_Row: #N/A
Name Last_Row: #N/A
Name LastCol: MATCH(REPT("z",255),Mortgage!$10:$10)
Name LastRow: MATCH(9.99E+307,Mortgage!$B:$B)
Name LenderName: Mortgage!$H$8:$I$8
Name Loan_Amount: #REF!
Name Loan_Amount: #REF!
Name Loan_Amount: #REF!
Name Loan_Start: #REF!
Name Loan_Start: #REF!

Sheet FinSnapshot
A8: Category | B8: Dec'02 | C8: Dec '03 | D8: Dec'04 | E8: Dec'05 | F8: Dec'06 | G8: Dec'07 | H8: Dec'08 | I8: Dec'09 | J8: Dec '10 | K8: Dec'11 | L8: Dec'12 | M8: Dec'13 | N8: Dec'14 | O8: Dec'15 | P8: Dec'16 | Q8: Dec'17 | R8: Dec'18 | S8: Dec'19 | T8: Dec'20 | U8: Dec'21 | V8: Dec'22 | W8: Dec'23 | X8: Dec'24 | Y8: DDec'25 | Z8: Dec'19 | AA8: Dec'20 | AB8: Dec'30 | AC8: Comp NE'15 | AD8: Decade | AE8: Yrly Avg/Dec
A9: Year | B9: 1 | C9: 2 | D9: 3 | E9: 4 | F9: 5 | G9: 6 | H9: 7 | I9: 8 | J9: 9 | K9: 10 | L9: 11 | M9: 12 | N9: 13 | O9: 14 | P9: 15 | Q9: 16 | R9: 17 | S9: 18 | T9: 19 | U9: 20 | V9: 21 | W9: 22 | X9: 23 | Z9: 18 | AA9: 18 | AB9: 30
A10: Cash Assets | B10: =SUM(B11:B12) -> 33800 | C10: =SUM(C11:C12) -> 46727 | D10: =SUM(D11:D12) -> 51927 | E10: =SUM(E11:E12) -> 48000 | F10: =SUM(F11:F12) -> 61000 | G10: =SUM(G11:G12) -> 90551 | H10: =SUM(H11:H12) -> 90898 | I10: =SUM(I11:I12) -> 155500 | ... X10: =SUM(X11:X12) -> 510000 | Z10: =SUM(Z11:Z12) -> 1016000 | AA10: =SUM(AA11:AA12) -> 115000 | AB10: =SUM(AB11:AB12) -> 355000 | AC10: =(R10-O10)/O10 -> 3.375 | AD10: =(Z10-I10)/I10 -> 5.5337621 | AE10: =(Z10-I10)/10 -> 86050
A11: Savings | B11: 32800 | C11: 45727 | D11: 50927 | E11: 47000 | F11: 60000 | G11: 89551 | H11: 89898 | I11: 153000 | J11: 136163 | K11: 132700 | L11: 80000 | M11: 92353 | N11: 162000 | O11: 195000 | P11: 499000 | Q11: 730000 | R11: 860000 | S11: =205282 + 121225 + 358493 + 30000 + 86000 + 200000 -> 1001000 | T11: 300500 | U11: 340000 | V11: 334000 | W11: =347000 -> 347000 | X11: 400000 | Z11: =205282 + 121225 + 358493 + 30000 + 86000 + 200000 -> 1001000 | AA11: 100000 | AB11: 340000 | AD11: =(Z11-I11)/I11 -> 5.5424837 | AE11: =(Z11-I11)/10 -> 84800
A12: Checking | B12: 1000 | C12: 1000 | D12: 1000 | E12: 1000 | F12: 1000 | G12: 1000 | H12: 1000 | I12: 2500 | J12: 3540 | K12: 3500 | L12: 3500 | M12: 20000 | N12: 20000 | O12: 5000 | P12: 35280 | Q12: 15000 | R12: 15000 | S12: 15000 | T12: 58000 | U12: 120000 | V12: 90000 | W12: 80000 | X12: 110000 | Z12: 15000 | AA12: 15000 | AB12: 15000 | AD12: =(Z12-I12)/I12 -> 5 | AE12: =(Z12-I12)/10 -> 1250
A13: Investment Accounts | B13: =SUM(B14:B20) -> 0 | C13: =SUM(C14:C20) -> 11900 | D13: =SUM(D14:D20) -> 22700 | E13: =SUM(E14:E20) -> 47268 | F13: =SUM(F14:F20) -> 89280 | G13: =SUM(G14:G20) -> 137032 | H13: =SUM(H14:H20) -> 111608 | I13: =SUM(I14:I20) -> 132750 | ... X13: =SUM(X14:X20) -> 2621522.8 | Z13: =SUM(Z14:Z20) -> 1034727 | AA13: =SUM(AA14:AA20) -> 1187900 | AB13: =SUM(AB14:AB20) -> 1562355 | AC13: =(R13-O13)/O13 -> 0.16880696 | AD13: =(Z13-I13)/I13 -> 6.7945537 | AE13: =(Z13-I13)/10 -> 90197.7
A14: SPP/SOP - S | B14: 0 | C14: 8000 | D14: 19000 | E14: 33268 | F14: 56938 | G14: 87551 | H14: 51586 | I14: 61900 | J14: 90000 | K14: 100285 | L14: 130793 | M14: 145234 | N14: 170609 | O14: 135000 | P14: 15666 | Q14: 20000 | R14: 0 | S14: 8400 | T14: 0 | U14: 65000 | V14: 0 | W14: 379429.03 | X14: 504000 | Z14: 8400 | AA14: 0 | AB14: 0 | AD14: =(Z14-I14)/I14 -> -0.86429725 | AE14: =(Z14-I14)/10 -> -5350 | AT14: SRP
A15: SPP/SOP - R | B15: 0 | C15: 1500 | D15: 1500 | E15: 1000 | F15: 3300 | G15: 7000 | H15: 265 | I15: 0 | J15: 12000 | K15: 21282 | L15: 35612 | M15: 41349 | N15: 58751 | O15: 38000 | P15: 1241 | Q15: 1500 | R15: 0 | S15: 0 | T15: 0 | U15: 0 | V15: 0 | W15: 668707.07 | X15: 310849.01 | Z15: 0 | AA15: 0 | AB15: 0 | AC15: 0 | AD15: - | AE15: =(Z15-I15)/10 -> 0 | AU15: SRP
A16: Vanguard | B16: 0 | C16: 0 | D16: 0 | E16: 10800 | F16: 25800 | G16: 39150 | H16: 52000 | I16: 62000 | J16: 120000 | K16: 158586 | L16: 201000 | M16: 284057 | N16: 327669 | O16: 375595 | P16: 439873 | Q16: 536436 | R16: 536436 | S16: 656355 | T16: 720112 | U16: 862000 | V16: 531529 | W16: 861860.61 | X16: 1015673.6 | Z16: 656355 | AA16: 862000 | AB16: 656355 | AD16: =(Z16-I16)/I16 -> 9.586371 | AE16: =(Z16-I16)/10 -> 59435.5 | AJ16: 1015673.6 | AU16: 401K
A17: Fidelity | B17: 0 | C17: 0 | D17: 0 | E17: 0 | F17: 0 | G17: 0 | H17: 0 | I17: 0 | J17: 5400 | K17: 5200 | L17: 6000 | M17: 7429 | N17: 7822 | O17: 7158 | P17: 8418 | Q17: 8922 | R17: 7500 | S17: 9072 | T17: 17700 | U17: 0 | V17: 7500 | W17: 700 | X17: 900 | Z17: 9072 | AA17: 0 | AB17: 0 | AC17: 0 | AD17: - | AE17: =(Z17-I17)/10 -> 907.2
A18: Funds/Stocks | B18: 0 | C18: 2400 | D18: 2200 | E18: 2200 | F18: 2200 | G18: 2281 | H18: 1700 | I18: 2050 | J18: 1900 | K18: 1950 | L18: 2000 | M18: 3194 | N18: 0 | O18: 0 | P18: 27513 | Q18: 30000 | R18: 35000 | S18: 35000 | T18: 42862 | U18: 48000 | V18: 45000 | W18: 48000 | X18: 78000 | Z18: 35000 | AA18: 0 | AB18: 447000 | AC18: 0 | AD18: =(Z18-I18)/I18 -> 16.073171 | AE18: =(Z18-I18)/10 -> 3295 | AU18: EMC | AV18: 12407.78
A19: 529 Plan | B19: 0 | C19: 0 | D19: 0 | E19: 0 | F19: 0 | G19: 0 | H19: 0 | I19: 400 | J19: 6400 | K19: 22000 | L19: 40000 | M19: =18714 + 52331 + 219 -> 71264 | N19: =36533 + 63300 + 239 -> 100072 | O19: 119513 | P19: 151516 | Q19: 209680 | R19: 214500 | S19: =159400 + 137000 -> 296400 | T19: =189400 + 161400 -> 350800 | U19: =227000 + 192000 -> 419000 | V19: 415000 | W19: =227100.18 + 191000 -> 418100.18 | X19: =221100.18 + 266000 -> 487100.18 | Z19: =159400 + 137000 -> 296400 | AA19: =159400 + 137000 -> 296400 | AB19: =227000 + 192000 -> 419000 | AD19: =(Z19-I19)/I19 -> 740 | AE19: =(Z19-I19)/10 -> 29600 | AU19: Scality | AV19: 6522.14
A20: T-Bills/Bonds | B20: 0 | C20: 0 | D20: 0 | E20: 0 | F20: 1042 | G20: 1050 | H20: 6057 | I20: 6400 | J20: 6400 | K20: 11672 | L20: 21672 | M20: =L20 -> 21672 | N20: 23068 | O20: 23313 | P20: 23642 | Q20: 23168 | R20: 23068 | S20: 29500 | T20: 30000 | U20: 40000 | V20: 63068 | W20: 215000 | X20: 225000 | Z20: 29500 | AA20: 29500 | AB20: 40000 | AD20: =(Z20-I20)/I20 -> 3.609375 | AE20: =(Z20-I20)/10 -> 2310
A21: Retirement Accounts | B21: =SUM(B22:B25) -> 1000 | C21: =SUM(C22:C25) -> 10300 | D21: =SUM(D22:D25) -> 26300 | E21: =SUM(E22:E25) -> 44554 | F21: =SUM(F22:F25) -> 73236 | G21: =SUM(G22:G25) -> 87000 | H21: =SUM(H22:H25) -> 70000 | I21: =SUM(I22:I25) -> 151000 | ... X21: =SUM(X22:X25) -> 1297920 | Z21: =SUM(Z22:Z25) -> 1285208 | AA21: =SUM(AA22:AA25) -> 1285208 | AB21: =SUM(AB22:AB25) -> 1581500 | AC21: =(R21-O21)/O21 -> 0.65464153 | AD21: =(Z21-I21)/I21 -> 7.5113113 | AE21: =(Z21-I21)/10 -> 113420.8 | AU21: After Tax
A22: 401K -R | B22: 0 | C22: 6800 | D22: 16000 | E22: 25000 | F22: 39452 | G22: 43000 | H22: 35000 | I22: 76000 | J22: 115000 | K22: 124165 | L22: 167229 | M22: 238869 | N22: 274827 | O22: 309828 | P22: 386453 | Q22: 446484 | R22: 16900 | S22: 42500 | T22: 76700 | U22: 115000 | V22: 142500 | W22: 167712.87 | X22: 220000 | Z22: 42500 | AA22: 42500 | AB22: 42500 | AD22: =(Z22-I22)/I22 -> -0.44078947 | AE22: =(Z22-I22)/10 -> -3350 | AU22: EMC | AV22: 5592
A23: 401K -S | B23: 1000 | C23: 3500 | D23: 10300 | E23: 19554 | F23: 33784 | G23: 44000 | H23: 35000 | I23: 75000 | J23: 112000 | K23: 122199 | L23: 163784 | M23: 236528 | N23: 276020 | O23: 316000 | P23: 386301 | Q23: 483000 | R23: 31600 | S23: =7800 + 63168 -> 70968 | T23: 122568 | U23: 199000 | V23: 199000 | W23: 280806.68 | X23: 391000 | Z23: =7800 + 63168 -> 70968 | AA23: =7800 + 63168 -> 70968 | AB23: 199000 | AD23: =(Z23-I23)/I23 -> -0.05376 | AE23: =(Z23-I23)/10 -> -403.2 | AU23: Scality
A24: Trad + Roth IRA - R | B24: 0 | C24: 0 | D24: 0 | E24: 0 | F24: 0 | G24: 0 | H24: 0 | I24: 0 | J24: 0 | K24: 0 | L24: 0 | M24: 0 | N24: 0 | O24: 0 | P24: 16119 | Q24: 83292 | R24: 503521 | S24: =507340 + 96400 -> 603740 | T24: 676000 | U24: =639000 + 133000 -> 772000 | V24: =639000 + 133000 -> 772000 | W24: =583729.6 + 132965.26 -> 716694.86 | X24: 633910 | Z24: =507340 + 96400 -> 603740 | AA24: =507340 + 96400 -> 603740 | AB24: =639000 + 133000 -> 772000 | AD24: - | AE24: =(Z24-I24)/10 -> 60374
A25: Trad + Roth IRA -S | B25: 0 | C25: 0 | D25: 0 | E25: 0 | F25: 0 | G25: 0 | H25: 0 | I25: 0 | J25: 0 | K25: 0 | L25: 0 | M25: 0 | N25: 0 | O25: 0 | P25: 23353 | Q25: 33758 | R25: 483500 | S25: =537000 + 31000 -> 568000 | T25: =585500 + 37700 -> 623200 | U25: 45000 | V25: =537000 + 31000 -> 568000 | W25: 44180.53 | X25: 53010 | Z25: =537000 + 31000 -> 568000 | AA25: =537000 + 31000 -> 568000 | AB25: =537000 + 31000 -> 568000 | AD25: - | AE25: =(Z25-I25)/10 -> 56800 | AV25: =SUM(AV19:AV24) -> 12114.14
A26: Net Worth | B26: =B28-B29 -> -2700 | C26: =C28-C29 -> 38927 | D26: =D28-D29 -> 96627 | E26: =E28-E29 -> 139210 | F26: =F28-F29 -> 223516 | G26: =G28-G29 -> 301083 | H26: =H28-H29 -> 272506 | I26: =I28-I29 -> 421750 | ... X26: =X28-X29 -> 4399442.8 | Z26: =Z28-Z29 -> 3325935 | AA26: =AA28-AA29 -> 2578108 | AB26: =AB28-AB29 -> 3488855 | AC26: =(R26-O26)/O26 -> 0.78070883 | AD26: =(Z26-I26)/I26 -> 6.8860344 | AE26: =(Z26-I26)/10 -> 290418.5
A27: NR Assets | B27: =B10+ B13 -> 33800 | C27: =C10+C13 -> 58627 | D27: =D10+D13 -> 74627 | E27: =E10 + E13 -> 95268 | F27: =F10 + F13 -> 150280 | G27: =G10 + G13 -> 227583 | H27: =H10 + H13 -> 202506 | I27: =I10+ I13 -> 288250 | J27: =J10+J13 -> 381803 | K27: =K10+K13 -> 457175 | L27: =L10 + L13 -> 520577 | M27: =M10 + M13 -> 686552 | N27: =N10 + N13 -> 869991 | O27: =O10 + O13 -> 898579 | P27: =P10 + P13 -> 1202149 | Q27: =Q10 + Q13 -> 1574706 | R27: =R10 + R13 -> 1691504 | S27: =S10 + S13 -> 2050727 | ... X27: =X10 + X13 -> 3131522.8 | Z27: =Z10 + Z13 -> 2050727 | AA27: =AA10 + AA13 -> 1302900 | AB27: =AB10 + AB13 -> 1917355 | AD27: =(Z27-I27)/I27 -> 6.1144042 | AE27: =(Z27-I27)/10 -> 176247.7
A28: Net Assets | B28: =B10+B21+B13 -> 34800 | C28: =C10+C21+C13 -> 68927 | D28: =D10+D21+D13 -> 100927 | E28: =E10+E21+E13 -> 139822 | F28: =F10+F21+F13 -> 223516 | G28: =G10+G21+G13 -> 314583 | H28: =H10+H21+H13 -> 272506 | I28: =I10+I21+I13 -> 439250 | ... X28: =X10+X21+X13 -> 4429442.8 | Z28: =Z10+Z21+Z13 -> 3335935 | AA28: =AA10+AA21+AA13 -> 2588108 | AB28: =AB10+AB21+AB13 -> 3498855 | AD28: =(Z28-I28)/I28 -> 6.5946158 | AE28: =(Z28-I28)/10 -> 289668.5
A29: Debt | B29: 37500 | C29: 30000 | D29: 4300 | E29: 612 | F29: 0 | G29: 13500 | H29: 0 | I29: 17500 | J29: 17500 | K29: 12500 | L29: 0 | M29: 0 | N29: 0 | O29: 0 | P29: 9209 | Q29: 10900 | R29: 12500 | S29: 10900 | T29: 15000 | U29: 11000 | V29: 10900 | W29: 60000 | X29: 30000 | Z29: 10000 | AA29: 10000 | AB29: 10000 | AD29: =(Z29-I29)/I29 -> -0.42857143 | AE29: -
A30: Home
A31: Home Ownership | B31: 0 | C31: 0 | D31: 0.010230918 | E31: 0.040341832 | F31: 0.073463644 | G31: 0.1173 | H31: 0.063926789 | I31: -0.14693035 | J31: 0 | K31: -0.096293153 | L31: -0.068697073 | M31: 0.010600279 | N31: 0.010600279 | O31: 0.010600279 | P31: 0 | Q31: 0 | R31: 0 | S31: =S32/300500 -> 0 | T31: =T34/3267379 -> 0.72584448 | U31: =U34/3267379 -> 0.71059097 | V31: =V34/3267379 -> 0.69355223 | W31: =W34/3267379 -> 0.67608159 | X31: =X34/3267379 -> 0.67608159 | Z31: 0 | AA31: 0.25 | AB31: 0.25 | AD31: - | AE31: =(Z31-I31)/10 -> 0.014693035
A32: Home Equity | B32: 0 | C32: 0 | D32: 3074.3907 | E32: 12122.72 | F32: 22075.825 | G32: 31799.357 | H32: 19210 | I32: -44152.571 | J32: -36763.754 | K32: -28936.093 | L32: -20643.47 | M32: 3185.3837 | N32: 3185.3837 | O32: 3185.3837 | P32: 0 | Q32: 0 | R32: 0 | S32: =R32 -> 0 | T32: =3267379-T34 -> 895770 | U32: =3267379-U34 -> 945609 | V32: =3267379-V34 -> 1001281 | W32: =3267379-W36 -> 1058364.2 | X32: =3267379-X36 -> 1058364.2 | Z32: 0 | AA32: 0 | AB32: 0 | AD32: - | AE32: -
A33: YoY Change | B33: --- | C33: --- | D33: ---- | E33: 2.9431294 | F33: 0.82102896 | G33: 0.44046064 | H33: -0.39589974 | I33: - | J33: - | K33: - | L33: - | M33: - | N33: 0 | O33: 0 | P33: -1 | Q33: 0 | R33: 0 | S33: 0 | T33: 0 | U33: 0 | V33: 0 | W33: 0 | X33: 0 | Z33: 0 | AA33: 0 | AB33: 0 | AD33: -
A34: Mortgage | B34: 0 | C34: 0 | D34: 297325.61 | E34: 288277.28 | F34: 278324.17 | G34: 268600.64 | H34: 255790 | I34: 249152.57 | J34: 241763.75 | K34: 233936.09 | L34: 225643.47 | M34: 201814.62 | N34: 197000 | O34: 197000 | P34: 0 | Q34: 0 | R34: 0 | S34: =S36+S37 -> 0 | T34: 2371609 | U34: =SUM(U36+U37) -> 2321770 | V34: =V36+V37 -> 2266098 | W34: =W36+W37 -> 2209014.8 | X34: =X36+X37 -> 2209014.8 | Z34: 0 | AA34: 0 | AB34: 0 | AC34: =(R34-O34)/O34 -> -1 | AD34: =(Z34-I34)/I34 -> -1 | AE34: =(Z34-I34)/10 -> -24915.257
A35: YoY Change | E35: -0.030432393 | F35: -0.03452615 | G35: -0.034935995 | H35: -0.047694014 | I35: -0.025948744 | J35: -0.02965579 | K35: -0.032377318 | L35: -0.035448237 | M35: -0.105604 | N35: -0.023856628 | O35: 0 | P35: -1 | Q35: - | R35: - | S35: - | T35: - | U35: - | V35: - | W35: - | X35: - | Z35: - | AA35: - | AB35: - | AD35: - | AE35: -
A36: Mortgage 1 | B36: 0 | C36: 0 | D36: 238579.07 | E36: 235042.72 | F36: 230519.01 | G36: 226559.74 | H36: 218784.9 | I36: 215752.76 | J36: 212549.59 | K36: 209165.73 | L36: 205590.99 | M36: 201814.62 | N36: 197000 | O36: 197000 | P36: 0 | Q36: 0 | R36: 0 | S36: 0 | T36: 2371609 | U36: 2321770 | V36: 2266098 | W36: 2209014.8 | X36: 2209014.8 | Z36: 0 | AA36: 2435000 | AB36: 2435000 | AD36: - | AE36: -
A37: Mortgage 2 | B37: 0 | C37: 0 | D37: 58746.538 | E37: 53234.556 | F37: 47805.166 | G37: 42040.902 | H37: 37342.287 | I37: 33399.809 | J37: 29214.167 | K37: 24770.363 | L37: 20052.476 | M37: 0 | N37: 0 | O37: 0 | P37: 0 | Q37: 0 | R37: 0 | S37: 0 | T37: 0 | U37: 0 | V37: 0 | W37: 0 | X37: 0 | Z37: 0 | AA37: 0 | AB37: 0
A38: Net Worth **** | B38: =B26+B32 -> -2700 | C38: =C26+C32 -> 38927 | D38: =D26+D32 -> 99701.391 | E38: =E26+E32 -> 151332.72 | F38: =F26+F32 -> 245591.83 | G38: =G26+G32 -> 332882.36 | H38: =H26+H32 -> 291716 | I38: =I26+I32 -> 377597.43 | ... X38: =X26+X32 -> 5457807 | Z38: =Z26+Z32 -> 3325935 | AA38: =AA26+AA32 -> 2578108 | AB38: =AB26+AB32 -> 3488855 | AC38: =(R38-O38)/O38 -> 0.77699564 | AD38: =(Z38-I38)/I38 -> 7.8081505 | AE38: =(Z38-I38)/10 -> 294833.76 | AH38: =663901-T42 -> 385984.4
A39: YoY Change | C39: =(C38-B38) -> 41627 | D39: =(D38-C38) -> 60774.391 | E39: =(E38-D38) -> 51631.33 | F39: =(F38-E38) -> 94259.105 | G39: =(G38-F38) -> 87290.532 | H39: =(H38-G38) -> -41166.357 | I39: =(I38-H38) -> 85881.429 | J39: =(J38-I38) -> 176941.82 | ... V39: =(V38-U38) -> 198369 | W39: =(W38-U39) -> 5166159 | X39: =(X38-V38) -> 1299829 | Z39: =(Z38-X38) -> -2131872 | AA39: =(AA38-Z38) -> -747827 | AB39: =(AB38-AA38) -> 910747 | AD39: =(Z39-I39)/I39 -> -25.823434 | AE39: =(Z39-I39)/10 -> -221775.34
A40: YoY Change (%) | B40: --- | C40: =(C38-B38)/B38 -> -15.417407 | D40: =(D38-C38)/C38 -> 1.56124 | E40: =(E38-D38)/D38 -> 0.51785967 | F40: =(F38-E38)/E38 -> 0.62286004 | G40: =(G38-F38)/F38 -> 0.35542931 | H40: =(H38-G38)/G38 -> -0.12366638 | I40: =(I38-H38)/H38 -> 0.29440082 | J40: =(J38-I38)/I38 -> 0.4685991 | ... V40: =(V38-U38)/U38 -> 0.050098128 | W40: =(W38-U39)/U39 -> 85.536683 | X40: =(X38-V38)/V38 -> 0.31261083 | Z40: =(Z38-X38)/X38 -> -0.39060963 | AA40: =(AA38-Z38)/Z38 -> -0.22484715 | AB40: =(AB38-AA38)/AA38 -> 0.35326177
A41: Income
A42: Income R | B42: 72015.84 | C42: 72883 | D42: 78693 | E42: 80432 | F42: 92844 | G42: 102510 | H42: 107237 | I42: 126931 | J42: 123458.78 | K42: 131775 | L42: 139708 | M42: 143728 | N42: 153511 | O42: 179905 | P42: 217425 | Q42: 323386 | R42: 245200 | S42: 245735 | T42: 277916.6 | U42: 306582.43 | V42: =280458.32+ 64928.5 -> 345386.82 | W42: 519947.38 | X42: 519947.38 | Z42: 245735 | AA42: 245200 | AB42: 245200 | AC42: =(R42-O42)/O42 -> 0.36294155 | AD42: =(S42-P42)/P42 -> 0.13020582 | AE42: =(T42-Q42)/Q42 -> -0.14060411
A43: YoY | B43: =(B42-49315-3000)/(49315+3000) -> 0.3765811 | C43: =(C42-B42)/B42 -> 0.01204124 | D43: =(D42-C42)/C42 -> 0.079716806 | E43: =(E42-D42)/D42 -> 0.022098535 | F43: =(F42-E42)/E42 -> 0.15431669 | G43: =(G42-F42)/F42 -> 0.10411012 | H43: =(H42-G42)/G42 -> 0.046112574 | I43: =(I42-H42)/H42 -> 0.1836493 | J43: =(J42-I42)/I42 -> -0.027355177 | ... W43: =(W42-V42)/V42 -> 0.50540597 | X43: =(X42-V42)/V42 -> 0.50540597 | Z43: =(Z42-X42)/X42 -> -0.52738487 | AA43: =(AA42-Z42)/Z42 -> -0.002177142 | AB43: =(AB42-AA42)/AA42 -> 0
A44: CAGR | B44: =POWER(B42/72000, 1/B9)-1 -> 0.00022 | C44: =POWER(C42/72000, 1/C9)-1 -> 0.0061132585 | D44: =POWER(D42/72000, 1/D9)-1 -> 0.030072679 | E44: =POWER(E42/72000, 1/E9)-1 -> 0.02807333 | F44: =POWER(F42/72000, 1/F9)-1 -> 0.052166013 | G44: =POWER(G42/72000, 1/G9)-1 -> 0.060650472 | H44: =POWER(H42/72000, 1/H9)-1 -> 0.058561325 | I44: =POWER(I42/72000, 1/I9)-1 -> 0.073444019 | ... X44: =POWER(X42/72000, 1/X9)-1 -> 0.08976186 | Z44: =POWER(Z42/72000, 1/Z9)-1 -> 0.070578665 | AA44: =POWER(AA42/72000, 1/AA9)-1 -> 0.070449043 | AB44: =POWER(AB42/72000, 1/AB9)-1 -> 0.041692648
A45: Income S | B45: 44442 | C45: 65729 | D45: 67442 | E45: 79608 | F45: 90760 | G45: 93773 | H45: 97767 | I45: 86678 | J45: 110788 | K45: 110000 | L45: 116037 | M45: 132572 | N45: 141359 | O45: 162697 | P45: 168200 | Q45: 230386 | R45: 276835 | S45: =170906 + 116873 -> 287779 | T45: 276835 | U45: 278512.23 | V45: 411915.6 | W45: 463790.18 | X45: 463790.18 | Z45: 276835 | AA45: 276835 | AB45: 276835 | AC45: =(R45-O45)/O45 -> 0.70153721 | AD45: =(S45-P45)/P45 -> 0.71093341 | AE45: =(T45-Q45)/Q45 -> 0.20161381
A46: YoY | B46: =(B45-20000)/(20000) -> 1.2221 | C46: =(C45-B45)/B45 -> 0.47898384 | D46: =(D45-C45)/C45 -> 0.026061556 | E46: =(E45-D45)/D45 -> 0.18039204 | F46: =(F45-E45)/E45 -> 0.14008642 | G46: =(G45-F45)/F45 -> 0.033197444 | H46: =(H45-G45)/G45 -> 0.042592217 | I46: =(I45-H45)/H45 -> -0.11342273 | J46: =(J45-I45)/I45 -> 0.27815593 | ... W46: =(W45-V45)/V45 -> 0.12593497 | X46: =(X45-V45)/V45 -> 0.12593497 | Z46: =(Z45-X45)/X45 -> -0.40310293 | AA46: =(AA45-Z45)/Z45 -> 0 | AB46: =(AB45-AA45)/AA45 -> 0
A47: CAGR | B47: --- | C47: =POWER(C42/65000, 1/(C9-1))-1 -> 0.12127692 | D47: =POWER(D42/65000, 1/(D9-1))-1 -> 0.10030066 | E47: =POWER(E42/65000, 1/(E9-1))-1 -> 0.073590114 | F47: =POWER(F42/65000, 1/(F9-1))-1 -> 0.093226427 | G47: =POWER(G42/65000, 1/(G9-1))-1 -> 0.095394549 | H47: =POWER(H42/65000, 1/(H9-1))-1 -> 0.087022541 | I47: =POWER(I42/65000, 1/(I9-1))-1 -> 0.10032771 | J47: =POWER(J42/65000, 1/(J9-1))-1 -> 0.083492921 | ... X47: =POWER(X42/65000, 1/(X9-1))-1 -> 0.099126167 | Z47: =POWER(Z42/65000, 1/(Z9-1))-1 -> 0.081368575 | AA47: =POWER(AA42/65000, 1/(AA9-1))-1 -> 0.081229945 | AB47: =POWER(AB42/65000, 1/(AB9-1))-1 -> 0.046846496
A48: Interest Income | B48: 309 | C48: 589 | D48: 826 | E48: 1393 | F48: 2451 | G48: 3788 | H48: 2497 | I48: 2742 | J48: 1599 | K48: 764 | L48: 824 | M48: 653 | N48: 1045 | O48: 1522 | P48: 2640 | Q48: 6126 | R48: 11198 | S48: 17896 | T48: 5523 | U48: 1768 | V48: 3788 | W48: 13162 | X48: 13162 | Z48: 17896 | AA48: 11198 | AB48: 11198
A49: YoY Change | B49: --- | C49: =(C48-B48)/B48 -> 0.90614887 | D49: =(D48-C48)/C48 -> 0.40237691 | E49: =(E48-D48)/D48 -> 0.68644068 | F49: =(F48-E48)/E48 -> 0.75951184 | G49: =(G48-F48)/F48 -> 0.54549164 | H49: =(H48-G48)/G48 -> -0.34081309 | I49: =(I48-H48)/H48 -> 0.098117741 | J49: =(J48-I48)/I48 -> -0.41684902 | ... W49: =(W48-V48)/V48 -> 2.4746568 | X49: =(X48-V48)/V48 -> 2.4746568 | Z49: =(Z48-X48)/X48 -> 0.35967178 | AA49: =(AA48-Z48)/Z48 -> -0.37427358 | AB49: =(AB48-AA48)/AA48 -> 0
A50: Dividend Income | B50: 0 | C50: 0 | D50: 129 | E50: 162 | F50: 850 | G50: 1287 | H50: 1695 | I50: 1762 | J50: 2063 | K50: 3696 | L50: 4272 | M50: 6413 | N50: 8820 | O50: 9848 | P50: 11811 | Q50: 8359 | R50: 13028 | S50: 14960 | T50: 13419 | U50: 17143 | V50: 1287 | W50: 21771 | X50: 21771 | Z50: 14960 | AA50: 13028 | AB50: 13028
A51: Real. Investment Gains | B51: 0 | C51: 0 | D51: 0 | E51: 0 | F51: 0 | G51: 0 | H51: -11723 | I51: 1550 | J51: 3371 | K51: -3386 | L51: 2420 | M51: 2472 | N51: 4737 | O51: -2639 | P51: 32862 | Q51: -15 | R51: -15 | S51: -389 | T51: 18679 | U51: -15 | V51: -15 | W51: 3841 | X51: 3841 | Z51: -389 | AA51: -15 | AB51: -15
A52: Inc (Div,Int,Gains) | B52: =B48+B50+B51 -> 309 | C52: =C48+C50+C51 -> 589 | D52: =D48+D50+D51 -> 955 | E52: =E48+E50+E51 -> 1555 | F52: =F48+F50+F51 -> 3301 | G52: =G48+G50+G51 -> 5075 | H52: =H48+H50+H51 -> -7531 | I52: =I48+I50+I51 -> 6054 | ... M52: =M48+M50+M51 -> 9538 | N52: 2049 | O52: =O48+O50+O51 -> 8731 | P52: =P48+P50+P51 -> 47313 | Q52: =Q48+Q50+Q51 -> 14470 | R52: =R48+R50+R51 -> 24211 | S52: =S48+S50+S51 -> 32467 | T52: =T48+T50+T51 -> 37621 | U52: =U48+U50+U51 -> 18896 | V52: =V48+V50+V51 -> 5060 | ... X52: =X48+X50+X51 -> 38774 | Z52: =Z48+Z50+Z51 -> 32467 | AA52: =AA48+AA50+AA51 -> 24211 | AB52: =AB48+AB50+AB51 -> 24211
A53: Other Income | B53: =B54+B55 -> 0 | C53: =C54+C55 -> 0 | D53: =D54+D55 -> 0 | E53: =E54+E55 -> 0 | F53: =F54+F55 -> 0 | G53: =G54+G55 -> 0 | H53: =H54+H55 -> 0 | I53: =I54+I55 -> 0 | ... Q53: =Q54+Q55 -> 79014 | R53: 0 | S53: 2700 | T53: 0 | U53: 0 | W53: 0 | Z53: 0 | AA53: 0 | AB53: 0
A54: R | B54: 0 | C54: 0 | D54: 0 | E54: 0 | F54: 0 | G54: 0 | H54: 0 | I54: 0 | J54: 0 | K54: 0 | L54: 0 | M54: 0 | N54: 0 | O54: 0 | P54: 0 | Q54: 79014 | R54: 0 | S54: 0 | T54: 0 | U54: 0 | Z54: 0 | AA54: 0 | AB54: 0
A55: S | B55: 0 | C55: 0 | D55: 0 | E55: 0 | F55: 0 | G55: 0 | H55: 0 | I55: 0 | J55: 0 | K55: 0 | L55: 0 | M55: 0 | N55: 0 | O55: 0 | P55: 0 | Q55: 0 | R55: 0 | S55: 0 | T55: 0 | U55: 0 | Z55: 0 | AA55: 0 | AB55: 0
A56: YoY Change | B56: --- | C56: =(C52-B52)/B52 -> 0.90614887 | D56: =(D52-C52)/C52 -> 0.62139219 | E56: =(E52-D52)/D52 -> 0.62827225 | F56: =(F52-E52)/E52 -> 1.1228296 | G56: =(G52-F52)/F52 -> 0.53741291 | H56: =(H52-G52)/G52 -> -2.4839409 | I56: =(I52-(ABS(H52))/ABS(H52)) -> 6053 | J56: =(J52-I52)/I52 -> 0.16171127 | K56: =(K52-J52)/J52 -> -0.84729134 | L56: =(L52-K52)/K52 -> 5.9981378 | M56: =(M52-L52)/L52 -> 0.26902608 | N56: =(N52-M52)/M52 -> -0.78517509 | O56: =(O52-N52)/N52 -> 3.261103 | P56: =(P52-O52)/O52 -> 4.4189669 | Q56: =(Q52-P52)/P52 -> -0.69416439 | ... V56: =(V52-U52)/U52 -> -0.73221846 | W56: =(W52-V52)/W52 -> 0.86950018 | X56: =(X52-W52)/W52 -> 0 | Z56: =(Z52-X52)/X52 -> -0.16266055 | AA56: =(AA52-Z52)/Z52 -> -0.25428897 | AB56: =(AB52-AA52)/AA52 -> 0
A57: RSUs - RDP | N57: 10471 | O57: 11237 | P57: 171319 | Q57: 182908 | R57: 0 | S57: 0 | T57: 0 | U57: 0 | Z57: 0 | AA57: 0 | AB57: 0
A58: RSUs - SRP | N58: 13547 | O58: 14623 | P58: 21053 | Q58: 5000 | R58: 0 | S58: 0 | T58: 0 | U58: 141018.79 | W58: 155325.01 | Z58: 0 | AA58: 0 | AB58: 0
A59: Total RSU Income | B59: =B57+B58 -> 0 | C59: =C57+C58 -> 0 | D59: =D57+D58 -> 0 | E59: =E57+E58 -> 0 | F59: =F57+F58 -> 0 | G59: =G57+G58 -> 0 | H59: =H57+H58 -> 0 | I59: =I57+I58 -> 0 | ... Q59: =Q57+Q58 -> 187908 | R59: 0 | S59: 0 | T59: =T57+T58 -> 0 | U59: =U57+U58 -> 141018.79 | W59: 0 | Z59: 0 | AA59: =AA57+AA58 -> 0 | AB59: =AB57+AB58 -> 0
A60: Income from Earnings | B60: =B42+B45+B53 -> 116457.84 | C60: =C42+C45+C53 -> 138612 | D60: =D42+D45+D53 -> 146135 | E60: =E42+E45+E53 -> 160040 | F60: =F42+F45+F53 -> 183604 | G60: =G42+G45+G53 -> 196283 | H60: =H42+H45+H53 -> 205004 | I60: =I42+I45+I53 -> 213609 | ... P60: =P42+P45+P53 -> 385625 | Q60: =Q42+Q45+Q53+Q59 -> 820694 | R60: =R42+R45 -> 522035 | S60: =S42+S45 -> 533514 | T60: =T42+T45 -> 554751.6 | U60: =U42+U45 -> 585094.66 | V60: =V42+V45 -> 757302.42 | W60: =W42+W45 -> 983737.56 | X60: =X42+X45 -> 983737.56 | Z60: =Z42+Z45 -> 522570 | AA60: =AA42+AA45 -> 522035 | AB60: =AB42+AB45 -> 522035 | AC60: =(R60-O60)/O60 -> 0.523736 | AD60: =(S60-P60)/P60 -> 0.3835047 | AE60: =(T60-Q60)/Q60 -> -0.32404575
A61: YoY Change | B61: ---- | C61: =(C60-B60)/B60 -> 0.19023331 | D61: =(D60-C60)/C60 -> 0.0542738 | E61: =(E60-D60)/D60 -> 0.095151743 | F61: =(F60-E60)/E60 -> 0.14723819 | G61: =(G60-F60)/F60 -> 0.06905623 | H61: =(H60-G60)/G60 -> 0.044430745 | I61: =(I60-H60)/H60 -> 0.041974791 | J61: =(J60-I60)/I60 -> 0.096614749 | ... W61: =(W60-V60)/V60 -> 0.29900227 | X61: =(X60-V60)/V60 -> 0.29900227 | Z61: =(Z60-X60)/X60 -> -0.46879125 | AA61: =(AA60-Z60)/Z60 -> -0.0010237863 | AB61: =(AB60-AA60)/AA60 -> 0
A62: CAGR | B62: --- | C62: =POWER(C60/137000, 1/C9)-1 -> 0.0058660067 | D62: =POWER(D60/137000, 1/D9)-1 -> 0.021749794 | E62: =POWER(E60/137000, 1/E9)-1 -> 0.039625669 | F62: =POWER(F60/137000, 1/F9)-1 -> 0.060308674 | G62: =POWER(G60/137000, 1/G9)-1 -> 0.061761614 | H62: =POWER(H60/137000, 1/H9)-1 -> 0.059268279 | I62: =POWER(I60/137000, 1/I9)-1 -> 0.057090993 | J62: =POWER(J60/137000, 1/J9)-1 -> 0.061411219 | ... X62: =POWER(X60/137000, 1/X9)-1 -> 0.089492615 | Z62: =POWER(Z60/137000, 1/Z9)-1 -> 0.077212361 | AA62: =POWER(AA60/137000, 1/AA9)-1 -> 0.077151062 | AB62: =POWER(AB60/137000, 1/AB9)-1 -> 0.045600948
A63: Other Income (Relo) | B63: 0 | C63: 0 | D63: 0 | E63: 0 | F63: 0 | G63: 0 | H63: 0 | I63: 0 | J63: 0 | K63: 0 | L63: 0 | M63: 0 | N63: 0 | O63: 0 | P63: 103339 | Q63: 79014 | R63: 0 | S63: 0 | T63: 0 | U63: 0 | V63: 0 | W63: 0 | X63: 0 | Z63: 0 | AA63: 0 | AB63: 0
A64: Total Income | B64: =B60+B48+B50 -> 116766.84 | C64: =C60+C48+C50 -> 139201 | D64: =D60+D48+D50 -> 147090 | E64: =E60+E48+E50 -> 161595 | F64: =F60+F48+F50 -> 186905 | G64: =G60+G48+G50 -> 201358 | H64: =H60+H48+H50 -> 209196 | I64: =I60+I48+I50 -> 218113 | ... O64: =O60+O48+O50 -> 353972 | P64: =P48+P51+P50+P63+P60 -> 536277 | Q64: =Q48+Q51+Q50+Q63+Q60 -> 914178 | R64: =R48+R51+R50+R63+R60 -> 546246 | S64: =S48+S51+S50+S63+S60 -> 565981 | T64: =T48+T51+T50+T63+T60 -> 592372.6 | U64: =U48+U51+U50+U63+U60 -> 603990.66 | V64: =V48+V51+V50+V63+V60 -> 762362.42 | W64: =W48+W51+W50+W63+W60 -> 1022511.6 | X64: =X48+X51+X50+X63+X60 -> 1022511.6 | Z64: =Z48+Z51+Z50+Z63+Z60 -> 555037 | AA64: =AA48+AA51+AA50+AA63+AA60 -> 546246 | AB64: =AB48+AB51+AB50+AB63+AB60 -> 546246
A65: YoY Change | B65: --- | C65: =(C64-B64)/B64 -> 0.19212783 | D65: =(D64-C64)/C64 -> 0.056673443 | E65: =(E64-D64)/D64 -> 0.098613094 | F65: =(F64-E64)/E64 -> 0.15662613 | G65: =(G64-F64)/F64 -> 0.077328054 | H65: =(H64-G64)/G64 -> 0.038925695 | I65: =(I64-H64)/H64 -> 0.042625098 | J65: =(J64-I64)/I64 -> 0.090759285 | ... W65: =(W64-V64)/V64 -> 0.34124077 | X65: =(X64-V64)/V64 -> 0.34124077 | Z65: =(Z64-X64)/X64 -> -0.45718267 | AA65: =(AA64-Z64)/Z64 -> -0.015838584 | AB65: =(AB64-AA64)/AA64 -> 0
A66: CAGR | C66: =POWER(C64/137000, 1/C9)-1 -> 0.00800084 | D66: =POWER(D64/137000, 1/D9)-1 -> 0.023970693 | E66: =POWER(E64/137000, 1/E9)-1 -> 0.042141853 | F66: =POWER(F64/137000, 1/F9)-1 -> 0.064094186 | G66: =POWER(G64/137000, 1/G9)-1 -> 0.066288488 | H66: =POWER(H64/137000, 1/H9)-1 -> 0.062335831 | I66: =POWER(I64/137000, 1/I9)-1 -> 0.059851754 | J66: =POWER(J64/137000, 1/J9)-1 -> 0.063242215 | ... X66: =POWER(X64/137000, 1/X9)-1 -> 0.091325357 | Z66: =POWER(Z64/137000, 1/Z9)-1 -> 0.080825622 | AA66: =POWER(AA64/137000, 1/AA9)-1 -> 0.079867394 | AB66: =POWER(AB64/137000, 1/AB9)-1 -> 0.047182213
A67: Taxes - W2
A68: Fed Taxes R | B68: 12254 | C68: 13441 | D68: 13490 | E68: 16551 | F68: 15632 | G68: 14724 | H68: 16856.99 | I68: 22861 | J68: 22751 | K68: 24888 | L68: 27776 | M68: 30255 | N68: 32604 | O68: 36623 | P68: 117098 | Q68: 129844 | R68: 60817.99 | S68: 60817.99 | T68: 64922.95 | U68: 73543.88 | V68: 94262.98 | Z68: 60817.99 | AA68: 60817.99 | AB68: 60817.99
A69: Fed Taxes S | B69: 5067 | C69: 10791 | D69: 10259 | E69: 12925 | F69: 15247 | G69: 17628 | H69: 15125.51 | I69: 12694 | J69: 14911 | K69: 12958 | L69: 17596 | M69: 21898 | N69: 29827 | O69: 40036 | P69: 61599 | Q69: 69484 | R69: 74651 | S69: =44845 + 28069 -> 72914 | T69: 93508 | U69: 69484 | V69: 96062.96 | Z69: 74651 | AA69: 74651 | AB69: 74651
A70: State Taxes R | B70: 3377 | C70: 3465 | D70: 3608 | E70: 3680 | F70: 4283 | G70: 4429 | H70: 4518.79 | I70: 5633 | J70: 5563 | K70: 6004 | L70: 6550 | M70: 7064 | N70: 7493 | O70: 8225 | P70: 43418 | Q70: 52104 | R70: 20508 | S70: 20508 | T70: 20508 | U70: 25640.58 | V70: 33779.47 | Z70: 20508 | AA70: 20508 | AB70: 20508
A71: State Taxes S | B71: 1328 | C71: 3031 | D71: 2980 | E71: 3555 | F71: 4057 | G71: 4480 | H71: 4056 | I71: 3699 | J71: 4126 | K71: 3502 | L71: 4648 | M71: 5563 | N71: 6348 | O71: 7896 | P71: 18881 | Q71: 21596 | R71: 23607 | S71: =13740 + 11779 -> 25519 | T71: 40165 | U71: 21596 | V71: 40913.47 | Z71: 23607 | AA71: 23607 | AB71: 23607
A72: SSN R | B72: 4464 | C72: 4260 | D72: 4878 | E72: 4986 | F72: 5756 | G72: 6045 | H72: 6324 | I72: 7869 | J72: 6621 | K72: 4486 | L72: 4624 | M72: 7049 | N72: 7254 | O72: 7347 | P72: 7347 | Q72: 10502 | R72: 7960 | S72: 7960 | T72: 8537.4 | U72: 8864 | V72: 9114 | Z72: 7960 | AA72: 7960 | AB72: 7960
A73: SSN S | B73: 4073 | C73: 4465 | D73: 4073 | E73: 4831 | F73: 5663 | G73: 6045 | H73: 6182 | I73: 5373 | J73: 6317 | K73: 3737 | L73: 4624 | M73: 7049 | N73: 7254 | O73: 7347 | P73: 7347 | Q73: 14416 | R73: 7960 | S73: =8239 + 7486 -> 15725 | T73: 8537.4 | U73: 14416 | V73: 9114 | Z73: 7960 | AA73: 7960 | AB73: 7960
A74: Medicare R | B74: 1044 | C74: 996 | D74: 1141 | E74: 1166 | F74: 1346 | G74: 1511 | H74: 1555 | I74: 1840 | J74: 1791 | K74: 1913 | L74: 2085 | M74: 2236 | N74: 2375 | O74: 2609 | P74: 9749 | Q74: 9409 | R74: 3973 | S74: 3973 | T74: 4679.5 | U74: 5303 | V74: 7226.06 | Z74: 3973 | AA74: 3973 | AB74: 3973
A75: Medicare S | B75: 952 | C75: 1045 | D75: 952 | E75: 1129 | F75: 1324 | G75: 1554 | H75: 1446 | I75: 1255 | J75: 1478 | K75: 1290 | L75: 1638 | M75: 1898 | N75: 2123 | O75: 2580 | P75: 3379 | Q75: 3371 | R75: 4455 | S75: =2478+1694 -> 4172 | T75: 7948.51 | U75: 3371 | V75: 8361.77 | Z75: 4455 | AA75: 4455 | AB75: 4455
A76: Taxes - Actual
A77: Additional Taxes (Medicare) | B77: 0 | C77: 0 | D77: 0 | E77: 0 | F77: 0 | G77: 0 | H77: 0 | I77: 0 | J77: 0 | K77: 0 | L77: 0 | M77: 0 | N77: 0 | O77: 0 | P77: 2806 | Q77: 0 | R77: - | T77: - | Z77: - | AA77: - | AB77: -
A78: Fed Taxes | B78: 20828 | C78: 23124 | D78: 22624 | E78: 22937 | F78: 29354 | G78: 33313 | H78: 29276 | I78: 31878 | J78: 35312 | K78: 32994 | L78: 40350 | M78: 55597 | N78: 61767 | O78: 76492 | P78: =210359 - P77 -> 207553 | Q78: 215374 | R78: 136476 | S78: 136476 | T78: 136476 | U78: 215374 | V78: 215374 | Z78: 136476 | AA78: 136476 | AB78: 136476 | AC78: =(R78-O78)/O78 -> 0.78418658 | AD78: =(S78-P78)/P78 -> -0.34245229 | AE78: =(T78-Q78)/Q78 -> -0.3663302
A79: State Taxes | B79: =SUM(B70:B71) -> 4705 | C79: =SUM(C70:C71) -> 6496 | D79: =SUM(D70:D71) -28 -> 6560 | E79: =SUM(E70:E71) +164 -> 7399 | F79: =SUM(F70:F71) +250 -> 8590 | G79: 9597 | H79: 8755 | I79: 9546 | J79: 9843 | K79: 9586 | L79: 11080 | M79: 13353 | N79: 14238 | O79: 16178 | P79: 58151 | Q79: 9597 | R79: 41191 | S79: 41191 | T79: 41191 | U79: 9597 | V79: 9597 | Z79: 41191 | AA79: 41191 | AB79: 41191 | AC79: =(R79-O79)/O79 -> 1.546112 | AD79: =(S79-P79)/P79 -> -0.29165449 | AE79: =(T79-Q79)/Q79 -> 3.2920704
A80: Refund Fed | B80: =B68 + B69 - B78 -> -3507 | C80: =C68 + C69 - C78 -> 1108 | D80: =D68 + D69 - D78 -> 1125 | E80: =E68 + E69 - E78 -> 6539 | F80: =F68 + F69 - F78 -> 1525 | G80: =G68 + G69 - G78 -> -961 | H80: =H68 + H69 - H78 -> 2706.5 | I80: =I68 + I69 - I78 -> 3677 | ... O80: =O68 + O69 - O78 -> 167 | P80: =P68+P69 -P78 - P77 -> -31662 | Q80: 4185 | R80: 15764 | S80: 9156 | T80: -27899 | U80: -23718 | V80: =V68 + V69 - V78 -> -25048.06 | W80: =W68 + W69 - W78 -> 0 | X80: =X68 + X69 - X78 -> 0 | Z80: 15764 | AA80: 15764 | AB80: 15764
A81: Refund State | B81: =B70 + B71 - B79 -> 0 | C81: =C70 + C71 - C79 -> 0 | D81: =D70 + D71 - D79 -> 28 | E81: =E70 + E71 - E79 -> -164 | F81: =F70 + F71 - F79 -> -250 | G81: =G70 + G71 - G79 -> -688 | H81: =H70 + H71 - H79 -> -180.21 | I81: =I70 + I71 - I79 -> -214 | ... P81: =P70 + P71 - P79 -> 4148 | Q81: -2887 | R81: 2734 | S81: 2107 | T81: 2734 | U81: 13000 | V81: =V70 + V71 - V79 -> 65095.94 | W81: =W70 + W71 - W79 -> 0 | X81: =X70 + X71 - X79 -> 0 | Z81: 2734 | AA81: 2734 | AB81: 2734
A83: Total Income | B83: 116223 | C83: 133256 | D83: 137587 | E83: 151014 | F83: 173978 | G83: 193978 | H83: 177273 | I83: 196567 | J83: 212675 | K83: 203249 | L83: 233079 | M83: 275485 | N83: 193978 | O83: 193978 | P83: 728414 | Q83: 747241 | R83: =R64 -> 546246 | S83: =S64 -> 565981 | T83: =T64 -> 592372.6 | U83: 193978 | V83: 193978 | W83: 193978 | X83: 193978 | Z83: =Z64 -> 555037 | AA83: =AA64 -> 546246 | AB83: =AB64 -> 546246
A84: Taxable income | B84: 100117 | C84: 117656 | D84: 116648 | E84: 118456 | F84: 142910 | G84: 161745 | H84: 145038 | I84: 157457 | J84: 166850 | K84: 162070 | L84: 190756 | M84: 234437 | N84: 181900 | O84: 181900 | P84: 720361 | Q84: 674847 | R84: 505780 | S84: 505780 | T84: 505780 | U84: 181900 | V84: 181900 | W84: 181900 | X84: 181900 | Z84: 505780 | AA84: 505780 | AB84: 505780
A85: Total Taxes | B85: =SUM(B68:B75) + SUM(B80:B81) -> 29052 | C85: =SUM(C68:C75) + SUM(C80:C81) -> 42602 | D85: =SUM(D68:D75) + SUM(D80:D81) -> 42534 | E85: =SUM(E68:E75) + SUM(E80:E81) -> 55198 | F85: =SUM(F68:F75) + SUM(F80:F81) -> 54583 | G85: =SUM(G68:G75) + SUM(G80:G81) -> 54767 | H85: =SUM(H68:H75) + SUM(H80:H81) -> 58590.58 | I85: =SUM(I68:I75) + SUM(I80:I81) -> 64687 | ... Q85: =SUM(Q68:Q75) + SUM(Q80:Q81) -> 312024 | R85: =SUM(R72:R79) -> 202015 | S85: =SUM(S72:S79) -> 209497 | T85: =SUM(T72:T79) -> 207369.81 | U85: 192614 | V85: =SUM(V72:V79) -> 258786.83 | W85: =SUM(W72:W79) -> 0 | X85: =SUM(X72:X79) -> 0 | Z85: =SUM(Z72:Z79) -> 202015 | AA85: =SUM(AA72:AA79) -> 202015 | AB85: =SUM(AB72:AB79) -> 202015 | AC85: =(R85-O85)/O85 -> 0.7913419 | AD85: =(S85-P85)/P85 -> -0.13181298 | AE85: =(T85-Q85)/Q85 -> -0.3354043
A86: YoY Change | B86: --- | C86: =(C85-B85)/B85 -> 0.46640507 | D86: =(D85-C85)/C85 -> -0.0015961692 | E86: =(E85-D85)/D85 -> 0.29773828 | F86: =(F85-E85)/E85 -> -0.011141708 | G86: =(G85-F85)/F85 -> 0.003371013 | H86: =(H85-G85)/G85 -> 0.0698154 | I86: =(I85-H85)/H85 -> 0.1040512 | J86: =(J85-I85)/I85 -> 0.016494813 | ... V86: =(V85-U85)/U85 -> 0.34355151 | W86: =(W85-U86)/U86 -> -1 | X86: =(X85-V85)/V85 -> -1 | Z86: =(Z85-X85)/X85 -> #DIV/0! | AA86: =(AA85-Z85)/Z85 -> 0 | AB86: =(AB85-AA85)/AA85 -> 0
A87: Effective Tax Rate | B87: =B85/B64 -> 0.24880351 | C87: =C85/C64 -> 0.30604665 | D87: =D85/D64 -> 0.2891699 | E87: =E85/E64 -> 0.34158235 | F87: =F85/F64 -> 0.29203606 | G87: =G85/G64 -> 0.2719882 | H87: =H85/H64 -> 0.28007505 | I87: =I85/I64 -> 0.29657563 | ... X87: =X85/X64 -> 0 | Z87: =Z85/Z64 -> 0.36396673 | AA87: =AA85/AA64 -> 0.36982422 | AB87: =AB85/AB64 -> 0.36982422
A88: Effective Tax Rate on Earnings | I88: =I85/I60 -> 0.302829 | J88: =J85/J60 -> 0.28070397 | K88: =K85/K60 -> 0.26284769 | L88: =L85/L60 -> 0.29201353 | M88: =M85/M60 -> 0.28534926 | N88: =N85/N60 -> 0.32402415 | O88: =O85/O60 -> 0.3291662 | P88: =P85/P60 -> 0.62574781 | ... X88: =X85/X60 -> 0 | Z88: =Z85/Z60 -> 0.38657979 | AA88: =AA85/AA60 -> 0.38697597 | AB88: =AB85/AB60 -> 0.38697597
A89: Earned Income After Taxes | B89: =B60-B85 -> 87405.84 | C89: =C60-C85 -> 96010 | D89: =D60-D85 -> 103601 | E89: =E60-E85 -> 104842 | F89: =F60-F85 -> 129021 | G89: =G60-G85 -> 141516 | H89: =H60-H85 -> 146413.42 | I89: =I60-I85 -> 148922 | ... X89: =X60-X85 -> 983737.56 | Z89: =Z60-Z85 -> 320555 | AA89: =AA60-AA85 -> 320020 | AB89: =AB60-AB85 -> 320020
A90: YoY Change | B90: --- | C90: =(C89-B89)/B89 -> 0.098439189 | D90: =(D89-C89)/C89 -> 0.079064681 | E90: =(E89-D89)/D89 -> 0.011978649 | F90: =(F89-E89)/E89 -> 0.23062322 | G90: =(G89-F89)/F89 -> 0.0968447 | H90: =(H89-G89)/G89 -> 0.034606829 | I90: =(I89-H89)/H89 -> 0.017133539 | J90: =(J89-I89)/I89 -> 0.13141631 | ... V90: =(V89-U89)/U89 -> 0.270166 | W90: =(W89-U90)/U90 -> 7577406.5 | X90: =(X89-V89)/V89 -> 0.97333359 | Z90: =(Z89-X89)/X89 -> -0.67414582 | AA90: =(AA89-Z89)/Z89 -> -0.0016689804 | AB90: =(AB89-AA89)/AA89 -> 0
A91: Non-Operating Expenses | B91: =SUM(B93:B108) -> 1514 | C91: =SUM(C93:C108) -> 1814 | D91: =SUM(D93:D108) -> 956 | E91: =SUM(E93:E108) -> 1796 | F91: =SUM(F93:F108) -> 2018 | G91: =SUM(G93:G108) -> 2516 | H91: =SUM(H93:H108) -> 2478 | I91: =SUM(I93:I108) -> 3852 | ... X91: =SUM(X93:X108) -> 5732 | Z91: =SUM(Z93:Z108) -> 5732 | AA91: =SUM(AA93:AA108) -> 5732 | AB91: =SUM(AB93:AB108) -> 5732 | AC91: =(R91-O91)/O91 -> -0.038900067 | AD91: =(S91-P91)/P91 -> -0.13959772 | AE91: =(T91-Q91)/Q91 -> 0.94634975
A92: YoY Change | B92: --- | C92: =(C91-B91)/B91 -> 0.19815059 | D92: =(D91-C91)/C91 -> -0.47298787 | E92: =(E91-D91)/D91 -> 0.87866109 | F92: =(F91-E91)/E91 -> 0.12360802 | G92: =(G91-F91)/F91 -> 0.24677899 | H92: =(H91-G91)/G91 -> -0.015103339 | I92: =(I91-H91)/H91 -> 0.55447942 | J92: =(J91-I91)/I91 -> 0.29698858 | ... V92: =(V91-U91)/U91 -> 0 | W92: =(W91-U92)/U92 -> #DIV/0! | X92: =(X91-V91)/V91 -> 0 | Z92: =(Z91-X91)/X91 -> 0 | AA92: =(AA91-Z91)/Z91 -> 0 | AB92: =(AB91-AA91)/AA91 -> 0
A93: R Group Term Life | B93: 16 | C93: 16 | D93: 16 | E93: 18 | F93: 23 | G93: 40 | H93: 48 | I93: 40 | J93: 217 | K93: 216 | L93: 240 | M93: 240 | N93: 240 | O93: 240 | P93: 321 | Q93: 321 | R93: 240 | S93: 240 | T93: 240 | U93: 240 | V93: 240 | W93: 240 | X93: 240 | Z93: 240 | AA93: 240 | AB93: 240
A94: Healthcare | B94: 412 | C94: 695 | D94: 0 | E94: 0 | F94: 0 | G94: 0 | H94: 0 | I94: 0 | J94: 0 | K94: 0 | L94: 0 | M94: 0 | N94: 0 | O94: 0 | P94: 0 | Q94: 938 | R94: 0 | S94: 0 | T94: 0 | U94: 0 | V94: 0 | W94: 0 | X94: 0 | Z94: 0 | AA94: 0 | AB94: 0
A95: Voluntary AD&D | B95: 13 | C95: 12 | D95: 0 | E95: 0 | F95: 0 | G95: 0 | H95: 0 | I95: 0 | J95: 0 | K95: 0 | L95: 0 | M95: 0 | N95: 0 | O95: 0 | P95: 0 | Q95: 0 | R95: 0 | S95: 0 | T95: 0 | U95: 0 | V95: 0 | W95: 0 | X95: 0 | Z95: 0 | AA95: 0 | AB95: 0
A96: D/V/H: VSP | B96: 133 | C96: 184 | D96: 0 | E96: 0 | F96: 0 | G96: 0 | H96: 0 | I96: 0 | J96: 0 | K96: 0 | L96: 0 | M96: 0 | N96: 0 | O96: 0 | P96: 0 | Q96: 288 | R96: 0 | S96: 0 | T96: 0 | U96: 0 | V96: 0 | W96: 0 | X96: 0 | Z96: 0 | AA96: 0 | AB96: 0
A97: ARAG | B97: 0 | C97: 0 | D97: 0 | E97: 0 | F97: 0 | G97: 0 | H97: 0 | I97: 0 | J97: 0 | K97: 0 | L97: 0 | M97: 0 | N97: 0 | O97: 0 | P97: 0 | Q97: 0 | R97: 0 | S97: 0 | T97: 0 | U97: 0 | V97: 0 | W97: 0 | X97: 0 | Z97: 0 | AA97: 0 | AB97: 0
A98: LTD Plus Buy Up | B98: 0 | C98: 0 | D98: 0 | E98: 0 | F98: 0 | G98: 0 | H98: 0 | I98: 62 | J98: 180 | K98: 188 | L98: 193 | M98: 220 | N98: 220 | O98: 268 | P98: 427 | Q98: 558 | R98: 220 | S98: 220 | T98: 220 | U98: 220 | V98: 220 | W98: 220 | X98: 220 | Z98: 220 | AA98: 220 | AB98: 220
A99: STD Plus Buy Up | B99: 0 | C99: 0 | D99: 0 | E99: 0 | F99: 0 | G99: 0 | H99: 0 | I99: 184 | J99: 341 | K99: 351 | L99: 364 | M99: 368 | N99: 368 | O99: 429 | P99: 512 | Q99: 0 | R99: 368 | S99: 368 | T99: 368 | U99: 368 | V99: 368 | W99: 368 | X99: 368 | Z99: 368 | AA99: 368 | AB99: 368
A100: HC-FSA | B100: 0 | C100: 0 | D100: 0 | E100: 0 | F100: 0 | G100: 0 | H100: 0 | I100: 0 | J100: 0 | K100: 0 | L100: 0 | M100: 0 | N100: 0 | O100: 0 | P100: 0 | Q100: 0 | R100: 0 | S100: 0 | T100: 0 | U100: 0 | V100: 0 | W100: 0 | X100: 0 | Z100: 0 | AA100: 0 | AB100: 0
A101: S Group Term Life | B101: 26 | C101: 16 | D101: 26 | E101: 26 | F101: 26 | G101: 26 | H101: 26 | I101: 0 | J101: 108 | K101: 153 | L101: 240 | M101: 240 | N101: 236 | O101: 239 | P101: 321 | Q101: 161 | R101: 236 | S101: 236 | T101: 236 | U101: 236 | V101: 236 | W101: 236 | X101: 236 | Z101: 236 | AA101: 236 | AB101: 236
A102: Healthcare | B102: 300 | C102: 695 | D102: 300 | E102: 1427 | F102: 1562 | G102: 1670 | H102: 1750 | I102: 1960 | J102: 2830 | K102: 2771 | L102: 3440 | M102: 3613 | N102: 3433 | O102: 3499 | P102: =3538 + 383 -> 3921 | Q102: 0 | R102: 3433 | S102: 3433 | T102: 3433 | U102: 3433 | V102: 3433 | W102: 3433 | X102: 3433 | Z102: 3433 | AA102: 3433 | AB102: 3433
A103: Voluntary AD&D | B103: 54 | C103: 12 | D103: 54 | E103: 53 | F103: 135 | G103: 138 | H103: 138 | I103: 0 | J103: 12 | K103: 0 | L103: 0 | M103: 0 | N103: 0 | O103: 0 | P103: 0 | Q103: 0 | R103: 0 | S103: 0 | T103: 0 | U103: 0 | V103: 0 | W103: 0 | X103: 0 | Z103: 0 | AA103: 0 | AB103: 0
A104: Vision | B104: 22 | C104: 184 | D104: 22 | E104: 22 | F104: 22 | G104: 24 | H104: 28 | I104: 31 | J104: 45 | K104: 39 | L104: 48 | M104: 48 | N104: 48 | O104: 52 | P104: 52 | Q104: 0 | R104: 48 | S104: 48 | T104: 48 | U104: 48 | V104: 48 | W104: 48 | X104: 48 | Z104: 48 | AA104: 48 | AB104: 48
A105: Legal/ARAG | B105: 238 | C105: 0 | D105: 238 | E105: 10 | F105: 0 | G105: 228 | H105: 238 | I105: 229 | J105: 249 | K105: 211 | L105: 249 | M105: 249 | N105: 237 | O105: 237 | P105: 237 | Q105: 119 | R105: 237 | S105: 237 | T105: 237 | U105: 237 | V105: 237 | W105: 237 | X105: 237 | Z105: 237 | AA105: 237 | AB105: 237
A106: HC-FSA | B106: 300 | C106: 0 | D106: 300 | E106: 240 | F106: 250 | G106: 390 | H106: 250 | I106: 1100 | J106: 700 | K106: 423 | L106: 500 | M106: 799 | N106: 390 | O106: 390 | P106: 0 | Q106: 0 | R106: 390 | S106: 390 | T106: 390 | U106: 390 | V106: 390 | W106: 390 | X106: 390 | Z106: 390 | AA106: 390 | AB106: 390 | AH106: Base | AI106: Variable | AK106: OTE | AL106: 2022 Increase | AM106: RSU Value | AN106: Annual | AO106: OTE Inc
A107: LTD Plus Buy Up | B107: 0 | C107: 0 | D107: 0 | E107: 0 | F107: 0 | G107: 0 | H107: 0 | I107: 62 | J107: 85 | K107: 84 | L107: 113 | M107: 164 | N107: 204 | O107: 229 | P107: 391 | Q107: 204 | R107: 204 | S107: 204 | T107: 204 | U107: 204 | V107: 204 | W107: 204 | X107: 204 | Z107: 204 | AA107: 204 | AB107: 204 | AH107: 253988.8 | AI107: 46000 | AJ107: =AI107/AH107 -> 0.18111035 | AK107: =AH107+AI107 -> 299988.8 | AM107: 0 | AN107: =AK107 -> 299988.8
A108: STD Plus Buy Up | B108: 0 | C108: 0 | D108: 0 | E108: 0 | F108: 0 | G108: 0 | H108: 0 | I108: 184 | J108: 229 | K108: 208 | L108: 267 | M108: 333 | N108: 356 | O108: 381 | P108: 480 | Q108: 356 | R108: 356 | S108: 356 | T108: 356 | U108: 356 | V108: 356 | W108: 356 | X108: 356 | Z108: 356 | AA108: 356 | AB108: 356 | AH108: 300037 | AI108: 84831.51 | AK108: =AH108+AI108 -> 384868.51 | AL108: =(AK108-AK107)/AK107 -> 0.28294293 | AM108: =AM111*AM110 -> 227983.91 | AN108: =AK108+AM108 -> 612852.42 | AO108: =(AN108-AN107)/AN107 -> 1.0429177
...

Sheet Comp
C3: Curr | D3: New | E3: Delta | F3: %
B4: SRP | C4: 233600 | D4: 265188 | E4: =D4-C4 -> 31588 | F4: =(D4-C4)/C4 -> 0.1352226 | G4: Base
C5: 45000 | D5: 55900 | E5: =D5-C5 -> 10900 | F5: =(D5-C5)/C5 -> 0.24222222 | G5: Var
C6: =C4+C5 -> 278600 | D6: =D4+D5 -> 321088 | E6: =D6-C6 -> 42488 | F6: =(D6-C6)/C6 -> 0.15250538 | G6: Total
B9: RDP | C9: 252000 | D9: 285750 | E9: =D9-C9 -> 33750 | F9: =(D9-C9)/C9 -> 0.13392857 | G9: Base
C10: 30000 | D10: 71370 | E10: =D10-C10 -> 41370 | F10: =(D10-C10)/C10 -> 1.379 | G10: Var
C11: =C9+C10 -> 282000 | D11: =D9+D10 -> 357120 | E11: =E9+E10 -> 75120 | F11: =(D11-C11)/C11 -> 0.26638298 | G11: Total
B13: HH | C13: =C9+C4 -> 485600 | D13: =D9+D4 -> 550938 | E13: =D13-C13 -> 65338 | F13: =(D13-C13)/C13 -> 0.13455107 | G13: Base
C14: =C5+C10 -> 75000 | D14: =D5+D10 -> 127270 | E14: =D14-C14 -> 52270 | F14: =(D14-C14)/C14 -> 0.69693333 | G14: Var
C15: =C6+C11 -> 560600 | D15: =D6+D11 -> 678208 | E15: =D15-C15 -> 117608 | F15: =(D15-C15)/C15 -> 0.20978951 | G15: Total
C42: CitiNRI | D42: 31/3/22 | E42: 1399
D43: 30/6/22 | E43: 1254
D44: 31/12/22 | E44: 1315
E46: =SUM(E42:E44) -> 3968
E47: =E46/70 -> 56.685714

Sheet Financials & Forecast
A2: Income Statement | B2: 2002 | C2: 2003 | D2: 2004 | E2: 2005 | F2: 2006 | G2: 2007 | H2: 2008 | I2: 2009 | J2: 2010 | K2: 2011 | L2: 2012 | M2: 2013 | N2: 2014 | O2: 2015 | P2: 2016 | Q2: 2017 | R2: 2018 | S2: 2019E | T2: 2019E | U2: 2019E
A3: Earnings | B3: =FinSnapshot!B60 -> 116457.84 | C3: =FinSnapshot!C60 -> 138612 | D3: =FinSnapshot!D60 -> 146135 | E3: =FinSnapshot!E60 -> 160040 | F3: =FinSnapshot!F60 -> 183604 | G3: =FinSnapshot!G60 -> 196283 | H3: =FinSnapshot!H60 -> 205004 | I3: =FinSnapshot!I60 -> 213609 | ... U3: =FinSnapshot!U60 -> 585094.66
A4: Expenses | B4: =FinSnapshot!B112 -> 69054 | C4: =FinSnapshot!C112 -> 74224 | D4: =FinSnapshot!D112 -> 79170 | E4: =FinSnapshot!E112 -> 82173 | F4: =FinSnapshot!F112 -> 81548 | G4: =FinSnapshot!G112 -> 89971 | H4: =FinSnapshot!H112 -> 82506.566 | I4: =FinSnapshot!I112 -> 83029.687 | ... U4: =FinSnapshot!U112 -> 236052.19
A5: Gross Income | B5: =B3-B4 -> 47403.84 | C5: =C3-C4 -> 64388 | D5: =D3-D4 -> 66965 | E5: =E3-E4 -> 77867 | F5: =F3-F4 -> 102056 | G5: =G3-G4 -> 106312 | H5: =H3-H4 -> 122497.43 | I5: =I3-I4 -> 130579.31 | ... U5: =U3-U4 -> 349042.47
A6: Taxes | B6: =FinSnapshot!B85 -> 29052 | C6: =FinSnapshot!C85 -> 42602 | D6: =FinSnapshot!D85 -> 42534 | E6: =FinSnapshot!E85 -> 55198 | F6: =FinSnapshot!F85 -> 54583 | G6: =FinSnapshot!G85 -> 54767 | H6: =FinSnapshot!H85 -> 58590.58 | I6: =FinSnapshot!I85 -> 64687 | ... U6: =FinSnapshot!U85 -> 192614
A7: Income after taxes | B7: =B5-B6 -> 18351.84 | C7: =C5-C6 -> 21786 | D7: =D5-D6 -> 24431 | E7: =E5-E6 -> 22669 | F7: =F5-F6 -> 47473 | G7: =G5-G6 -> 51545 | H7: =H5-H6 -> 63906.854 | I7: =I5-I6 -> 65892.313 | ... U7: =U5-U6 -> 156428.47
A8: Non-Operating Expenses | B8: =FinSnapshot!B91 -> 1514 | C8: =FinSnapshot!C91 -> 1814 | D8: =FinSnapshot!D91 -> 956 | E8: =FinSnapshot!E91 -> 1796 | F8: =FinSnapshot!F91 -> 2018 | G8: =FinSnapshot!G91 -> 2516 | H8: =FinSnapshot!H91 -> 2478 | I8: =FinSnapshot!I91 -> 3852 | ... U8: =FinSnapshot!U91 -> 5732
A9: Income | B9: =B7-B8 -> 16837.84 | C9: =C7-C8 -> 19972 | D9: =D7-D8 -> 23475 | E9: =E7-E8 -> 20873 | F9: =F7-F8 -> 45455 | G9: =G7-G8 -> 49029 | H9: =H7-H8 -> 61428.854 | I9: =I7-I8 -> 62040.313 | ... U9: =U7-U8 -> 150696.47
A10: Other Income (Div/ Interest) | B10: =FinSnapshot!B52 -> 309 | C10: =FinSnapshot!C52 -> 589 | D10: =FinSnapshot!D52 -> 955 | E10: =FinSnapshot!E52 -> 1555 | F10: =FinSnapshot!F52 -> 3301 | G10: =FinSnapshot!G52 -> 5075 | H10: =FinSnapshot!H52 -> -7531 | I10: =FinSnapshot!I52 -> 6054 | ... U10: =FinSnapshot!U52 -> 18896
A11: Non Operating Income | B11: 0 | C11: 0 | D11: 0 | E11: 0 | F11: 0 | G11: 0 | H11: 0 | I11: 0 | J11: 0 | K11: 0 | L11: 0 | M11: 0 | N11: 0 | O11: 0 | P11: 0 | Q11: 0 | R11: 0 | S11: 0 | T11: 0 | U11: 0
A12: Net Income | B12: =SUM(B9+B10) -> 17146.84 | C12: =SUM(C9+C10) -> 20561 | D12: =SUM(D9+D10) -> 24430 | E12: =SUM(E9+E10) -> 22428 | F12: =SUM(F9:F11) -> 48756 | G12: =SUM(G9+G10) -> 54104 | H12: =SUM(H9+H10) -> 53897.854 | I12: =SUM(I9+I10) -> 68094.313 | J12: =SUM(J9+J10) -> 51361.381 | K12: =SUM(K9+K10) -> 77899.685 | L12: =SUM(L9+L10) -> 65061.601 | M12: =SUM(M9+M10) -> 67187.2 | N12: =SUM(N9+N10) -> 78566 | ... U12: =SUM(U9+U10) -> 169592.47
A13: Net Profit Margin | B13: =B12/B3 -> 0.14723646 | C13: =C12/C3 -> 0.14833492 | D13: =D12/D3 -> 0.16717419 | E13: =E12/E3 -> 0.14013997 | F13: =F12/F3 -> 0.26554977 | G13: =G12/G3 -> 0.27564282 | H13: =H12/H3 -> 0.26291123 | I13: =I12/I3 -> 0.31878017 | ... U13: =U12/U3 -> 0.28985475
A14: Actual Increase in assets | C14: =FinSnapshot!$C$28-FinSnapshot!$B$28 -> 34127 | D14: =FinSnapshot!$D$28-FinSnapshot!$C$28 -> 32000 | E14: =FinSnapshot!$E$28-FinSnapshot!$D$28 -> 38895 | F14: =FinSnapshot!$F$28-FinSnapshot!$E$28 -> 83694 | G14: =FinSnapshot!$G$28-FinSnapshot!$F$28 -> 91067 | H14: =FinSnapshot!$H$28-FinSnapshot!$G$28 -> -42077 | I14: =FinSnapshot!$I$28-FinSnapshot!$H$28 -> 166744 | J14: =FinSnapshot!$J$28-FinSnapshot!$I$28 -> 169553 | K14: =FinSnapshot!$K$28-FinSnapshot!$J$28 -> 94736 | L14: =FinSnapshot!$L$28-FinSnapshot!$K$28 -> 148051 | M14: =FinSnapshot!$M$28-FinSnapshot!$L$28 -> 310359 | N14: =FinSnapshot!$N$28-FinSnapshot!$M$28 -> 258889 | O14: =FinSnapshot!$O$28-FinSnapshot!$N$28 -> 103569 | P14: =FinSnapshot!$P$28-FinSnapshot!$O$28 -> 489968 | Q14: =FinSnapshot!$O$28-FinSnapshot!$N$28 -> 103569 | R14: =FinSnapshot!$O$28-FinSnapshot!$N$28 -> 103569 | S14: =FinSnapshot!$O$28-FinSnapshot!$N$28 -> 103569 | T14: =FinSnapshot!$O$28-FinSnapshot!$N$28 -> 103569 | U14: =FinSnapshot!$O$28-FinSnapshot!$N$28 -> 103569
B15: 2015 | C15: 2016 E | D15: 2017 E | E15: 2018 E | F15: 2019 E | G15: 2020 E | H15: 2021 E | I15: 2022 E | J15: 2023 E | K15: 2024 E | L15: 2025 E
A16: Housing | B16: =Monthly!C864 -> 1655 | C16: =B16*(1+$B$39) -> 1737.75 | D16: =4500*12/$B$40 -> 54000 | E16: =D16*(1+$B$39) -> 56700 | F16: =E16*(1+$B$39) -> 59535 | G16: =F16*(1+$B$39) -> 62511.75 | H16: =G16*(1+$B$39) -> 65637.338 | I16: =H16*(1+$B$39) -> 68919.204 | J16: =I16*(1+$B$39) -> 72365.165 | K16: =J16*(1+$B$39) -> 75983.423 | L16: =K16*(1+$B$39) -> 79782.594
A17: Car | B17: =Monthly!C878 -> 491 | C17: =B17*(1+$B$38) -> 662.85 | D17: =(C17*(1+$B$39) + 800*12)/$B$40 -> 10295.993 | E17: =(C17*(1+$B$39) + 800*12)/$B$40 -> 10295.993 | F17: =(C17*(1+$B$39) + 1600*12)/$B$40 -> 19895.993 | G17: =(C17*(1+$B$39) + 1600*12)/$B$40 -> 19895.993 | H17: =(C17*(1+$B$39) + 1600*12)/$B$40 -> 19895.993 | I17: =(C17*(1+$B$39) + 1600*12)/$B$40 -> 19895.993 | J17: =(C17*(1+$B$39) + 1600*12)/$B$40 -> 19895.993 | K17: =($C$17*1.5 + 800*12)/$B$40 -> 10594.275 | L17: =($C$17*1.5 + 800*12)/$B$40 -> 10594.275
A18: Transportation | B18: =Monthly!C886 -> 246 | C18: =B18*(1+$B$38) -> 332.1 | D18: =C18*(1+$B$39) -> 348.705 | E18: =D18*(1+$B$39) -> 366.14025 | F18: =E18*(1+$B$39) -> 384.44726 | G18: =F18*(1+$B$39) -> 403.66963 | H18: =G18*(1+$B$39) -> 423.85311 | I18: =H18*(1+$B$39) -> 445.04576 | J18: =I18*(1+$B$39) -> 467.29805 | K18: =J18*(1+$B$39) -> 490.66295 | L18: =K18*(1+$B$39) -> 515.1961
A19: Food | B19: =Monthly!C892 -> 993 | C19: =B19*(1+$B$38) -> 1340.55 | D19: =C19*(1+$B$39) -> 1407.5775 | E19: =D19*(1+$B$39) -> 1477.9564 | F19: =E19*(1+$B$39) -> 1551.8542 | G19: =F19*(1+$B$39) -> 1629.4469 | H19: =G19*(1+$B$39) -> 1710.9192 | I19: =H19*(1+$B$39) -> 1796.4652 | J19: =I19*(1+$B$39) -> 1886.2885 | K19: =J19*(1+$B$39) -> 1980.6029 | L19: =K19*(1+$B$39) -> 2079.633
A20: Utilities | B20: =Monthly!C896 -> 463 | C20: =B20*(1+$B$38) -> 625.05 | D20: =C20*(1+$B$39) -> 656.3025 | E20: =D20*(1+$B$39) -> 689.11763 | F20: =E20*(1+$B$39) -> 723.57351 | G20: =F20*(1+$B$39) -> 759.75218 | H20: =G20*(1+$B$39) -> 797.73979 | I20: =H20*(1+$B$39) -> 837.62678 | J20: =I20*(1+$B$39) -> 879.50812 | K20: =J20*(1+$B$39) -> 923.48353 | L20: =K20*(1+$B$39) -> 969.6577
A21: Misc | B21: =Monthly!C906 -> 129 | C21: =B21*(1+$B$38) -> 174.15 | D21: =C21*(1+$B$39) -> 182.8575 | E21: =D21*(1+$B$39) -> 192.00038 | F21: =E21*(1+$B$39) -> 201.60039 | G21: =F21*(1+$B$39) -> 211.68041 | H21: =G21*(1+$B$39) -> 222.26443 | I21: =H21*(1+$B$39) -> 233.37766 | J21: =I21*(1+$B$39) -> 245.04654 | K21: =J21*(1+$B$39) -> 257.29887 | L21: =K21*(1+$B$39) -> 270.16381
A22: Trips (EET) | B22: =Monthly!C914 -> 0 | C22: =B22*(1+$B$38) -> 0 | D22: =C22*(1+$B$39) -> 0 | E22: =D22*(1+$B$39) -> 0 | F22: =E22*(1+$B$39) -> 0 | G22: =F22*(1+$B$39) -> 0 | H22: =G22*(1+$B$39) -> 0 | I22: =H22*(1+$B$39) -> 0 | J22: =I22*(1+$B$39) -> 0 | K22: =J22*(1+$B$39) -> 0 | L22: =K22*(1+$B$39) -> 0
A23: School | B23: =Monthly!O917 -> 576.58333 | C23: =B23*(1+$B$38) -> 778.3875 | D23: =((C23)*(1+$B$39)) -> 817.30688 | E23: =((D23)*(1+$B$39)) -> 858.17222 | F23: =((E23)*(1+$B$39)) -> 901.08083 | G23: =((F23)*(1+$B$39)) -> 946.13487 | H23: =((G23)*(1+$B$39)) -> 993.44161 | I23: =((H23)*(1+$B$39)) -> 1043.1137 | J23: =((I23)*(1+$B$39)) -> 1095.2694 | K23: =((J23)*(1+$B$39)) -> 1150.0328 | L23: =((K23)*(1+$B$39)) -> 1207.5345
A24: Day Care/ Extra Classes | B24: =Monthly!O918 -> 1891.4167 | C24: =B24*(1+$B$38) -> 2553.4125 | D24: =(C24*(1+$B$39)) -> 2681.0831 | E24: =(D24*(1+$B$39)) -> 2815.1373 | F24: =(E24*(1+$B$39)) -> 2955.8941 | G24: =(F24*(1+$B$39)) -> 3103.6889 | H24: =(G24*(1+$B$39)) -> 3258.8733 | I24: =(H24*(1+$B$39)) -> 3421.817 | J24: =(I24*(1+$B$39)) -> 3592.9078 | K24: =(J24*(1+$B$39)) -> 3772.5532 | L24: =(K24*(1+$B$39)) -> 3961.1809
A25: Medical | B25: =FinSnapshot!P102/B40 -> 3921 | C25: =B25*(1+$B$38) -> 5293.35 | D25: =(C25*(1+$B$39)) -> 5558.0175 | E25: =(D25*(1+$B$39)) -> 5835.9184 | F25: =(E25*(1+$B$39)) -> 6127.7143 | G25: =(F25*(1+$B$39)) -> 6434.1 | H25: =(G25*(1+$B$39)) -> 6755.805 | I25: =(H25*(1+$B$39)) -> 7093.5953 | J25: =(I25*(1+$B$39)) -> 7448.275 | K25: =(J25*(1+$B$39)) -> 7820.6888 | L25: =(K25*(1+$B$39)) -> 8211.7232
A26: OTE | B26: =Monthly!O929 -> 53.166667 | C26: =B26*(1+$B$38) -> 71.775 | D26: =(C26*(1+$B$39)) -> 75.36375 | E26: =(D26*(1+$B$39)) -> 79.131938 | F26: =(E26*(1+$B$39)) -> 83.088534 | G26: =(F26*(1+$B$39)) -> 87.242961 | H26: =(G26*(1+$B$39)) -> 91.605109 | I26: =(H26*(1+$B$39)) -> 96.185365 | J26: =(I26*(1+$B$39)) -> 100.99463 | K26: =(J26*(1+$B$39)) -> 106.04436 | L26: =(K26*(1+$B$39)) -> 111.34658
A27: Non Opex | B27: =(FinSnapshot!P91 - B25)/B40 -> 2741 | C27: =B27*(1+$B$38) -> 3700.35 | D27: =(C27*(1+$B$39)) -> 3885.3675 | E27: =(D27*(1+$B$39)) -> 4079.6359 | F27: =(E27*(1+$B$39)) -> 4283.6177 | G27: =(F27*(1+$B$39)) -> 4497.7986 | H27: =(G27*(1+$B$39)) -> 4722.6885 | I27: =(H27*(1+$B$39)) -> 4958.8229 | J27: =(I27*(1+$B$39)) -> 5206.764 | K27: =(J27*(1+$B$39)) -> 5467.1023 | L27: =(K27*(1+$B$39)) -> 5740.4574
A28: India | B28: =Monthly!O930 -> 750 | C28: =B28*(1+$B$38) -> 1012.5 | D28: =12000/$B$40 -> 12000 | E28: =12000/$B$40 -> 12000 | F28: =12000/$B$40 -> 12000 | G28: =12000/$B$40 -> 12000 | H28: =12000/$B$40 -> 12000 | I28: =12000/$B$40 -> 12000 | J28: =12000/$B$40 -> 12000 | K28: =12000/$B$40 -> 12000 | L28: =12000/$B$40 -> 12000
A29: Expenses | B29: =SUM(B16:B26) -> 10419.167 | C29: =SUM(C16:C26) -> 13569.375 | D29: =SUM(D16:D26) -> 76023.206 | E29: =SUM(E16:E26) -> 79309.567 | F29: =SUM(F16:F26) -> 92360.246 | G29: =SUM(G16:G26) -> 95983.458 | H29: =SUM(H16:H26) -> 99787.832 | I29: =SUM(I16:I26) -> 103782.42 | ... L29: =SUM(L16:L26) -> 107703.3
A30: Taxes | B30: =FinSnapshot!O85/B40 -> 112773 | C30: =C32*$B$38 -> 123508.02 | D30: =D32*$B$38 -> 127213.26 | E30: =E32*$B$38 -> 131029.66 | F30: =F32*$B$38 -> 134960.55 | G30: =G32*$B$38 -> 139009.37 | H30: =H32*$B$38 -> 143179.65 | I30: =I32*$B$38 -> 147475.04 | J30: =J32*$B$38 -> 151899.29 | ... L30: =L32*$B$38 -> 161149.95
A31: Total Expenses | B31: =Monthly!O934 -> 8969.25 | C31: =Monthly!O857 -> 9854.0833 | D31: =SUM(D16:D30)/1 - D29 -> 219121.84 | E31: =SUM(E16:E30)/1 - E29 -> 226418.86 | F31: =SUM(F16:F30)/1 - F29 -> 243604.41 | G31: =SUM(G16:G30)/1 - G29 -> 251490.62 | H31: =SUM(H16:H30)/1 - H29 -> 259690.17 | I31: =SUM(I16:I30)/1 - I29 -> 268216.28 | J31: =SUM(J16:J30)/1 - J29 -> 277082.8 | K31: =SUM(K16:K30)/1 - K29 -> 277002.43 | L31: =SUM(L16:L30)/1 - L29 -> 286593.72
A32: Household Income | B32: =FinSnapshot!O60/$B$40 -> 342602 | C32: =(B32*(1+$B$42)) -> 352880.06 | D32: =(C32*(1+$B$42)) -> 363466.46 | E32: =(D32*(1+$B$42)) -> 374370.46 | F32: =(E32*(1+$B$42)) -> 385601.57 | G32: =(F32*(1+$B$42)) -> 397169.62 | H32: =(G32*(1+$B$42)) -> 409084.7 | I32: =(H32*(1+$B$42)) -> 421357.25 | J32: =(I32*(1+$B$42)) -> 433997.96 | ... L32: =(K32*(1+$B$42)) -> 460428.44
A33: Investments | B33: =80000/$B$40 -> 80000 | C33: =80000/$B$40 -> 80000 | D33: =80000/$B$40 -> 80000 | E33: =80000/$B$40 -> 80000 | F33: =80000/$B$40 -> 80000 | G33: =80000/$B$40 -> 80000 | H33: =80000/$B$40 -> 80000 | I33: =80000/$B$40 -> 80000 | ... L33: =80000/$B$40 -> 80000
A34: 529 Plan | B34: =20000/$B$40 -> 20000 | C34: =20000/$B$40 -> 20000 | D34: =20000/$B$40 -> 20000 | E34: =20000/$B$40 -> 20000 | F34: =20000/$B$40 -> 20000 | G34: =20000/$B$40 -> 20000 | H34: =20000/$B$40 -> 20000 | I34: =20000/$B$40 -> 20000 | ... L34: =20000/$B$40 -> 20000
A35: Savings | B35: =(B32-B33-B34-B31)/$B$40 -> 233632.75 | C35: =(C32-C33-C34-C31)/$B$40 -> 243025.98 | D35: =(D32-D33-D34-D31)/$B$40 -> 44344.626 | E35: =(E32-E33-E34-E31)/$B$40 -> 47951.593 | F35: =(F32-F33-F34-F31)/$B$40 -> 41997.157 | G35: =(G32-G33-G34-G31)/$B$40 -> 45678.994 | H35: =(H32-H33-H34-H31)/$B$40 -> 49394.538 | I35: =(I32-I33-I34-I31)/$B$40 -> 53140.963 | ... L35: =(L32-L33-L34-L31)/$B$40 -> 73834.723
A37: COLA | B37: 0.5
A38: Tax Rate | B38: 0.35
A39: Inflation | B39: 0.05
A40: Monthly | B40: 1
A41: Investments /yr contr growth | B41: 0
A42: Avg Income Growth | B42: 0.03
A44: OTE - 2017 | B44: 60000 | C44: 800/PM
A45: OTE 2019 | B45: 50000 | C45: 600/PM
A47: School | B47: AMSA | C47: 2021

Sheet M
B1: 2002 | C1: 2003 | D1: 2004 | E1: 2005 | F1: 2006 | G1: 2007 | H1: 2008 | I1: 2009 | J1: 2010 | K1: 2011 | L1: 2012 | M1: 2013 | N1: 2014 | O1: 2015 | P1: 2016 | Q1: 2017 | R1: 2018 | S1: 2019 | T1: 2020 | U1: 2021 | V1: 2022 | W1: 2023 | X1: Avg | Y1: Trends | Z1: Median | AA1: Max | AB1: Min
A2: Jan | B2: NA | C2: 4791 | D2: =Monthly!C$1784 -> 5167.1667 | E2: =Monthly!$C$1706 -> 6372.0833 | F2: =Monthly!C$1628 -> 5839.5833 | G2: =Monthly!C$1550 -> 9598.6667 | H2: =Monthly!C$1473 -> 10828.249 | I2: =Monthly!C$1396 -> 4603.823 | J2: =Monthly!C$1319 -> 11670.033 | K2: =Monthly!C$1241 -> 9174.6166 | L2: =Monthly!C$1164 -> 9285.5332 | M2: =Monthly!C$1087 -> 9994.6999 | N2: =Monthly!C$1010 -> 9449.1667 | O2: =Monthly!C$934 -> 7233.4167 | P2: =Monthly!C$857 -> 10627.917 | Q2: =Monthly!C$780 -> 12832.9 | R2: =Monthly!C703 -> 11992.5 | S2: =Monthly!C$626 -> 11212.5 | T2: =Monthly!C550 -> 16403.5 | U2: =Monthly!C473 -> 19249.967 | V2: =Monthly!C396 -> 37226.8 | W2: =Monthly!C312 -> 21040.633 | X2: =(SUM(C2:T2))/($B$34-1) -> 6961.5565 | Z2: =MEDIAN(B2:T2) -> 9523.9167 | AA2: =MAX(B2:T2) -> 16403.5 | AB2: =MIN(B2:T2) -> 4603.823
A3: Feb | B3: NA | C3: 4789 | D3: =Monthly!D$1784 -> 5284.1667 | E3: =Monthly!D$1706 -> 4553.0833 | F3: =Monthly!D$1628 -> 5277.5833 | G3: =Monthly!D$1550 -> 5674.6667 | H3: =Monthly!D$1473 -> 6757.2495 | I3: =Monthly!D$1396 -> 16616.491 | J3: =Monthly!D$1319 -> 7230.0332 | K3: =Monthly!D$1241 -> 9024.6999 | L3: =Monthly!D1164 -> 8761.5332 | M3: =Monthly!D$1087 -> 10482.7 | N3: =Monthly!D$1010 -> 6971.1667 | O3: =Monthly!D$934 -> 11151.417 | P3: =Monthly!D$857 -> 8998.9167 | Q3: =Monthly!D$780 -> 8990.9 | R3: =Monthly!D$703 -> 11070.5 | S3: =Monthly!D$626 -> 11427.5 | T3: =Monthly!D$550 -> 12072.5 | U3: =Monthly!D473 -> 17398.967 | V3: =Monthly!D396 -> 22335.125 | W3: =Monthly!D312 -> 16593.633 | X3: =(SUM(C3:T3))/($B$34-1) -> 6463.9211 | Z3: =MEDIAN(B3:T3) -> 8876.2166 | AA3: =MAX(B3:T3) -> 16616.491 | AB3: =MIN(B3:T3) -> 4553.0833
A4: Mar | B4: NA | C4: 5967 | D4: =Monthly!E$1784 -> 21805.167 | E4: =Monthly!E$1706 -> 7299.0833 | F4: =Monthly!E$1628 -> 5674.5833 | G4: =Monthly!E$1550 -> 8183.6667 | H4: =Monthly!E$1473 -> 7029.2495 | I4: =Monthly!E$1396 -> 7078.1617 | J4: =Monthly!E1319 -> 7665.0332 | K4: =Monthly!E$1241 -> 6130.6999 | L4: =Monthly!E$1164 -> 9062.5332 | M4: =Monthly!E$1087 -> 7952.6999 | N4: =Monthly!E$1010 -> 8020.1667 | O4: =Monthly!E$934 -> 8972.4167 | P4: =Monthly!E$857 -> 7265.9167 | Q4: =Monthly!E$780 -> 8806.9 | R4: =Monthly!E703 -> 11857.5 | S4: =Monthly!E$626 -> 9677.5 | T4: =Monthly!E$550 -> 10550.5 | U4: =Monthly!E473 -> 20023.967 | V4: =Monthly!E396 -> 27187.8 | W4: =Monthly!E312 -> 16992.633 | X4: =(SUM(C4:T4))/($B$34-1) -> 6624.9491 | Z4: =MEDIAN(B4:T4) -> 7986.4333 | AA4: =MAX(B4:T4) -> 21805.167 | AB4: =MIN(B4:T4) -> 5674.5833
A5: Apr | B5: NA | C5: 6991 | D5: =Monthly!F$1784 -> 4288.1667 | E5: =Monthly!F$1706 -> 4978.0833 | F5: =Monthly!F$1628 -> 12725.583 | G5: =Monthly!F$1550 -> 5737.6667 | H5: =Monthly!F$1473 -> 8759.2495 | I5: =Monthly!F$1396 -> 5574.8361 | J5: =Monthly!F$1319 -> 9896.0332 | K5: =Monthly!F$1241 -> 8064.6999 | L5: =Monthly!F$1164 -> 9753.5332 | M5: =Monthly!F$1087 -> 9141.6999 | N5: =Monthly!F$1010 -> 19469.167 | O5: =Monthly!F$934 -> 11032.417 | P5: =Monthly!F$857 -> 12264.917 | Q5: =Monthly!F$780 -> 11078.9 | R5: =Monthly!F703 -> 14610.5 | S5: =Monthly!F$626 -> 19728.5 | T5: =Monthly!F$550 -> 10159.5 | U5: =Monthly!F473 -> 18280.967 | V5: =Monthly!F396 -> 21155.8 | W5: =Monthly!F312 -> 24239.633 | X5: =(SUM(C5:T5))/($B$34-1) -> 7677.2688 | Z5: =MEDIAN(B5:T5) -> 9824.7832 | AA5: =MAX(B5:T5) -> 19728.5 | AB5: =MIN(B5:T5) -> 4288.1667
A6: May | B6: NA | C6: 5585 | D6: =Monthly!G$1784 -> 4218.1667 | E6: =Monthly!G$1706 -> 4643.0833 | F6: =Monthly!G$1628 -> 8793.5833 | G6: =Monthly!G$1550 -> 9511.6667 | H6: =Monthly!G$1473 -> 6834.2495 | I6: =Monthly!G$1396 -> 5204.5139 | J6: =Monthly!G$1319 -> 11692.033 | K6: =Monthly!G$1241 -> 9467.6999 | L6: =Monthly!G$1164 -> 10968.533 | M6: =Monthly!G$1087 -> 27395.25 | N6: =Monthly!G$1010 -> 9000.1667 | O6: =Monthly!G$934 -> 7590.4167 | P6: =Monthly!G$857 -> 6091.9167 | Q6: =Monthly!G$780 -> 10325.9 | R6: =Monthly!G703 -> 11106.5 | S6: =Monthly!G$626 -> 11871.5 | T6: =Monthly!G$550 -> 106767.33 | U6: =Monthly!G473 -> 18692.967 | V6: =Monthly!G396 -> 18135.8 | W6: =Monthly!G312 -> 19097.633 | X6: =(SUM(C6:T6))/($B$34-1) -> 11127.813 | Z6: =MEDIAN(B6:T6) -> 9233.9333 | AA6: =MAX(B6:T6) -> 106767.33 | AB6: =MIN(B6:T6) -> 4218.1667
A7: Jun | B7: NA | C7: 7709 | D7: =Monthly!H$1784 -> 5993.1667 | E7: =Monthly!H$1706 -> 5477.0833 | F7: =Monthly!H$1628 -> 8650.5833 | G7: =Monthly!H$1550 -> 8655.6667 | H7: =Monthly!H$1473 -> 9419.2495 | I7: =Monthly!H$1396 -> 7862.195 | J7: =Monthly!H$1319 -> 9412.0332 | K7: =Monthly!H$1241 -> 6516.6999 | L7: =Monthly!H$1164 -> 10179.533 | M7: =Monthly!H$1087 -> 10406.25 | N7: =Monthly!H$1010 -> 7495.1667 | O7: =Monthly!H$934 -> 8498.4167 | P7: =Monthly!H$857 -> 10510.917 | Q7: =Monthly!H$780 -> 12252.5 | R7: =Monthly!H703 -> 12425.5 | S7: =Monthly!H$626 -> 12699 | T7: =Monthly!H$550 -> 14815.5 | U7: =Monthly!H473 -> 20225.967 | V7: =Monthly!H396 -> 26746.8 | W7: =Monthly!H312 -> 22820.633 | X7: =(SUM(C7:T7))/($B$34-1) -> 7040.7692 | Z7: =MEDIAN(B7:T7) -> 9033.8499 | AA7: =MAX(B7:T7) -> 14815.5 | AB7: =MIN(B7:T7) -> 5477.0833
A8: Jul | B8: =Monthly!I1938 -> 5456.8333 | C8: 5900 | D8: =Monthly!I$1784 -> 5600.1667 | E8: =Monthly!I$1706 -> 5987.0833 | F8: =Monthly!I$1628 -> 5499.5833 | G8: =Monthly!I$1550 -> 7081.6667 | H8: =Monthly!I$1473 -> 6543.4352 | I8: =Monthly!$I$1396 -> 4673.8796 | J8: =Monthly!I$1319 -> 7790.0332 | K8: =Monthly!I$1241 -> 7044.6999 | L8: =Monthly!I$1164 -> 8539.5332 | M8: =Monthly!I$1087 -> 9164.25 | N8: =Monthly!I$1010 -> 12308.167 | O8: =Monthly!I$934 -> 8914.4167 | P8: =Monthly!I$857 -> 11037.25 | Q8: =Monthly!I$780 -> 15014.5 | R8: =Monthly!I703 -> 12768.5 | S8: =Monthly!I$626 -> 13387 | T8: =Monthly!I$550 -> 12328.5 | U8: =Monthly!I473 -> 19035.967 | V8: =Monthly!I396 -> 20303.8 | W8: =Monthly!I312 -> 29160.633 | X8: =(SUM(B8:T8))/($B$34-1) -> 6876.6457 | Z8: =MEDIAN(B8:T8) -> 7790.0332 | AA8: =MAX(B8:T8) -> 15014.5 | AB8: =MIN(B8:T8) -> 4673.8796
A9: Aug | B9: =Monthly!J$1938 -> 5662.8333 | C9: 5630 | D9: =Monthly!J$1784 -> 3364.1667 | E9: =Monthly!J$1706 -> 5948.0833 | F9: =Monthly!J$1628 -> 5795.5833 | G9: =Monthly!J$1550 -> 6232.6667 | H9: =Monthly!J$1473 -> 5047.4808 | I9: =Monthly!$J$1396 -> 4805.5676 | J9: =Monthly!J$1319 -> 14323.033 | K9: =Monthly!J$1241 -> 7836.6999 | L9: =Monthly!J$1164 -> 9616.5332 | M9: =Monthly!J$1087 -> 10647.25 | N9: =Monthly!J$1010 -> 9470.1667 | O9: =Monthly!J$934 -> 7069.4167 | P9: =Monthly!J$857 -> 7795.25 | Q9: =Monthly!J$780 -> 10862 | R9: =Monthly!J703 -> 10280.167 | S9: =Monthly!J$626 -> 11054 | T9: =Monthly!J$550 -> 10952.5 | U9: =Monthly!J473 -> 18994.058 | V9: =Monthly!J396 -> 50314.8 | W9: =Monthly!J312 -> 24057.633 | X9: =(SUM(B9:T9))/($B$34-1) -> 6349.7249 | Z9: =MEDIAN(B9:T9) -> 7795.25 | AA9: =MAX(B9:T9) -> 14323.033 | AB9: =MIN(B9:T9) -> 3364.1667
A10: Sep | B10: =Monthly!K$1938 -> 7364.8333 | C10: 6794 | D10: =Monthly!K$1784 -> 3667.1667 | E10: =Monthly!K$1706 -> 8321.0833 | F10: =Monthly!K$1628 -> 6247.5833 | G10: =Monthly!K$1550 -> 9424.6667 | H10: =Monthly!K$1473 -> 5837.0501 | I10: =Monthly!K$1396 -> 5329.259 | J10: =Monthly!K$1319 -> 12724.033 | K10: =Monthly!K$1241 -> 7861.6999 | L10: =Monthly!K$1164 -> 9328.5332 | M10: =Monthly!K$1087 -> 7533.25 | N10: =Monthly!K$1010 -> 8408.1667 | O10: =Monthly!K$934 -> 8576.4167 | P10: =Monthly!K$857 -> 8664.25 | Q10: =Monthly!K$780 -> 11410.5 | R10: =Monthly!K703 -> 16317.167 | S10: =Monthly!K$626 -> 14983 | T10: =Monthly!K$550 -> 69707.5 | U10: =Monthly!K473 -> 21111.872 | V10: =Monthly!K396 -> 19300.8 | W10: =Monthly!K312 -> 20546.633 | X10: =(SUM(B10:T10))/($B$34-1) -> 9520.84 | Z10: =MEDIAN(B10:T10) -> 8408.1667 | AA10: =MAX(B10:T10) -> 69707.5 | AB10: =MIN(B10:T10) -> 3667.1667
A11: Oct | B11: =Monthly!L$1938 -> 5230.8333 | C11: 7198 | D11: =Monthly!L$1784 -> 10177.167 | E11: =Monthly!L$1706 -> 15253.083 | F11: =Monthly!L$1628 -> 4554.5833 | G11: =Monthly!L$1550 -> 7160.6667 | H11: =Monthly!L$1473 -> 4859.0423 | I11: =Monthly!L$1396 -> 5249.9539 | J11: =Monthly!L$1319 -> 6941.0332 | K11: =Monthly!L$1241 -> 7059.6999 | L11: =Monthly!L$1164 -> 9311.5332 | M11: =Monthly!L$1087 -> 10955.25 | N11: =Monthly!L$1010 -> 7497.1667 | O11: =Monthly!L$934 -> 9452.4167 | P11: =Monthly!L$857 -> 9897.25 | Q11: =Monthly!L$780 -> 10009.5 | R11: =Monthly!L703 -> 9973.1667 | S11: =Monthly!L$626 -> 10662 | T11: =Monthly!L$550 -> 34119.167 | U11: =Monthly!L473 -> 23184.852 | V11: =Monthly!L396 -> 18289.8 | W11: =Monthly!L312 -> 22515.633 | X11: =(SUM(B11:T11))/($B$34-1) -> 7731.7297 | Z11: =MEDIAN(B11:T11) -> 9311.5332 | AA11: =MAX(B11:T11) -> 34119.167 | AB11: =MIN(B11:T11) -> 4554.5833
A12: Nov | B12: =Monthly!M$1938 -> 6914.8333 | C12: 5855 | D12: =Monthly!M$1784 -> 4857.1667 | E12: =Monthly!M$1706 -> 5164.0833 | F12: =Monthly!M$1628 -> 6491.5833 | G12: =Monthly!M$1550 -> 6183.6667 | H12: =Monthly!M$1473 -> 5084.0344 | I12: =Monthly!M$1396 -> 8362.6522 | J12: =Monthly!M$1319 -> 7833.0332 | K12: =Monthly!M$1241 -> 10236.7 | L12: =Monthly!M$1164 -> 11229.533 | M12: =Monthly!M$1087 -> 10874.25 | N12: =Monthly!M$1010 -> 11906.167 | O12: =Monthly!M$934 -> 9131.4167 | P12: =Monthly!M$857 -> 9158.25 | Q12: =Monthly!M$780 -> 10471.5 | R12: =Monthly!M703 -> 16661.167 | S12: =Monthly!M$626 -> 11502 | T12: =Monthly!M$550 -> 20456.8 | U12: =Monthly!M473 -> 18051.831 | V12: =Monthly!M396 -> 18987.8 | W12: =Monthly!M312 -> 22076.633 | X12: =(SUM(B12:T12))/($B$34-1) -> 7432.2432 | Z12: =MEDIAN(B12:T12) -> 9131.4167 | AA12: =MAX(B12:T12) -> 20456.8 | AB12: =MIN(B12:T12) -> 4857.1667
A13: Dec | B13: =Monthly!N$1938 -> 8423.8333 | C13: 7015 | D13: =Monthly!N$1784 -> 4748.1667 | E13: =Monthly!N$1706 -> 8177.0833 | F13: =Monthly!N$1628 -> 5997.5833 | G13: =Monthly!N$1550 -> 6525.6667 | H13: =Monthly!N$1473 -> 5508.0265 | I13: =Monthly!N$1396 -> 7668.3541 | J13: =Monthly!N$1319 -> 11992.033 | K13: =Monthly!N$1241 -> 8336.6999 | L13: =Monthly!N$1164 -> 11827.533 | M13: =Monthly!N$1087 -> 8987.25 | N13: =Monthly!N$1010 -> 7081.1667 | O13: =Monthly!N$934 -> 10008.417 | P13: =Monthly!N$857 -> 15936.25 | Q13: =Monthly!N$780 -> 11762.5 | R13: =Monthly!N703 -> 11240.167 | S13: =Monthly!N$626 -> 11631 | T13: =Monthly!N$550 -> 26284.217 | U13: =Monthly!N473 -> 21800.811 | V13: =Monthly!N396 -> 19823.8 | W13: =Monthly!N312 -> 18777.633 | X13: =(SUM(B13:T13))/($B$34-1) -> 7881.2895 | Z13: =MEDIAN(B13:T13) -> 8423.8333 | AA13: =MAX(B13:T13) -> 26284.217 | AB13: =MIN(B13:T13) -> 4748.1667
A14: Avg Exp. | B14: =(SUM(B8:B13))/6 -> 6509 | C14: =(SUM(C2:C13))/12 -> 6185.3333 | D14: =SUM(D2:D13)/12 -> 6597.5 | E14: =SUM(E2:E13)/12 -> 6847.75 | F14: =SUM(F2:F13)/12 -> 6795.6667 | G14: =SUM(G2:G10)/9 -> 7789 | H14: =SUM(H2:H13)/12 -> 6875.5472 | I14: =SUM(I2:I13)/12 -> 6919.1406 | J14: =SUM(J2:J13)/12 -> 9930.6999 | K14: =SUM(K2:K13)/12 -> 8062.943 | L14: =SUM(L2:L13)/12 -> 9822.0332 | M14: =SUM(M2:M13)/12 -> 11127.9 | N14: =SUM(N2:N13)/12 -> 9756.3333 | O14: =SUM(O2:O13)/12 -> 8969.25 | ... W14: =SUM(W2:W13)/12 -> 21493.3 | X14: =(SUM(B14:T14))/($B$34-1) -> 7788.4758 | Z14: =MEDIAN(B14:T14) -> 8969.25 | AA14: =MAX(B14:T14) -> 28718.126 | AB14: =MIN(B14:T14) -> 6185.3333
A15: Expenses | B15: =SUM(B8:B13) + 5000*6 -> 69054 | C15: =SUM(C2:C13) -> 74224 | D15: =SUM(D2:D13) -> 79170 | E15: =SUM(E2:E13) -> 82173 | F15: =SUM(F2:F13) -> 81548 | G15: =SUM(G2:G13) -> 89971 | H15: =SUM(H2:H13) -> 82506.566 | I15: =SUM(I2:I13) -> 83029.687 | J15: =SUM(J2:J13) -> 119168.4 | ... W15: =SUM(W2:W13) -> 257919.6 | X15: =(SUM(B15:T15))/($B$34-1) -> 92938.751 | Z15: =MEDIAN(B15:T15) -> 107631 | AA15: =MAX(B15:T15) -> 344617.52 | AB15: =MIN(B15:T15) -> 69054
A16: Non Opex | B16: =FinSnapshot!B91 -> 1514 | C16: =FinSnapshot!C91 -> 1814 | D16: =FinSnapshot!D91 -> 956 | E16: =FinSnapshot!E91 -> 1796 | F16: =FinSnapshot!F91 -> 2018 | G16: =FinSnapshot!G91 -> 2516 | H16: =FinSnapshot!H91 -> 2478 | I16: =FinSnapshot!I91 -> 3852 | ... Q16: =FinSnapshot!Q91 -> 2945 | R16: =FinSnapshot!Q91 -> 2945 | S16: =FinSnapshot!S91 -> 5732 | T16: =FinSnapshot!T91 -> 5732 | U16: =FinSnapshot!U91 -> 5732 | V16: =FinSnapshot!V91 -> 5732 | W16: =FinSnapshot!X91 -> 5732 | X16: =(SUM(B16:T16))/($B$34-1) -> 3092.6667 | Z16: =MEDIAN(B16:T16) -> 3852 | AA16: =MAX(B16:T16) -> 6662 | AB16: =MIN(B16:T16) -> 956
A17: Total Expenses | B17: =B15+B16 -> 70568 | C17: =C15+C16 -> 76038 | D17: =D15+D16 -> 80126 | E17: =E15+E16 -> 83969 | F17: =F15+F16 -> 83566 | G17: =G15+G16 -> 92487 | H17: =H15+H16 -> 84984.566 | I17: =I15+I16 -> 86881.687 | ... W17: =W15+W16 -> 263651.6 | X17: =(SUM(B17:T17))/($B$34-1) -> 96031.417 | Z17: =MEDIAN(B17:T17) -> 113595 | AA17: =MAX(B17:T17) -> 350349.52 | AB17: =MIN(B17:T17) -> 70568
A18: IPM | B18: =FinSnapshot!B109/12 -> 7157.6533 | C18: =FinSnapshot!C109/12 -> 7849.6667 | D18: =FinSnapshot!D109/12 -> 8553.75 | E18: =FinSnapshot!E109/12 -> 8587.1667 | F18: =FinSnapshot!F109/12 -> 10583.583 | G18: =FinSnapshot!G109/12 -> 11583.333 | H18: =FinSnapshot!H109/12 -> 11994.618 | I18: =FinSnapshot!I109/12 -> 12089.167 | ... V18: =FinSnapshot!V109/12 -> 41486.966 | W18: =FinSnapshot!X109/12 -> 84731.63 | X18: =(SUM(B18:T18))/($B$34-1) -> 13449.524 | Z18: =MEDIAN(B18:T18) -> 14836.75 | AA18: =MAX(B18:T18) -> 43349.583 | AB18: =MIN(B18:T18) -> 7157.6533
A19: EPD | B19: =B17/365 -> 193.33699 | C19: =C17/365 -> 208.32329 | D19: =D17/365 -> 219.52329 | E19: =E17/365 -> 230.05205 | F19: =F17/365 -> 228.94795 | G19: =G17/365 -> 253.38904 | H19: =H17/365 -> 232.83443 | I19: =I17/365 -> 238.03202 | ... W19: =W17/365 -> 722.33315 | X19: =(SUM(B19:T19))/($B$34-1) -> 263.09977 | Z19: =MEDIAN(B19:T19) -> 311.21918 | AA19: =MAX(B19:T19) -> 959.86169 | AB19: =MIN(B19:T19) -> 193.33699
A20: IPD | B20: =FinSnapshot!B89/365 -> 239.46805 | C20: =FinSnapshot!C89/365 -> 263.0411 | D20: =FinSnapshot!D89/365 -> 283.83836 | E20: =FinSnapshot!E89/365 -> 287.23836 | F20: =FinSnapshot!F89/365 -> 353.48219 | G20: =FinSnapshot!G89/365 -> 387.71507 | H20: =FinSnapshot!H89/365 -> 401.13266 | I20: =FinSnapshot!I89/365 -> 408.00548 | ... V20: =FinSnapshot!V89/365 -> 1365.7961 | W20: =FinSnapshot!X89/365 -> 2695.1714 | X20: =(SUM(B20:T20))/($B$34-1) -> 428.82818 | Z20: =MEDIAN(B20:T20) -> 461.62405 | AA20: =MAX(B20:T20) -> 1393.6164 | AB20: =MIN(B20:T20) -> 239.46805
A21: EPH | B21: =B19/24 -> 8.0557078 | C21: =C19/24 -> 8.680137 | D21: =D19/24 -> 9.1468037 | E21: =E19/24 -> 9.5855023 | F21: =F19/24 -> 9.5394977 | G21: =G19/24 -> 10.557877 | H21: =H19/24 -> 9.7014345 | I21: =I19/24 -> 9.9180008 | ... W21: =W19/24 -> 30.097215 | X21: =(SUM(B21:T21))/($B$34-1) -> 10.962491 | Z21: =MEDIAN(B21:T21) -> 12.967466 | AA21: =MAX(B21:T21) -> 39.994237 | AB21: =MIN(B21:T21) -> 8.0557078
A22: IPH | B22: =B20/24 -> 9.9778356 | C22: =C20/24 -> 10.960046 | D22: =D20/24 -> 11.826598 | E22: =E20/24 -> 11.968265 | F22: =F20/24 -> 14.728425 | G22: =G20/24 -> 16.154795 | H22: =H20/24 -> 16.713861 | I22: =I20/24 -> 17.000228 | ... W22: =W20/24 -> 112.29881 | X22: =(SUM(B22:T22))/($B$34-1) -> 17.867841 | Z22: =MEDIAN(B22:T22) -> 19.234336 | AA22: =MAX(B22:T22) -> 58.067352 | AB22: =MIN(B22:T22) -> 9.9778356
A23: Net Income | B23: ='Financials & Forecast'!B12 -> 17146.84 | C23: ='Financials & Forecast'!C12 -> 20561 | D23: ='Financials & Forecast'!D12 -> 24430 | E23: ='Financials & Forecast'!E12 -> 22428 | F23: ='Financials & Forecast'!F12 -> 48756 | G23: ='Financials & Forecast'!G12 -> 54104 | H23: ='Financials & Forecast'!H12 -> 53897.854 | I23: ='Financials & Forecast'!I12 -> 68094.313 | ... V23: ='Financials & Forecast'!V12 -> 0 | X23: =(SUM(B23:T23))/($B$34-1) -> 68805.159 | Z23: =MEDIAN(B23:T23) -> 65061.601 | AA23: =MAX(B23:T23) -> 386376.5 | AB23: =MIN(B23:T23) -> 17146.84
A24: % Savings | B24: =B23/FinSnapshot!B60 -> 0.14723646 | C24: =C23/FinSnapshot!C60 -> 0.14833492 | D24: =D23/FinSnapshot!D60 -> 0.16717419 | E24: =E23/FinSnapshot!E60 -> 0.14013997 | F24: =F23/FinSnapshot!F60 -> 0.26554977 | G24: =G23/FinSnapshot!G60 -> 0.27564282 | H24: =H23/FinSnapshot!H60 -> 0.26291123 | I24: =I23/FinSnapshot!I60 -> 0.31878017 | ... V24: =V23/FinSnapshot!V60 -> 0 | W24: =W23/FinSnapshot!X60 -> 0 | X24: =(SUM(B24:T24))/($B$34-1) -> 0.20164054 | Z24: =MEDIAN(B24:T24) -> 0.26291123 | AA24: =MAX(B24:T24) -> 0.4707924 | AB24: =MIN(B24:T24) -> 0.062466287
A25: ExpTaxes:Earn | B25: =(B17+ FinSnapshot!B85)/FinSnapshot!B60 -> 0.85541686 | C25: =(C17+ FinSnapshot!C85)/FinSnapshot!C60 -> 0.85591435 | D25: =(D17+ FinSnapshot!D85)/FinSnapshot!D60 -> 0.83936086 | E25: =(E17+ FinSnapshot!E85)/FinSnapshot!E60 -> 0.86957636 | F25: =(F17+ FinSnapshot!F85)/FinSnapshot!F60 -> 0.75242914 | G25: =(G17+ FinSnapshot!G85)/FinSnapshot!G60 -> 0.7502127 | H25: =(H17+ FinSnapshot!H85)/FinSnapshot!H60 -> 0.7003529 | I25: =(I17+ FinSnapshot!I85)/FinSnapshot!I60 -> 0.70956133 | J25: =(J17+ FinSnapshot!J85)/FinSnapshot!J60 -> 0.81076205 | K25: =K17/FinSnapshot!K60 -> 0.41939537 | L25: =L17/FinSnapshot!L60 -> 0.48297483 | M25: =M17/FinSnapshot!M60 -> 0.50600362 | N25: =N17/FinSnapshot!N60 -> 0.41648184 | O25: =O17/FinSnapshot!O60 -> 0.33156549 | P25: =P17/FinSnapshot!P60 -> 0.32391831 | Q25: =Q17/FinSnapshot!Q60 -> 0.16664372 | R25: =R17/FinSnapshot!R60 -> 0.2935595 | ... V25: =V17/FinSnapshot!V60 -> 0.40345959 | W25: =W17/FinSnapshot!X60 -> 0.2680101 | X25: =(SUM(B25:T25))/($B$34-1) -> 0.45863594 | Z25: =MEDIAN(B25:T25) -> 0.63154305 | AA25: =MAX(B25:T25) -> 0.86957636 | AB25: =MIN(B25:T25) -> 0.16664372
A26: NS/M | B26: =B23/12 -> 1428.9033 | C26: =C23/12 -> 1713.4167 | D26: =D23/12 -> 2035.8333 | E26: =E23/12 -> 1869 | F26: =F23/12 -> 4063 | G26: =IF(YEAR(TODAY())=2007,G23/MONTH(TODAY()),G23/12) -> 4508.6667 | H26: =IF(YEAR(TODAY())=2007,H23/MONTH(TODAY()),H23/12) -> 4491.4878 | I26: =IF(YEAR(TODAY())=2007,I23/MONTH(TODAY()),I23/12) -> 5674.5261 | J26: =IF(YEAR(TODAY())=2007,J23/MONTH(TODAY()),J23/12) -> 4280.1151 | K26: =IF(YEAR(TODAY())=2007,K23/MONTH(TODAY()),K23/12) -> 6491.6404 | L26: =IF(YEAR(TODAY())=2007,L23/MONTH(TODAY()),L23/12) -> 5421.8001 | M26: =IF(YEAR(TODAY())=2013,M23/MONTH(TODAY()),M23/12) -> 5598.9334 | N26: =IF(YEAR(TODAY())=2013,N23/MONTH(TODAY()),N23/12) -> 6547.1667 | O26: =IF(YEAR(TODAY())=2013,O23/MONTH(TODAY()),O23/12) -> 10413.75 | P26: =IF(YEAR(TODAY())=2013,P23/MONTH(TODAY()),P23/12) -> 5560.25 | Q26: =IF(YEAR(TODAY())=2013,Q23/MONTH(TODAY()),Q23/12) -> 32198.042 | R26: =IF(YEAR(TODAY())=2013,R23/MONTH(TODAY()),R23/12) -> 15682.972 | S26: =IF(YEAR(TODAY())=2013,S23/MONTH(TODAY()),S23/12) -> 16743.042 | T26: =IF(YEAR(TODAY())=2013,T23/MONTH(TODAY()),T23/12) -> 2887.7727 | ... W26: =IF(YEAR(TODAY())=2013,W23/MONTH(TODAY()),W23/12) -> 0 | X26: =(SUM(B26:T26))/($B$34-1) -> 5733.7632 | Z26: =MEDIAN(B26:T26) -> 5421.8001 | AA26: =MAX(B26:T26) -> 32198.042 | AB26: =MIN(B26:T26) -> 1428.9033
A27: Gross Inc/M | B27: =FinSnapshot!B64/12 -> 9730.57 | C27: =FinSnapshot!C64/12 -> 11600.083 | D27: =FinSnapshot!D64/12 -> 12257.5 | E27: =FinSnapshot!E64/12 -> 13466.25 | F27: =FinSnapshot!F64/12 -> 15575.417 | G27: =FinSnapshot!G64/12 -> 16779.833 | H27: =FinSnapshot!H64/12 -> 17433 | I27: =FinSnapshot!I64/12 -> 18176.083 | ... V27: =FinSnapshot!V64/12 -> 63530.202 | W27: =FinSnapshot!X64/12 -> 85209.297 | X27: =(SUM(B27:T27))/($B$34-1) -> 21605.338 | Z27: =MEDIAN(B27:T27) -> 20519.583 | AA27: =MAX(B27:T27) -> 76181.5 | AB27: =MIN(B27:T27) -> 9730.57
A28: Pass. Inc/M | B28: =FinSnapshot!B52/12 -> 25.75 | C28: =FinSnapshot!C52/12 -> 49.083333 | D28: =FinSnapshot!D52/12 -> 79.583333 | E28: =FinSnapshot!E52/12 -> 129.58333 | F28: =FinSnapshot!F52/12 -> 275.08333 | G28: =FinSnapshot!G52/12 -> 422.91667 | H28: =FinSnapshot!H52/12 -> -627.58333 | I28: =FinSnapshot!I52/12 -> 504.5 | ... V28: =FinSnapshot!V52/12 -> 421.66667 | W28: =FinSnapshot!X52/12 -> 3231.1667 | X28: =(SUM(B28:T28))/($B$34-1) -> 702.53472 | Z28: =MEDIAN(B28:T28) -> 504.5 | AA28: =MAX(B28:T28) -> 3942.75 | AB28: =MIN(B28:T28) -> -627.58333
A29: %Housing/Gross I
A30: Exp YoY | C30: =(C15-B15)/B15 -> 0.074868943 | D30: =(D15-C15)/C15 -> 0.066636128 | E30: =(E15-D15)/D15 -> 0.037931034 | F30: =(F15-E15)/E15 -> -0.0076059046 | G30: =(G15-F15)/F15 -> 0.10328886 | H30: =(H15-G15)/G15 -> -0.082964886 | I30: =(I15-H15)/H15 -> 0.0063403496 | J30: =(J15-I15)/I15 -> 0.43525049 | ... W30: =(W15-V15)/V15 -> -0.13972007
A31: Gross Inc YoY | C31: =(C27-B27)/B27 -> 0.19212783 | D31: =(D27-C27)/C27 -> 0.056673443 | E31: =(E27-D27)/D27 -> 0.098613094 | F31: =(F27-E27)/E27 -> 0.15662613 | G31: =(G27-F27)/F27 -> 0.077328054 | H31: =(H27-G27)/G27 -> 0.038925695 | I31: =(I27-H27)/H27 -> 0.042625098 | J31: =(J27-I27)/I27 -> 0.090759285 | ... W31: =(W27-V27)/V27 -> 0.34124077
A34: Years | B34: =YEAR(TODAY()) - 2002 + 1 -> 25

Sheet TripCompare
A2: Trip | B2: Santa Barbara | C2: LA | D2: Yosemite | E2: Tahoe | F2: Europe - Rome-Paris-London | G2: Oahu | H2: Death Valley | I2: Folsom, CA | J2: Tahoe2 | K2: Banff, AL, CAN | L2: Costa Rica | M2: Las Vegas | N2: Yellow Stone | O2: Tahoe | P2: Ger-FRA-Swiss | Q2: Japan | R2: Solvang, Santab Barbaba | S2: Denmark-Norway
A3: Year | B3: 2021 | C3: 2021 | D3: 2022 | E3: 2022 | F3: 2022 | G3: 2023 | H3: 2023 | I3: 2023 | J3: 2023 | K3: 2023 | L3: 2023 | M3: 2023 | N3: 2024 | O3: 2024 | P3: 2024 | Q3: 2024 | R3: 2024 | S3: 2025
A4: Dates | B4: Aug 4 - Aug 7 | C4: Dec 21 - Dec 25 | D4: Apr 13 -Apr 16 | E4: Jun 24 - Jun 29 | F4: Aug 7 - Aug 15 | G4: Jan 2- Jan 7 | H4: Feb 22- Feb 24 | I4: May27-May28 | J4: Jun 26- June 30 | K4: Aug 3-7 | L4: Nov 18-Nov 23 | M4: Dec 28-Dec 31 | N4: Jun 8 -Jun 12 | O4: Jul 3 -Jul 6 | P4: JUl 31- Aug 6 | Q4: Nov 24 - Nov 29 | R4: Dec 21 - Dec 24 | S4: July 30- Aug 7
A5: Days | B5: 4 | C5: 5 | D5: 4 | E5: 6 | F5: 9 | G5: 5 | H5: 3 | I5: 2 | J5: 5 | K5: 5 | L5: 6 | M5: 4 | N5: 5 | O5: 4 | P5: 7 | Q5: 5 | R5: 4 | S5: 8
A6: Nights | B6: 3 | C6: 4 | D6: 3 | E6: 5 | F6: 8 | G6: 4 | H6: 2 | I6: 1 | J6: 4 | K6: 4 | L6: 5 | M6: 3 | N6: 4 | O6: 3 | P6: 5 | Q6: 4 | R6: 3 | S6: 7
A7: Airfare | B7: - | C7: - | D7: - | E7: - | F7: =Aug!CE11 -> 4562 | G7: 2415 | H7: - | I7: - | K7: 1054 | L7: =Nov!CI12 -> 4053 | M7: =Dec!CI103 -> 1262 | N7: =Jun!CM16 -> 1385 | O7: 0 | P7: =Aug!CM11 -> 6100 | Q7: 5100 | R7: - | S7: 5800
A8: Transportation | B8: 150 | C8: 325 | D8: 225 | E8: 200 | F8: =Aug!CE23 -> 859 | G8: 125 | H8: =177 -> 177 | I8: 175 | J8: =Jun!CI84 -> 34 | K8: =1036-710 -> 326 | L8: =148 -> 148 | M8: =Dec!CI107 -> 197 | N8: =130 -> 130 | O8: =Jul!CM15 -> 288 | P8: =Aug!CM19 -> 1010 | Q8: 500 | R8: 200 | S8: 544
A9: Car Rentals | B9: - | C9: - | D9: - | E9: - | F9: 0 | G9: 469 | H9: - | I9: 0 | J9: - | K9: 605 | L9: 500 | M9: 0 | N9: 899 | O9: 0 | P9: =Aug!CM21 -> 700 | Q9: 899 | R9: 0 | S9: -
A10: Stays | B10: 495 | C10: 490 | D10: 1000 | E10: 1500 | F10: =Aug!CE15 -> 1441 | G10: 1000 | H10: =204 + 155 -> 359 | I10: 210 | J10: =Jun!CI79 -> 1300 | K10: 905 | L10: =1399 + 150 + 150 -> 1699 | M10: =Dec!CI104 -> 930 | N10: =Jun!CM17 -> 1330 | O10: =Jul!CM11 -> 1119 | P10: =Aug!CM13 -> 1254 | Q10: 1000 | R10: 520 | S10: 1931
A11: Food | B11: 180 | C11: 322 | D11: 271 | E11: 390 | F11: =Aug!CE19 -> 677 | G11: 622 | H11: 34 | I11: 102 | J11: =Jun!CI80 -> 414 | K11: 653 | L11: =Nov!CI15 -> 306 | M11: =Dec!CI106 -> 1008 | N11: =Jun!CM20 -> 548 | O11: =Jul!CM14 -> 478 | P11: =Aug!CM18 -> 732 | Q11: 1200 | R11: 240 | S11: =Aug!CQ17 -> 1194
A12: EET | B12: 50 | C12: 1240 | D12: 35 | E12: 620 | F12: =Aug!CE27 -> 416 | G12: 322 | H12: 30 | I12: 758 | J12: =Jun!CI82 -> 614 | K12: 65 | L12: =Nov!CI17 -> 900 | M12: =Dec!CI105 -> 512 | N12: 35 | O12: =Jul!CM20 -> 596 | P12: =Aug!CM24 -> 1004 | Q12: 1500 | R12: - | S12: =Aug!CQ22 -> 1756
A13: Pet boarding | B13: - | C13: - | D13: - | E13: 85 | F13: =Aug!CE32+Aug!CE31 -> 508 | G13: 294 | H13: 190 | I13: 98 | J13: =Jun!CI83 -> 80 | K13: 390 | L13: 390 | M13: 390 | N13: 450 | O13: =Jul!CM21 -> 450 | P13: =Aug!CM26 -> 311 | Q13: =Aug!CM26 -> 311 | R13: 200 | S13: 450
A14: Total | B14: =SUM(B7:B13) -> 875 | C14: =SUM(C7:C13) -> 2377 | D14: =SUM(D7:D13) -> 1531 | E14: =SUM(E7:E13) -> 2795 | F14: =SUM(F7:F13) -> 8463 | G14: =SUM(G7:G13) -> 5247 | H14: =SUM(H7:H13) -> 790 | I14: =SUM(I7:I13) -> 1343 | ... O14: =SUM(O7:O13) -> 2931 | P14: =SUM(P7:P13)-P9 -> 10411 | Q14: =SUM(Q7:Q13) -> 10510 | R14: =SUM(R7:R13) -> 1160 | S14: =SUM(S7:S13) -> 11675
A15: Price Per Night (PPN) | B15: =B14/7 -> 125 | C15: =C14/7 -> 339.57143 | D15: =D14/7 -> 218.71429 | E15: =E14/7 -> 399.28571 | F15: =F14/F6 -> 1057.875 | G15: =G14/G6 -> 1311.75 | H15: =H14/H6 -> 395 | I15: =I14/I6 -> 1343 | J15: =J14/J6 -> 610.5 | K15: =K14/K6 -> 999.5 | L15: =L14/L6 -> 1599.2 | M15: =M14/M6 -> 1433 | ... S15: =S14/S6 -> 1667.8571
A18: Year | B18: 2021 | C18: 2022 | D18: 2023 | E18: 2024 | CQ18: {=TripCompare!S2:S16} -> Denmark-Norway
A19: Trips | B19: 2 | C19: 3 | D19: 7 | E19: 5 | CQ19: 2025
A20: Days | B20: =B5+C5 -> 9 | C20: =SUM(D5:F5) -> 19 | D20: =SUM(G5:M5) -> 30 | E20: 25 | CQ20: July 30- Aug 7
A21: Nights | B21: =B6+C6 -> 7 | C21: =SUM(D6:F6) -> 16 | D21: =SUM(G6:M6) -> 23 | E21: 19 | CQ21: 8
A22: Airfare | B22: - | C22: =SUM(D7:F7) -> 4562 | D22: =SUM(G7:M7) -> 8784 | E22: =SUM(N7:R7) -> 12585 | CQ22: 7
A23: Transportation | B23: =B8+C8 -> 475 | C23: =SUM(D8:F8) -> 1284 | D23: =SUM(G8:M8) -> 1182 | E23: =SUM(N8:R8) -> 2128 | CQ23: 5800
A24: Car Rentals | B24: - | C24: =SUM(D9:F9) -> 0 | D24: =SUM(G9:M9) -> 1574 | E24: =SUM(N9:R9) -> 2498 | CQ24: 544
A25: Stays | B25: =B10+C10 -> 985 | C25: =SUM(D10:F10) -> 3941 | D25: =SUM(G10:M10) -> 6403 | E25: =SUM(N10:R10) -> 5223 | CQ25: -
A26: Food | B26: =B11+C11 -> 502 | C26: =SUM(D11:F11) -> 1338 | D26: =SUM(G11:M11) -> 3139 | E26: =SUM(N11:R11) -> 3198 | CQ26: 1931
A27: EET | B27: =B12+C12 -> 1290 | C27: =SUM(D12:F12) -> 1071 | D27: =SUM(G12:M12) -> 3201 | E27: =SUM(N12:R12) -> 3135 | CQ27: 1194
A28: Pet boarding | B28: - | C28: =SUM(D13:F13) -> 593 | D28: =SUM(G13:M13) -> 1832 | E28: =SUM(N13:R13) -> 1722 | CQ28: 1756
A29: Total | B29: =B14+C14 -> 3252 | C29: =SUM(D14:F14) -> 12789 | D29: =SUM(G14:M14) -> 26115 | E29: =SUM(N14:R14) -> 29789 | CQ29: 450
A30: Price Per Night (PPN) | B30: =B29/B21 -> 464.57143 | C30: =C29/C21 -> 799.3125 | D30: =D29/D21 -> 1135.4348 | E30: =E29/E21 -> 1567.8421 | CQ30: 11675
CQ31: 1667.8571
CQ32: 0

Sheet APM-Yearly
A1: Analysis | C1: APM
C2: APM
C3: Yearly
A4: Categories | C4: 2002 | D4: 2003 | E4: 2004 | F4: 2005 | G4: 2006 | H4: 2007 | I4: 2008 | J4: 2009 | K4: 2010 | L4: 2011 | M4: 2012 | N4: 2013 | O4: 2014 | P4: 2015 | Q4: 2016 | R4: 2017 | S4: 2018 | T4: 2019 | U4: 2020 | V4: 2021 | W4: 2022 | X4: 2023 | Y4: 2024 | Z4: Delta 15-18 | AA4: Delta 15-18 % | AB4: New House
AD5: Fixed:
A6: Home | C6: =SUM(C14:C19)+C8 -> 1075 | D6: =SUM(D14:D19)+D8 -> 1075.25 | E6: =SUM(E14:E19)+E8 -> 1672.9167 | F6: =SUM(F14:F19)+F8 -> 2662.25 | G6: =SUM(G14:G19)+G8 -> 2629.9167 | H6: =SUM(H14:H19)+H8 -> 2544.5 | I6: =SUM(I14:I19)+I8 -> 2585.1305 | J6: =SUM(J14:J19)+J8 -> 2624.8072 | ... U6: =SUM(U14:U19)+U8 -> 4746.1667 | V6: 4746.1667 | Z6: =S6-P6 -> 2811.6667 | AA6: =(S6-P6)/P6 -> 1.6475414 | AB6: =SUM(AB14:AB19)+AB8 -> 13192 | AD6: =AB6+AB20+AB38+AB57+AB61+AB72 -> 19202.333
B8: Mortgage/Rent | C8: =IF($C$1="APM",Monthly!O1870,IF($C$1="Yearly",Monthly!O1870*12,0)) -> 1075 | D8: =IF($C$1="APM",Monthly!O1793,IF($C$1="Yearly",Monthly!O1793*12,0)) -> 1075 | E8: =IF($C$1="APM",Monthly!O1716,IF($C$1="Yearly",Monthly!O1716*12,0)) -> 1378.75 | F8: =IF($C$1="APM",Monthly!O1638,IF($C$1="Yearly",Monthly!O1638*12,0)) -> 2045.0833 | G8: =IF($C$1="APM",Monthly!O1560,IF($C$1="Yearly",Monthly!O1560*12,0)) -> 1978.0833 | H8: =IF($C$1="APM",Monthly!O1482,IF($C$1="Yearly",Monthly!O1482*12,0)) -> 1894 | I8: =IF($C$1="APM",Monthly!O1405,IF($C$1="Yearly",Monthly!O1405*12,0)) -> 1895.2972 | J8: =IF($C$1="APM",Monthly!O1328,IF($C$1="Yearly",Monthly!O1328*12,0)) -> 1892.7239 | K8: =IF($C$1="APM",Monthly!O1251,IF($C$1="Yearly",Monthly!O1251*12,0)) -> 1755.4499 | L8: =IF($C$1="APM",Monthly!O1173,IF($C$1="Yearly",Monthly!O1173*12,0)) -> 1755.4499 | M8: =IF($C$1="APM",Monthly!O1096,IF($C$1="Yearly",Monthly!O1096*12,0)) -> 1755.4499 | N8: =IF($C$1="APM",Monthly!O1019,IF($C$1="Yearly",Monthly!O1019*12,0)) -> 2688.9 | O8: =IF($C$1="APM",Monthly!O942,IF($C$1="Yearly",Monthly!O942*12,0)) -> 1057 | P8: =IF($C$1="APM",Monthly!$O866,IF($C$1="Yearly",Monthly!$O866*12,0)) -> 1057 | Q8: =IF($C$1="APM",Monthly!$O789,IF($C$1="Yearly",Monthly!$O789*12,0)) -> 2446 | R8: =IF($C$1="APM",Monthly!$O712,IF($C$1="Yearly",Monthly!$O712*12,0)) -> 4296.8333 | S8: =IF($C$1="APM",Monthly!$O635,IF($C$1="Yearly",Monthly!$O635*12,0)) -> 4487 | T8: =IF($C$1="APM",Monthly!$O558,IF($C$1="Yearly",Monthly!$O558*12,0)) -> 4742 | U8: =IF($C$1="APM",Monthly!$O558,IF($C$1="Yearly",Monthly!$O558*12,0)) -> 4742 | Z8: =S8-P8 -> 3430 | AA8: =T8-Q8 -> 2296 | AB8: 9242
B9: Interest | C9: =IF($C$1="APM",Monthly!O1871,IF($C$1="Yearly",Monthly!O1871*12,0)) -> 0 | D9: =IF($C$1="APM",Monthly!O1794,IF($C$1="Yearly",Monthly!O1794*12,0)) -> 0 | E9: =IF($C$1="APM",Monthly!O1717,IF($C$1="Yearly",Monthly!O1717*12,0)) -> 899.5 | F9: =IF($C$1="APM",Monthly!O1639,IF($C$1="Yearly",Monthly!O1639*12,0)) -> 856.25 | G9: =IF($C$1="APM",Monthly!O1561,IF($C$1="Yearly",Monthly!O1561*12,0)) -> 837 | H9: =IF($C$1="APM",Monthly!O1483,IF($C$1="Yearly",Monthly!O1483*12,0)) -> 820.5 | I9: =IF($C$1="APM",Monthly!O1406,IF($C$1="Yearly",Monthly!O1406*12,0)) -> 966.11935 | J9: =IF($C$1="APM",Monthly!O1329,IF($C$1="Yearly",Monthly!O1329*12,0)) -> 902.71852 | K9: =IF($C$1="APM",Monthly!O1252,IF($C$1="Yearly",Monthly!O1252*12,0)) -> 982.2046 | L9: =IF($C$1="APM",Monthly!O1174,IF($C$1="Yearly",Monthly!O1174*12,0)) -> 967.14758 | M9: =IF($C$1="APM",Monthly!O1097,IF($C$1="Yearly",Monthly!O1097*12,0)) -> 951.24123 | N9: =IF($C$1="APM",Monthly!O1020,IF($C$1="Yearly",Monthly!O1020*12,0)) -> 751.72535 | O9: =IF($C$1="APM",Monthly!O943,IF($C$1="Yearly",Monthly!O943*12,0)) -> 657 | P9: =IF($C$1="APM",Monthly!$O867,IF($C$1="Yearly",Monthly!$O867*12,0)) -> 657 | Q9: =IF($C$1="APM",Monthly!$O790,IF($C$1="Yearly",Monthly!$O790*12,0)) -> 383.25 | R9: =IF($C$1="APM",Monthly!$O713,IF($C$1="Yearly",Monthly!$O713*12,0)) -> 0 | S9: =IF($C$1="APM",Monthly!$O636,IF($C$1="Yearly",Monthly!$O636*12,0)) -> 0 | T9: =IF($C$1="APM",Monthly!$O559,IF($C$1="Yearly",Monthly!$O559*12,0)) -> 0 | U9: =IF($C$1="APM",Monthly!$O559,IF($C$1="Yearly",Monthly!$O559*12,0)) -> 0 | Z9: =S9-P9 -> -657 | AA9: =IF($C$1="APM",Monthly!$O559,IF($C$1="Yearly",Monthly!$O559*12,0)) -> 0 | AB9: =IF($C$1="APM",Monthly!$O559,IF($C$1="Yearly",Monthly!$O559*12,0)) -> 0
B10: Principle | C10: =IF($C$1="APM",Monthly!O1872,IF($C$1="Yearly",Monthly!O1872*12,0)) -> 0 | D10: =IF($C$1="APM",Monthly!O1795,IF($C$1="Yearly",Monthly!O1795*12,0)) -> 0 | E10: =IF($C$1="APM",Monthly!O1718,IF($C$1="Yearly",Monthly!O1718*12,0)) -> 177.16667 | F10: =IF($C$1="APM",Monthly!O1640,IF($C$1="Yearly",Monthly!O1640*12,0)) -> 446 | G10: =IF($C$1="APM",Monthly!O1562,IF($C$1="Yearly",Monthly!O1562*12,0)) -> 431.75 | H10: =IF($C$1="APM",Monthly!O1484,IF($C$1="Yearly",Monthly!O1484*12,0)) -> 363.5 | I10: =IF($C$1="APM",Monthly!O1407,IF($C$1="Yearly",Monthly!O1407*12,0)) -> 281.22315 | J10: =IF($C$1="APM",Monthly!O1330,IF($C$1="Yearly",Monthly!O1330*12,0)) -> 346.41729 | K10: =IF($C$1="APM",Monthly!O1253,IF($C$1="Yearly",Monthly!O1253*12,0)) -> 266.9312 | L10: =IF($C$1="APM",Monthly!O1175,IF($C$1="Yearly",Monthly!O1175*12,0)) -> 281.98822 | M10: =IF($C$1="APM",Monthly!O1098,IF($C$1="Yearly",Monthly!O1098*12,0)) -> 297.89457 | N10: =IF($C$1="APM",Monthly!O1021,IF($C$1="Yearly",Monthly!O1021*12,0)) -> 369.31992 | O10: =IF($C$1="APM",Monthly!O944,IF($C$1="Yearly",Monthly!O944*12,0)) -> 400 | P10: =IF($C$1="APM",Monthly!$O868,IF($C$1="Yearly",Monthly!$O868*12,0)) -> 400 | Q10: =IF($C$1="APM",Monthly!$O791,IF($C$1="Yearly",Monthly!$O791*12,0)) -> 233.33333 | R10: =IF($C$1="APM",Monthly!$O714,IF($C$1="Yearly",Monthly!$O714*12,0)) -> 0 | S10: =IF($C$1="APM",Monthly!$O637,IF($C$1="Yearly",Monthly!$O637*12,0)) -> 0 | T10: =IF($C$1="APM",Monthly!$O560,IF($C$1="Yearly",Monthly!$O560*12,0)) -> 0 | U10: =IF($C$1="APM",Monthly!$O560,IF($C$1="Yearly",Monthly!$O560*12,0)) -> 0 | Z10: =S10-P10 -> -400 | AA10: =IF($C$1="APM",Monthly!$O560,IF($C$1="Yearly",Monthly!$O560*12,0)) -> 0 | AB10: =IF($C$1="APM",Monthly!$O560,IF($C$1="Yearly",Monthly!$O560*12,0)) -> 0
B11: Mortgage Exp | C11: =IF($C$1="APM",Monthly!O1873,IF($C$1="Yearly",Monthly!O1873*12,0)) -> 0 | D11: =IF($C$1="APM",Monthly!O1796,IF($C$1="Yearly",Monthly!O1796*12,0)) -> 0 | E11: =IF($C$1="APM",Monthly!O1719,IF($C$1="Yearly",Monthly!O1719*12,0)) -> 0 | F11: =IF($C$1="APM",Monthly!O1641,IF($C$1="Yearly",Monthly!O1641*12,0)) -> 0 | G11: =IF($C$1="APM",Monthly!O1563,IF($C$1="Yearly",Monthly!O1563*12,0)) -> 0 | H11: =IF($C$1="APM",Monthly!O1485,IF($C$1="Yearly",Monthly!O1485*12,0)) -> 0 | I11: =IF($C$1="APM",Monthly!O1408,IF($C$1="Yearly",Monthly!O1408*12,0)) -> 58.833333 | J11: =IF($C$1="APM",Monthly!O1331,IF($C$1="Yearly",Monthly!O1331*12,0)) -> 0 | K11: =IF($C$1="APM",Monthly!O1254,IF($C$1="Yearly",Monthly!O1254*12,0)) -> 0 | L11: =IF($C$1="APM",Monthly!O1176,IF($C$1="Yearly",Monthly!O1176*12,0)) -> 0 | M11: =IF($C$1="APM",Monthly!O1099,IF($C$1="Yearly",Monthly!O1099*12,0)) -> 0 | N11: =IF($C$1="APM",Monthly!O1022,IF($C$1="Yearly",Monthly!O1022*12,0)) -> 0 | O11: =IF($C$1="APM",Monthly!O945,IF($C$1="Yearly",Monthly!O945*12,0)) -> 0 | P11: =IF($C$1="APM",Monthly!$O869,IF($C$1="Yearly",Monthly!$O869*12,0)) -> 0 | Q11: =IF($C$1="APM",Monthly!$O792,IF($C$1="Yearly",Monthly!$O792*12,0)) -> 0 | R11: =IF($C$1="APM",Monthly!$O715,IF($C$1="Yearly",Monthly!$O715*12,0)) -> 0 | S11: =IF($C$1="APM",Monthly!$O638,IF($C$1="Yearly",Monthly!$O638*12,0)) -> 0 | T11: =IF($C$1="APM",Monthly!$O561,IF($C$1="Yearly",Monthly!$O561*12,0)) -> 0 | U11: =IF($C$1="APM",Monthly!$O561,IF($C$1="Yearly",Monthly!$O561*12,0)) -> 0 | Z11: =S11-P11 -> 0 | AA11: =IF($C$1="APM",Monthly!$O561,IF($C$1="Yearly",Monthly!$O561*12,0)) -> 0 | AB11: =IF($C$1="APM",Monthly!$O561,IF($C$1="Yearly",Monthly!$O561*12,0)) -> 0
B12: Heloc Interest | C12: =IF($C$1="APM",Monthly!O1874,IF($C$1="Yearly",Monthly!O1874*12,0)) -> 0 | D12: =IF($C$1="APM",Monthly!O1797,IF($C$1="Yearly",Monthly!O1797*12,0)) -> 0 | E12: =IF($C$1="APM",Monthly!O1720,IF($C$1="Yearly",Monthly!O1720*12,0)) -> 149.75 | F12: =IF($C$1="APM",Monthly!O1642,IF($C$1="Yearly",Monthly!O1642*12,0)) -> 283.16667 | G12: =IF($C$1="APM",Monthly!O1564,IF($C$1="Yearly",Monthly!O1564*12,0)) -> 255.66667 | H12: =IF($C$1="APM",Monthly!O1486,IF($C$1="Yearly",Monthly!O1486*12,0)) -> 231 | I12: =IF($C$1="APM",Monthly!O1409,IF($C$1="Yearly",Monthly!O1409*12,0)) -> 197.57011 | J12: =IF($C$1="APM",Monthly!O1332,IF($C$1="Yearly",Monthly!O1332*12,0)) -> 177.77422 | K12: =IF($C$1="APM",Monthly!O1255,IF($C$1="Yearly",Monthly!O1255*12,0)) -> 157.5106 | L12: =IF($C$1="APM",Monthly!O1177,IF($C$1="Yearly",Monthly!O1177*12,0)) -> 135.99716 | M12: =IF($C$1="APM",Monthly!O1100,IF($C$1="Yearly",Monthly!O1100*12,0)) -> 113.15682 | N12: =IF($C$1="APM",Monthly!O1023,IF($C$1="Yearly",Monthly!O1023*12,0)) -> 32.402276 | O12: =IF($C$1="APM",Monthly!O946,IF($C$1="Yearly",Monthly!O946*12,0)) -> 0 | P12: =IF($C$1="APM",Monthly!$O870,IF($C$1="Yearly",Monthly!$O870*12,0)) -> 0 | Q12: =IF($C$1="APM",Monthly!$O793,IF($C$1="Yearly",Monthly!$O793*12,0)) -> 0 | R12: =IF($C$1="APM",Monthly!$O716,IF($C$1="Yearly",Monthly!$O716*12,0)) -> 0 | S12: =IF($C$1="APM",Monthly!$O639,IF($C$1="Yearly",Monthly!$O639*12,0)) -> 0 | T12: =IF($C$1="APM",Monthly!$O562,IF($C$1="Yearly",Monthly!$O562*12,0)) -> 0 | U12: =IF($C$1="APM",Monthly!$O562,IF($C$1="Yearly",Monthly!$O562*12,0)) -> 0 | Z12: =S12-P12 -> 0 | AA12: =IF($C$1="APM",Monthly!$O562,IF($C$1="Yearly",Monthly!$O562*12,0)) -> 0 | AB12: =IF($C$1="APM",Monthly!$O562,IF($C$1="Yearly",Monthly!$O562*12,0)) -> 0
B13: Principle | C13: =IF($C$1="APM",Monthly!O1875,IF($C$1="Yearly",Monthly!O1875*12,0)) -> 0 | D13: =IF($C$1="APM",Monthly!O1798,IF($C$1="Yearly",Monthly!O1798*12,0)) -> 0 | E13: =IF($C$1="APM",Monthly!O1721,IF($C$1="Yearly",Monthly!O1721*12,0)) -> 105 | F13: =IF($C$1="APM",Monthly!O1643,IF($C$1="Yearly",Monthly!O1643*12,0)) -> 459.66667 | G13: =IF($C$1="APM",Monthly!O1565,IF($C$1="Yearly",Monthly!O1565*12,0)) -> 453.66667 | H13: =IF($C$1="APM",Monthly!O1487,IF($C$1="Yearly",Monthly!O1487*12,0)) -> 479 | I13: =IF($C$1="APM",Monthly!O1410,IF($C$1="Yearly",Monthly!O1410*12,0)) -> 391.55124 | J13: =IF($C$1="APM",Monthly!O1333,IF($C$1="Yearly",Monthly!O1333*12,0)) -> 465.81387 | K13: =IF($C$1="APM",Monthly!O1256,IF($C$1="Yearly",Monthly!O1256*12,0)) -> 348.8035 | L13: =IF($C$1="APM",Monthly!O1178,IF($C$1="Yearly",Monthly!O1178*12,0)) -> 370.31694 | M13: =IF($C$1="APM",Monthly!O1101,IF($C$1="Yearly",Monthly!O1101*12,0)) -> 393.15728 | N13: =IF($C$1="APM",Monthly!O1024,IF($C$1="Yearly",Monthly!O1024*12,0)) -> 1535.4524 | O13: =IF($C$1="APM",Monthly!O947,IF($C$1="Yearly",Monthly!O947*12,0)) -> 0 | P13: =IF($C$1="APM",Monthly!$O871,IF($C$1="Yearly",Monthly!$O871*12,0)) -> 0 | Q13: =IF($C$1="APM",Monthly!$O794,IF($C$1="Yearly",Monthly!$O794*12,0)) -> 0 | R13: =IF($C$1="APM",Monthly!$O717,IF($C$1="Yearly",Monthly!$O717*12,0)) -> 0 | S13: =IF($C$1="APM",Monthly!$O640,IF($C$1="Yearly",Monthly!$O640*12,0)) -> 0 | T13: =IF($C$1="APM",Monthly!$O563,IF($C$1="Yearly",Monthly!$O563*12,0)) -> 0 | U13: =IF($C$1="APM",Monthly!$O563,IF($C$1="Yearly",Monthly!$O563*12,0)) -> 0 | Z13: =S13-P13 -> 0 | AA13: =IF($C$1="APM",Monthly!$O563,IF($C$1="Yearly",Monthly!$O563*12,0)) -> 0 | AB13: =IF($C$1="APM",Monthly!$O563,IF($C$1="Yearly",Monthly!$O563*12,0)) -> 0
B14: Taxes | C14: =IF($C$1="APM",Monthly!O1876,IF($C$1="Yearly",Monthly!O1876*12,0)) -> 0 | D14: =IF($C$1="APM",Monthly!O1799,IF($C$1="Yearly",Monthly!O1799*12,0)) -> 0 | E14: =IF($C$1="APM",Monthly!O1722,IF($C$1="Yearly",Monthly!O1722*12,0)) -> 156 | F14: =IF($C$1="APM",Monthly!O1644,IF($C$1="Yearly",Monthly!O1644*12,0)) -> 312 | G14: =IF($C$1="APM",Monthly!O1566,IF($C$1="Yearly",Monthly!O1566*12,0)) -> 312 | H14: =IF($C$1="APM",Monthly!O1488,IF($C$1="Yearly",Monthly!O1488*12,0)) -> 312 | I14: =IF($C$1="APM",Monthly!O1411,IF($C$1="Yearly",Monthly!O1411*12,0)) -> 317.58333 | J14: =IF($C$1="APM",Monthly!O1334,IF($C$1="Yearly",Monthly!O1334*12,0)) -> 312 | K14: =IF($C$1="APM",Monthly!O1257,IF($C$1="Yearly",Monthly!O1257*12,0)) -> 308.25 | L14: =IF($C$1="APM",Monthly!O1179,IF($C$1="Yearly",Monthly!O1179*12,0)) -> 308.25 | M14: =IF($C$1="APM",Monthly!O1102,IF($C$1="Yearly",Monthly!O1102*12,0)) -> 308.25 | N14: =IF($C$1="APM",Monthly!O1025,IF($C$1="Yearly",Monthly!O1025*12,0)) -> 303 | O14: =IF($C$1="APM",Monthly!O948,IF($C$1="Yearly",Monthly!O948*12,0)) -> 303 | P14: =IF($C$1="APM",Monthly!$O872,IF($C$1="Yearly",Monthly!$O872*12,0)) -> 303 | Q14: =IF($C$1="APM",Monthly!$O795,IF($C$1="Yearly",Monthly!$O795*12,0)) -> 176.75 | R14: =IF($C$1="APM",Monthly!$O718,IF($C$1="Yearly",Monthly!$O718*12,0)) -> 0 | S14: =IF($C$1="APM",Monthly!$O641,IF($C$1="Yearly",Monthly!$O641*12,0)) -> 0 | T14: =IF($C$1="APM",Monthly!$O564,IF($C$1="Yearly",Monthly!$O564*12,0)) -> 0 | U14: =IF($C$1="APM",Monthly!$O564,IF($C$1="Yearly",Monthly!$O564*12,0)) -> 0 | Z14: =S14-P14 -> -303 | AA14: =IF($C$1="APM",Monthly!$O564,IF($C$1="Yearly",Monthly!$O564*12,0)) -> 0 | AB14: 3325
B15: Escrow | C15: =IF($C$1="APM",Monthly!O1877,IF($C$1="Yearly",Monthly!O1877*12,0)) -> 0 | D15: =IF($C$1="APM",Monthly!O1800,IF($C$1="Yearly",Monthly!O1800*12,0)) -> 0 | E15: =IF($C$1="APM",Monthly!O1723,IF($C$1="Yearly",Monthly!O1723*12,0)) -> 0 | F15: =IF($C$1="APM",Monthly!O1645,IF($C$1="Yearly",Monthly!O1645*12,0)) -> 10.416667 | G15: =IF($C$1="APM",Monthly!O1567,IF($C$1="Yearly",Monthly!O1567*12,0)) -> 22.916667 | H15: =IF($C$1="APM",Monthly!O1489,IF($C$1="Yearly",Monthly!O1489*12,0)) -> 22.916667 | I15: =IF($C$1="APM",Monthly!O1412,IF($C$1="Yearly",Monthly!O1412*12,0)) -> 25 | J15: =IF($C$1="APM",Monthly!O1335,IF($C$1="Yearly",Monthly!O1335*12,0)) -> 25 | K15: =IF($C$1="APM",Monthly!O1258,IF($C$1="Yearly",Monthly!O1258*12,0)) -> 25 | L15: =IF($C$1="APM",Monthly!O1180,IF($C$1="Yearly",Monthly!O1180*12,0)) -> 25 | M15: =IF($C$1="APM",Monthly!O1103,IF($C$1="Yearly",Monthly!O1103*12,0)) -> 25 | N15: =IF($C$1="APM",Monthly!O1026,IF($C$1="Yearly",Monthly!O1026*12,0)) -> 0 | O15: =IF($C$1="APM",Monthly!O949,IF($C$1="Yearly",Monthly!O949*12,0)) -> 0 | P15: =IF($C$1="APM",Monthly!$O873,IF($C$1="Yearly",Monthly!$O873*12,0)) -> 0 | Q15: =IF($C$1="APM",Monthly!$O796,IF($C$1="Yearly",Monthly!$O796*12,0)) -> 0 | R15: =IF($C$1="APM",Monthly!$O719,IF($C$1="Yearly",Monthly!$O719*12,0)) -> 0 | S15: =IF($C$1="APM",Monthly!$O642,IF($C$1="Yearly",Monthly!$O642*12,0)) -> 0 | T15: =IF($C$1="APM",Monthly!$O565,IF($C$1="Yearly",Monthly!$O565*12,0)) -> 0 | U15: =IF($C$1="APM",Monthly!$O565,IF($C$1="Yearly",Monthly!$O565*12,0)) -> 0 | Z15: =S15-P15 -> 0 | AA15: =IF($C$1="APM",Monthly!$O565,IF($C$1="Yearly",Monthly!$O565*12,0)) -> 0
B16: Insurance | C16: =IF($C$1="APM",Monthly!O1878,IF($C$1="Yearly",Monthly!O1878*12,0)) -> 0 | D16: =IF($C$1="APM",Monthly!O1801,IF($C$1="Yearly",Monthly!O1801*12,0)) -> 0 | E16: =IF($C$1="APM",Monthly!O1724,IF($C$1="Yearly",Monthly!O1724*12,0)) -> 15.333333 | F16: =IF($C$1="APM",Monthly!O1646,IF($C$1="Yearly",Monthly!O1646*12,0)) -> 14.916667 | G16: =IF($C$1="APM",Monthly!O1568,IF($C$1="Yearly",Monthly!O1568*12,0)) -> 15.333333 | H16: =IF($C$1="APM",Monthly!O1490,IF($C$1="Yearly",Monthly!O1490*12,0)) -> 15.333333 | I16: =IF($C$1="APM",Monthly!O1413,IF($C$1="Yearly",Monthly!O1413*12,0)) -> 16.75 | J16: =IF($C$1="APM",Monthly!O1336,IF($C$1="Yearly",Monthly!O1336*12,0)) -> 16.75 | K16: =IF($C$1="APM",Monthly!O1259,IF($C$1="Yearly",Monthly!O1259*12,0)) -> 17.083333 | L16: =IF($C$1="APM",Monthly!O1181,IF($C$1="Yearly",Monthly!O1181*12,0)) -> 17.416667 | M16: =IF($C$1="APM",Monthly!O1104,IF($C$1="Yearly",Monthly!O1104*12,0)) -> 18.583333 | N16: =IF($C$1="APM",Monthly!O1027,IF($C$1="Yearly",Monthly!O1027*12,0)) -> 20.166667 | O16: =IF($C$1="APM",Monthly!O950,IF($C$1="Yearly",Monthly!O950*12,0)) -> 20.166667 | P16: =IF($C$1="APM",Monthly!$O874,IF($C$1="Yearly",Monthly!$O874*12,0)) -> 21 | Q16: =IF($C$1="APM",Monthly!$O797,IF($C$1="Yearly",Monthly!$O797*12,0)) -> 20.166667 | R16: =IF($C$1="APM",Monthly!$O720,IF($C$1="Yearly",Monthly!$O720*12,0)) -> 0 | S16: =IF($C$1="APM",Monthly!$O643,IF($C$1="Yearly",Monthly!$O643*12,0)) -> 0 | T16: =IF($C$1="APM",Monthly!$O566,IF($C$1="Yearly",Monthly!$O566*12,0)) -> 0 | U16: =IF($C$1="APM",Monthly!$O566,IF($C$1="Yearly",Monthly!$O566*12,0)) -> 0 | Z16: =S16-P16 -> -21 | AA16: =IF($C$1="APM",Monthly!$O566,IF($C$1="Yearly",Monthly!$O566*12,0)) -> 0 | AB16: =1500/12 -> 125
B17: Assoc. Fee | C17: =IF($C$1="APM",Monthly!O1879,IF($C$1="Yearly",Monthly!O1879*12,0)) -> 0 | D17: =IF($C$1="APM",Monthly!O1802,IF($C$1="Yearly",Monthly!O1802*12,0)) -> 0 | E17: =IF($C$1="APM",Monthly!O1725,IF($C$1="Yearly",Monthly!O1725*12,0)) -> 102 | F17: =IF($C$1="APM",Monthly!O1647,IF($C$1="Yearly",Monthly!O1647*12,0)) -> 214 | G17: =IF($C$1="APM",Monthly!O1569,IF($C$1="Yearly",Monthly!O1569*12,0)) -> 234 | H17: =IF($C$1="APM",Monthly!O1491,IF($C$1="Yearly",Monthly!O1491*12,0)) -> 244 | I17: =IF($C$1="APM",Monthly!O1414,IF($C$1="Yearly",Monthly!O1414*12,0)) -> 274.75 | J17: =IF($C$1="APM",Monthly!O1337,IF($C$1="Yearly",Monthly!O1337*12,0)) -> 305.83333 | K17: =IF($C$1="APM",Monthly!O1260,IF($C$1="Yearly",Monthly!O1260*12,0)) -> 317.91667 | L17: =IF($C$1="APM",Monthly!O1182,IF($C$1="Yearly",Monthly!O1182*12,0)) -> 361.41667 | M17: =IF($C$1="APM",Monthly!O1105,IF($C$1="Yearly",Monthly!O1105*12,0)) -> 296.41667 | N17: =IF($C$1="APM",Monthly!O1028,IF($C$1="Yearly",Monthly!O1028*12,0)) -> 288.33333 | O17: =IF($C$1="APM",Monthly!O951,IF($C$1="Yearly",Monthly!O951*12,0)) -> 289 | P17: =IF($C$1="APM",Monthly!$O875,IF($C$1="Yearly",Monthly!$O875*12,0)) -> 308.33333 | Q17: =IF($C$1="APM",Monthly!$O798,IF($C$1="Yearly",Monthly!$O798*12,0)) -> 177.08333 | R17: =IF($C$1="APM",Monthly!$O721,IF($C$1="Yearly",Monthly!$O721*12,0)) -> 4.1666667 | S17: =IF($C$1="APM",Monthly!$O644,IF($C$1="Yearly",Monthly!$O644*12,0)) -> 0 | T17: =IF($C$1="APM",Monthly!$O567,IF($C$1="Yearly",Monthly!$O567*12,0)) -> 0 | U17: =IF($C$1="APM",Monthly!$O567,IF($C$1="Yearly",Monthly!$O567*12,0)) -> 0 | Z17: =S17-P17 -> -308.33333 | AA17: =IF($C$1="APM",Monthly!$O567,IF($C$1="Yearly",Monthly!$O567*12,0)) -> 0 | AB17: =IF($C$1="APM",Monthly!$O567,IF($C$1="Yearly",Monthly!$O567*12,0)) -> 0
B18: PMI | C18: =IF($C$1="APM",Monthly!O1880,IF($C$1="Yearly",Monthly!O1880*12,0)) -> 0 | D18: =IF($C$1="APM",Monthly!O1803,IF($C$1="Yearly",Monthly!O1803*12,0)) -> 0 | E18: =IF($C$1="APM",Monthly!O1726,IF($C$1="Yearly",Monthly!O1726*12,0)) -> 20.833333 | F18: =IF($C$1="APM",Monthly!O1648,IF($C$1="Yearly",Monthly!O1648*12,0)) -> 65.833333 | G18: =IF($C$1="APM",Monthly!O1570,IF($C$1="Yearly",Monthly!O1570*12,0)) -> 67.583333 | H18: =IF($C$1="APM",Monthly!O1492,IF($C$1="Yearly",Monthly!O1492*12,0)) -> 39 | I18: =IF($C$1="APM",Monthly!O1415,IF($C$1="Yearly",Monthly!O1415*12,0)) -> 36.916667 | J18: =IF($C$1="APM",Monthly!O1338,IF($C$1="Yearly",Monthly!O1338*12,0)) -> 34 | K18: =IF($C$1="APM",Monthly!O1261,IF($C$1="Yearly",Monthly!O1261*12,0)) -> 34 | L18: =IF($C$1="APM",Monthly!O1183,IF($C$1="Yearly",Monthly!O1183*12,0)) -> 34 | M18: =IF($C$1="APM",Monthly!O1106,IF($C$1="Yearly",Monthly!O1106*12,0)) -> 34 | N18: =IF($C$1="APM",Monthly!O1029,IF($C$1="Yearly",Monthly!O1029*12,0)) -> 0 | O18: =IF($C$1="APM",Monthly!O952,IF($C$1="Yearly",Monthly!O952*12,0)) -> 0 | P18: =IF($C$1="APM",Monthly!$O876,IF($C$1="Yearly",Monthly!$O876*12,0)) -> 0 | Q18: =IF($C$1="APM",Monthly!$O799,IF($C$1="Yearly",Monthly!$O799*12,0)) -> 0 | R18: =IF($C$1="APM",Monthly!$O722,IF($C$1="Yearly",Monthly!$O722*12,0)) -> 0 | S18: =IF($C$1="APM",Monthly!$O645,IF($C$1="Yearly",Monthly!$O645*12,0)) -> 0 | T18: =IF($C$1="APM",Monthly!$O568,IF($C$1="Yearly",Monthly!$O568*12,0)) -> 0 | U18: =IF($C$1="APM",Monthly!$O568,IF($C$1="Yearly",Monthly!$O568*12,0)) -> 0 | Z18: =S18-P18 -> 0 | AA18: =IF($C$1="APM",Monthly!$O568,IF($C$1="Yearly",Monthly!$O568*12,0)) -> 0 | AB18: =IF($C$1="APM",Monthly!$O568,IF($C$1="Yearly",Monthly!$O568*12,0)) -> 0
B19: Mt/Serv | C19: =IF($C$1="APM",Monthly!O1881,IF($C$1="Yearly",Monthly!O1881*12,0)) -> 0 | D19: =IF($C$1="APM",Monthly!O1804,IF($C$1="Yearly",Monthly!O1804*12,0)) -> 0.25 | E19: =IF($C$1="APM",Monthly!O1727,IF($C$1="Yearly",Monthly!O1727*12,0)) -> 0 | F19: =IF($C$1="APM",Monthly!O1649,IF($C$1="Yearly",Monthly!O1649*12,0)) -> 0 | G19: =IF($C$1="APM",Monthly!O1571,IF($C$1="Yearly",Monthly!O1571*12,0)) -> 0 | H19: =IF($C$1="APM",Monthly!O1493,IF($C$1="Yearly",Monthly!O1493*12,0)) -> 17.25 | I19: =IF($C$1="APM",Monthly!O1416,IF($C$1="Yearly",Monthly!O1416*12,0)) -> 18.833333 | J19: =IF($C$1="APM",Monthly!O1339,IF($C$1="Yearly",Monthly!O1339*12,0)) -> 38.5 | K19: =IF($C$1="APM",Monthly!O1262,IF($C$1="Yearly",Monthly!O1262*12,0)) -> 0.25 | L19: =IF($C$1="APM",Monthly!O1184,IF($C$1="Yearly",Monthly!O1184*12,0)) -> 73.083333 | M19: =IF($C$1="APM",Monthly!O1107,IF($C$1="Yearly",Monthly!O1107*12,0)) -> 38.333333 | N19: =IF($C$1="APM",Monthly!O1030,IF($C$1="Yearly",Monthly!O1030*12,0)) -> 255 | O19: =IF($C$1="APM",Monthly!O953,IF($C$1="Yearly",Monthly!O953*12,0)) -> 32.083333 | P19: =IF($C$1="APM",Monthly!$O877,IF($C$1="Yearly",Monthly!$O877*12,0)) -> 17.25 | Q19: =IF($C$1="APM",Monthly!$O800,IF($C$1="Yearly",Monthly!$O800*12,0)) -> 117.41667 | R19: =IF($C$1="APM",Monthly!$O723,IF($C$1="Yearly",Monthly!$O723*12,0)) -> 3 | S19: =IF($C$1="APM",Monthly!$O646,IF($C$1="Yearly",Monthly!$O646*12,0)) -> 31.25 | T19: =IF($C$1="APM",Monthly!$O569,IF($C$1="Yearly",Monthly!$O569*12,0)) -> 4.1666667 | U19: =IF($C$1="APM",Monthly!$O569,IF($C$1="Yearly",Monthly!$O569*12,0)) -> 4.1666667 | Z19: =S19-P19 -> 14 | AA19: =T19-Q19 -> -113.25 | AB19: 500
A20: Car | C20: =SUM(C22:C27) -> 966.66667 | D20: =SUM(D22:D27) -> 1729 | E20: =SUM(E22:E27) -> 1999.5 | F20: =SUM(F22:F27) -> 406.41667 | G20: =SUM(G22:G27) -> 560.41667 | H20: =SUM(H22:H27) -> 357.91667 | I20: =SUM(I22:I27) -> 355.25 | J20: =SUM(J22:J27) -> 246.58333 | ... U20: =SUM(U22:U27) -> 1175.7083 | Z20: =S20-P20 -> 1123.6944 | AA20: =(S20-P20)/P20 -> 4.9194941 | AB20: =SUM(AB22:AB27) -> 1323.3333
B22: Loans | C22: =IF($C$1="APM",Monthly!O1884,IF($C$1="Yearly",Monthly!O1884*12,0)) -> 808 | D22: =IF($C$1="APM",Monthly!O1807,IF($C$1="Yearly",Monthly!O1807*12,0)) -> 1379.25 | E22: =IF($C$1="APM",Monthly!O1730,IF($C$1="Yearly",Monthly!O1730*12,0)) -> 1716.8333 | F22: =IF($C$1="APM",Monthly!O1652,IF($C$1="Yearly",Monthly!O1652*12,0)) -> 0 | G22: =IF($C$1="APM",Monthly!O1574,IF($C$1="Yearly",Monthly!O1574*12,0)) -> 0 | H22: =IF($C$1="APM",Monthly!O1496,IF($C$1="Yearly",Monthly!O1496*12,0)) -> 0 | I22: =IF($C$1="APM",Monthly!O1419,IF($C$1="Yearly",Monthly!O1419*12,0)) -> 0 | J22: =IF($C$1="APM",Monthly!O1342,IF($C$1="Yearly",Monthly!O1342*12,0)) -> 39.166667 | K22: =IF($C$1="APM",Monthly!O1265,IF($C$1="Yearly",Monthly!O1265*12,0)) -> 470 | L22: =IF($C$1="APM",Monthly!O1187,IF($C$1="Yearly",Monthly!O1187*12,0)) -> 470 | M22: =IF($C$1="APM",Monthly!O1110,IF($C$1="Yearly",Monthly!O1110*12,0)) -> 470 | N22: =IF($C$1="APM",Monthly!O1033,IF($C$1="Yearly",Monthly!O1033*12,0)) -> 470 | O22: =IF($C$1="APM",Monthly!O956,IF($C$1="Yearly",Monthly!O956*12,0)) -> 430.83333 | P22: =IF($C$1="APM",Monthly!$O880,IF($C$1="Yearly",Monthly!$O880*12,0)) -> 0 | Q22: =IF($C$1="APM",Monthly!$O803,IF($C$1="Yearly",Monthly!$O803*12,0)) -> 389.16667 | R22: =IF($C$1="APM",Monthly!$O726,IF($C$1="Yearly",Monthly!$O726*12,0)) -> 778.33333 | S22: =IF($C$1="APM",Monthly!$O649,IF($C$1="Yearly",Monthly!$O649*12,0)) -> 778.33333 | T22: =IF($C$1="APM",Monthly!$O572,IF($C$1="Yearly",Monthly!$O572*12,0)) -> 778.33333 | U22: =IF($C$1="APM",Monthly!$O572,IF($C$1="Yearly",Monthly!$O572*12,0)) -> 778.33333 | Z22: =S22-P22 -> 778.33333 | AA22: =T22-Q22 -> 389.16667 | AB22: =IF($C$1="APM",Monthly!$O572,IF($C$1="Yearly",Monthly!$O572*12,0)) -> 778.33333
B23: Insurance | C23: =IF($C$1="APM",Monthly!O1885,IF($C$1="Yearly",Monthly!O1885*12,0)) -> 144 | D23: =IF($C$1="APM",Monthly!O1808,IF($C$1="Yearly",Monthly!O1808*12,0)) -> 149.83333 | E23: =IF($C$1="APM",Monthly!O1731,IF($C$1="Yearly",Monthly!O1731*12,0)) -> 166.83333 | F23: =IF($C$1="APM",Monthly!O1653,IF($C$1="Yearly",Monthly!O1653*12,0)) -> 170.5 | G23: =IF($C$1="APM",Monthly!O1575,IF($C$1="Yearly",Monthly!O1575*12,0)) -> 146.66667 | H23: =IF($C$1="APM",Monthly!O1497,IF($C$1="Yearly",Monthly!O1497*12,0)) -> 145.58333 | I23: =IF($C$1="APM",Monthly!O1420,IF($C$1="Yearly",Monthly!O1420*12,0)) -> 141.33333 | J23: =IF($C$1="APM",Monthly!O1343,IF($C$1="Yearly",Monthly!O1343*12,0)) -> 125.41667 | K23: =IF($C$1="APM",Monthly!O1266,IF($C$1="Yearly",Monthly!O1266*12,0)) -> 110.66667 | L23: =IF($C$1="APM",Monthly!O1188,IF($C$1="Yearly",Monthly!O1188*12,0)) -> 98 | M23: =IF($C$1="APM",Monthly!O1111,IF($C$1="Yearly",Monthly!O1111*12,0)) -> 102 | N23: =IF($C$1="APM",Monthly!O1034,IF($C$1="Yearly",Monthly!O1034*12,0)) -> 106 | O23: =IF($C$1="APM",Monthly!O957,IF($C$1="Yearly",Monthly!O957*12,0)) -> 91 | P23: =IF($C$1="APM",Monthly!$O881,IF($C$1="Yearly",Monthly!$O881*12,0)) -> 92 | Q23: =IF($C$1="APM",Monthly!$O804,IF($C$1="Yearly",Monthly!$O804*12,0)) -> 125 | R23: =IF($C$1="APM",Monthly!$O727,IF($C$1="Yearly",Monthly!$O727*12,0)) -> 157 | S23: =IF($C$1="APM",Monthly!$O650,IF($C$1="Yearly",Monthly!$O650*12,0)) -> 164.77778 | T23: =IF($C$1="APM",Monthly!$O573,IF($C$1="Yearly",Monthly!$O573*12,0)) -> 173.29167 | U23: =IF($C$1="APM",Monthly!$O573,IF($C$1="Yearly",Monthly!$O573*12,0)) -> 173.29167 | Z23: =S23-P23 -> 72.777778 | AA23: =T23-Q23 -> 48.291667 | AB23: 200
B24: Lic/Tx.Insp. | C24: =IF($C$1="APM",Monthly!O1886,IF($C$1="Yearly",Monthly!O1886*12,0)) -> 0 | D24: =IF($C$1="APM",Monthly!O1809,IF($C$1="Yearly",Monthly!O1809*12,0)) -> 56.833333 | E24: =IF($C$1="APM",Monthly!O1732,IF($C$1="Yearly",Monthly!O1732*12,0)) -> 31.083333 | F24: =IF($C$1="APM",Monthly!O1654,IF($C$1="Yearly",Monthly!O1654*12,0)) -> 29.166667 | G24: =IF($C$1="APM",Monthly!O1576,IF($C$1="Yearly",Monthly!O1576*12,0)) -> 17.416667 | H24: =IF($C$1="APM",Monthly!O1498,IF($C$1="Yearly",Monthly!O1498*12,0)) -> 20.833333 | I24: =IF($C$1="APM",Monthly!O1421,IF($C$1="Yearly",Monthly!O1421*12,0)) -> 14.083333 | J24: =IF($C$1="APM",Monthly!O1344,IF($C$1="Yearly",Monthly!O1344*12,0)) -> 21.583333 | K24: =IF($C$1="APM",Monthly!O1267,IF($C$1="Yearly",Monthly!O1267*12,0)) -> 59.333333 | L24: =IF($C$1="APM",Monthly!O1189,IF($C$1="Yearly",Monthly!O1189*12,0)) -> 55 | M24: =IF($C$1="APM",Monthly!O1112,IF($C$1="Yearly",Monthly!O1112*12,0)) -> 38.166667 | N24: =IF($C$1="APM",Monthly!O1035,IF($C$1="Yearly",Monthly!O1035*12,0)) -> 13.166667 | O24: =IF($C$1="APM",Monthly!O958,IF($C$1="Yearly",Monthly!O958*12,0)) -> 5.3333333 | P24: =IF($C$1="APM",Monthly!$O882,IF($C$1="Yearly",Monthly!$O882*12,0)) -> 31 | Q24: =IF($C$1="APM",Monthly!$O805,IF($C$1="Yearly",Monthly!$O805*12,0)) -> 40.666667 | R24: =IF($C$1="APM",Monthly!$O728,IF($C$1="Yearly",Monthly!$O728*12,0)) -> 47.833333 | S24: =IF($C$1="APM",Monthly!$O651,IF($C$1="Yearly",Monthly!$O651*12,0)) -> 122.91667 | T24: =IF($C$1="APM",Monthly!$O574,IF($C$1="Yearly",Monthly!$O574*12,0)) -> 55.25 | U24: =IF($C$1="APM",Monthly!$O574,IF($C$1="Yearly",Monthly!$O574*12,0)) -> 55.25 | Z24: =S24-P24 -> 91.916667 | AA24: =T24-Q24 -> 14.583333 | AB24: 120
B25: Repairs | C25: =IF($C$1="APM",Monthly!O1887,IF($C$1="Yearly",Monthly!O1887*12,0)) -> 0 | D25: =IF($C$1="APM",Monthly!O1810,IF($C$1="Yearly",Monthly!O1810*12,0)) -> 98.666667 | E25: =IF($C$1="APM",Monthly!O1733,IF($C$1="Yearly",Monthly!O1733*12,0)) -> 0 | F25: =IF($C$1="APM",Monthly!O1655,IF($C$1="Yearly",Monthly!O1655*12,0)) -> 0 | G25: =IF($C$1="APM",Monthly!O1577,IF($C$1="Yearly",Monthly!O1577*12,0)) -> 27.916667 | H25: =IF($C$1="APM",Monthly!O1499,IF($C$1="Yearly",Monthly!O1499*12,0)) -> 0 | I25: =IF($C$1="APM",Monthly!O1422,IF($C$1="Yearly",Monthly!O1422*12,0)) -> 4.9166667 | J25: =IF($C$1="APM",Monthly!O1345,IF($C$1="Yearly",Monthly!O1345*12,0)) -> 12.833333 | K25: =IF($C$1="APM",Monthly!O1268,IF($C$1="Yearly",Monthly!O1268*12,0)) -> 81.25 | L25: =IF($C$1="APM",Monthly!O1190,IF($C$1="Yearly",Monthly!O1190*12,0)) -> 0 | M25: =IF($C$1="APM",Monthly!O1113,IF($C$1="Yearly",Monthly!O1113*12,0)) -> 0 | N25: =IF($C$1="APM",Monthly!O1036,IF($C$1="Yearly",Monthly!O1036*12,0)) -> 0.83333333 | O25: =IF($C$1="APM",Monthly!O959,IF($C$1="Yearly",Monthly!O959*12,0)) -> 0.58333333 | P25: =IF($C$1="APM",Monthly!$O883,IF($C$1="Yearly",Monthly!$O883*12,0)) -> 0.58333333 | Q25: =IF($C$1="APM",Monthly!$O806,IF($C$1="Yearly",Monthly!$O806*12,0)) -> 43.166667 | R25: =IF($C$1="APM",Monthly!$O729,IF($C$1="Yearly",Monthly!$O729*12,0)) -> 33.333333 | S25: =IF($C$1="APM",Monthly!$O652,IF($C$1="Yearly",Monthly!$O652*12,0)) -> 162.83333 | T25: =IF($C$1="APM",Monthly!$O575,IF($C$1="Yearly",Monthly!$O575*12,0)) -> 20.25 | U25: =IF($C$1="APM",Monthly!$O575,IF($C$1="Yearly",Monthly!$O575*12,0)) -> 20.25 | Z25: =S25-P25 -> 162.25 | AA25: =T25-Q25 -> -22.916667 | AB25: 50
B26: Mt/Serv: Audi/Merc | C26: =IF($C$1="APM",Monthly!O1888,IF($C$1="Yearly",Monthly!O1888*12,0)) -> 5.3333333 | D26: =IF($C$1="APM",Monthly!O1811,IF($C$1="Yearly",Monthly!O1811*12,0)) -> 10.333333 | E26: =IF($C$1="APM",Monthly!O1734,IF($C$1="Yearly",Monthly!O1734*12,0)) -> 37.916667 | F26: =IF($C$1="APM",Monthly!O1656,IF($C$1="Yearly",Monthly!O1656*12,0)) -> 160.33333 | G26: =IF($C$1="APM",Monthly!O1578,IF($C$1="Yearly",Monthly!O1578*12,0)) -> 174.83333 | H26: =IF($C$1="APM",Monthly!O1500,IF($C$1="Yearly",Monthly!O1500*12,0)) -> 105.33333 | I26: =IF($C$1="APM",Monthly!O1423,IF($C$1="Yearly",Monthly!O1423*12,0)) -> 118 | J26: =IF($C$1="APM",Monthly!O1346,IF($C$1="Yearly",Monthly!O1346*12,0)) -> 1.5833333 | K26: =IF($C$1="APM",Monthly!O1269,IF($C$1="Yearly",Monthly!O1269*12,0)) -> 16 | L26: =IF($C$1="APM",Monthly!O1191,IF($C$1="Yearly",Monthly!O1191*12,0)) -> 97.25 | M26: =IF($C$1="APM",Monthly!O1114,IF($C$1="Yearly",Monthly!O1114*12,0)) -> 55.083333 | N26: =IF($C$1="APM",Monthly!O1037,IF($C$1="Yearly",Monthly!O1037*12,0)) -> 19.416667 | O26: =IF($C$1="APM",Monthly!O960,IF($C$1="Yearly",Monthly!O960*12,0)) -> 147.25 | P26: =IF($C$1="APM",Monthly!$O884,IF($C$1="Yearly",Monthly!$O884*12,0)) -> 16 | Q26: =IF($C$1="APM",Monthly!$O807,IF($C$1="Yearly",Monthly!$O807*12,0)) -> 71.333333 | R26: =IF($C$1="APM",Monthly!$O730,IF($C$1="Yearly",Monthly!$O730*12,0)) -> 97.916667 | S26: =IF($C$1="APM",Monthly!$O653,IF($C$1="Yearly",Monthly!$O653*12,0)) -> 97.916667 | T26: =IF($C$1="APM",Monthly!$O576,IF($C$1="Yearly",Monthly!$O576*12,0)) -> 97 | U26: =IF($C$1="APM",Monthly!$O576,IF($C$1="Yearly",Monthly!$O576*12,0)) -> 97 | Z26: =S26-P26 -> 81.916667 | AA26: =T26-Q26 -> 25.666667 | AB26: 100
B27: Mt/Serv: Altima | C27: =IF($C$1="APM",Monthly!O1889,IF($C$1="Yearly",Monthly!O1889*12,0)) -> 9.3333333 | D27: =IF($C$1="APM",Monthly!O1812,IF($C$1="Yearly",Monthly!O1812*12,0)) -> 34.083333 | E27: =IF($C$1="APM",Monthly!O1735,IF($C$1="Yearly",Monthly!O1735*12,0)) -> 46.833333 | F27: =IF($C$1="APM",Monthly!O1657,IF($C$1="Yearly",Monthly!O1657*12,0)) -> 46.416667 | G27: =IF($C$1="APM",Monthly!O1579,IF($C$1="Yearly",Monthly!O1579*12,0)) -> 193.58333 | H27: =IF($C$1="APM",Monthly!O1501,IF($C$1="Yearly",Monthly!O1501*12,0)) -> 86.166667 | I27: =IF($C$1="APM",Monthly!O1424,IF($C$1="Yearly",Monthly!O1424*12,0)) -> 76.916667 | J27: =IF($C$1="APM",Monthly!O1347,IF($C$1="Yearly",Monthly!O1347*12,0)) -> 46 | K27: =IF($C$1="APM",Monthly!O1270,IF($C$1="Yearly",Monthly!O1270*12,0)) -> 38.333333 | L27: =IF($C$1="APM",Monthly!O1192,IF($C$1="Yearly",Monthly!O1192*12,0)) -> 82.166667 | M27: =IF($C$1="APM",Monthly!O1115,IF($C$1="Yearly",Monthly!O1115*12,0)) -> 57.333333 | N27: =IF($C$1="APM",Monthly!O1038,IF($C$1="Yearly",Monthly!O1038*12,0)) -> 94.416667 | O27: =IF($C$1="APM",Monthly!O961,IF($C$1="Yearly",Monthly!O961*12,0)) -> 35 | P27: =IF($C$1="APM",Monthly!$O885,IF($C$1="Yearly",Monthly!$O885*12,0)) -> 88.833333 | Q27: =IF($C$1="APM",Monthly!$O808,IF($C$1="Yearly",Monthly!$O808*12,0)) -> 48.666667 | R27: =IF($C$1="APM",Monthly!$O731,IF($C$1="Yearly",Monthly!$O731*12,0)) -> 6.5 | S27: =IF($C$1="APM",Monthly!$O654,IF($C$1="Yearly",Monthly!$O654*12,0)) -> 25.333333 | T27: =IF($C$1="APM",Monthly!$O577,IF($C$1="Yearly",Monthly!$O577*12,0)) -> 51.583333 | U27: =IF($C$1="APM",Monthly!$O577,IF($C$1="Yearly",Monthly!$O577*12,0)) -> 51.583333 | Z27: =S27-P27 -> -63.5 | AA27: =T27-Q27 -> 2.9166667 | AB27: 75
A28: Transportation | C28: =SUM(C30:C33) -> 275.5 | D28: =SUM(D30:D33) -> 242.58333 | E28: =SUM(E30:E33) -> 189.25 | F28: =SUM(F30:F33) -> 239.16667 | G28: =SUM(G30:G33) -> 229.58333 | H28: =SUM(H30:H33) -> 293.5 | I28: =SUM(I30:I33) -> 404 | J28: =SUM(J30:J33) -> 283.33333 | ... U28: =SUM(U30:U33) -> 316.83333 | Z28: =S28-P28 -> 312.41667 | AA28: =(S28-P28)/P28 -> 1.0687001 | AB28: =SUM(AB30:AB33) -> 340
B30: Gas | C30: =IF($C$1="APM",Monthly!O1892,IF($C$1="Yearly",Monthly!O1892*12,0)) -> 221 | D30: =IF($C$1="APM",Monthly!O1815,IF($C$1="Yearly",Monthly!O1815*12,0)) -> 201.83333 | E30: =IF($C$1="APM",Monthly!O1738,IF($C$1="Yearly",Monthly!O1738*12,0)) -> 171.83333 | F30: =IF($C$1="APM",Monthly!O1660,IF($C$1="Yearly",Monthly!O1660*12,0)) -> 191.83333 | G30: =IF($C$1="APM",Monthly!O1582,IF($C$1="Yearly",Monthly!O1582*12,0)) -> 207.75 | H30: =IF($C$1="APM",Monthly!O1504,IF($C$1="Yearly",Monthly!O1504*12,0)) -> 246.58333 | I30: =IF($C$1="APM",Monthly!O1427,IF($C$1="Yearly",Monthly!O1427*12,0)) -> 328.58333 | J30: =IF($C$1="APM",Monthly!O1350,IF($C$1="Yearly",Monthly!O1350*12,0)) -> 231.58333 | K30: =IF($C$1="APM",Monthly!O1273,IF($C$1="Yearly",Monthly!O1273*12,0)) -> 257.25 | L30: =IF($C$1="APM",Monthly!O1195,IF($C$1="Yearly",Monthly!O1195*12,0)) -> 214.41667 | M30: =IF($C$1="APM",Monthly!O1118,IF($C$1="Yearly",Monthly!O1118*12,0)) -> 267 | N30: =IF($C$1="APM",Monthly!O1041,IF($C$1="Yearly",Monthly!O1041*12,0)) -> 330.58333 | O30: =IF($C$1="APM",Monthly!O964,IF($C$1="Yearly",Monthly!O964*12,0)) -> 327.08333 | P30: =IF($C$1="APM",Monthly!$O888,IF($C$1="Yearly",Monthly!$O888*12,0)) -> 230.08333 | Q30: =IF($C$1="APM",Monthly!$O811,IF($C$1="Yearly",Monthly!$O811*12,0)) -> 217.66667 | R30: =IF($C$1="APM",Monthly!$O734,IF($C$1="Yearly",Monthly!$O734*12,0)) -> 183.58333 | S30: =IF($C$1="APM",Monthly!$O657,IF($C$1="Yearly",Monthly!$O657*12,0)) -> 190.41667 | T30: =IF($C$1="APM",Monthly!$O580,IF($C$1="Yearly",Monthly!$O580*12,0)) -> 189.25 | U30: =IF($C$1="APM",Monthly!$O580,IF($C$1="Yearly",Monthly!$O580*12,0)) -> 189.25 | Z30: =S30-P30 -> -39.666667 | AA30: =T30-Q30 -> -28.416667 | AB30: 300
B31: Gas (Travel/Commute) | C31: =IF($C$1="APM",Monthly!O1893,IF($C$1="Yearly",Monthly!O1893*12,0)) -> 21.166667 | D31: =IF($C$1="APM",Monthly!O1816,IF($C$1="Yearly",Monthly!O1816*12,0)) -> 0 | E31: =IF($C$1="APM",Monthly!O1739,IF($C$1="Yearly",Monthly!O1739*12,0)) -> 0 | F31: =IF($C$1="APM",Monthly!O1661,IF($C$1="Yearly",Monthly!O1661*12,0)) -> 30.833333 | G31: =IF($C$1="APM",Monthly!O1583,IF($C$1="Yearly",Monthly!O1583*12,0)) -> 11.666667 | H31: =IF($C$1="APM",Monthly!O1505,IF($C$1="Yearly",Monthly!O1505*12,0)) -> 33.5 | I31: =IF($C$1="APM",Monthly!O1428,IF($C$1="Yearly",Monthly!O1428*12,0)) -> 44.333333 | J31: =IF($C$1="APM",Monthly!O1351,IF($C$1="Yearly",Monthly!O1351*12,0)) -> 0 | K31: =IF($C$1="APM",Monthly!O1274,IF($C$1="Yearly",Monthly!O1274*12,0)) -> 46.25 | L31: =IF($C$1="APM",Monthly!O1196,IF($C$1="Yearly",Monthly!O1196*12,0)) -> 8.25 | M31: =IF($C$1="APM",Monthly!O1119,IF($C$1="Yearly",Monthly!O1119*12,0)) -> 21.416667 | N31: =IF($C$1="APM",Monthly!O1042,IF($C$1="Yearly",Monthly!O1042*12,0)) -> 44.916667 | O31: =IF($C$1="APM",Monthly!O965,IF($C$1="Yearly",Monthly!O965*12,0)) -> 59.333333 | P31: =IF($C$1="APM",Monthly!$O889,IF($C$1="Yearly",Monthly!$O889*12,0)) -> 24 | Q31: =IF($C$1="APM",Monthly!$O812,IF($C$1="Yearly",Monthly!$O812*12,0)) -> 14.333333 | R31: =IF($C$1="APM",Monthly!$O735,IF($C$1="Yearly",Monthly!$O735*12,0)) -> 193.41667 | S31: =IF($C$1="APM",Monthly!$O658,IF($C$1="Yearly",Monthly!$O658*12,0)) -> 365.16667 | T31: =IF($C$1="APM",Monthly!$O581,IF($C$1="Yearly",Monthly!$O581*12,0)) -> 120 | U31: =IF($C$1="APM",Monthly!$O581,IF($C$1="Yearly",Monthly!$O581*12,0)) -> 120 | Z31: =S31-P31 -> 341.16667 | AA31: =T31-Q31 -> 105.66667 | AB31: -
B32: Park/Car Wash | C32: =IF($C$1="APM",Monthly!O1894,IF($C$1="Yearly",Monthly!O1894*12,0)) -> 7.5 | D32: =IF($C$1="APM",Monthly!O1817,IF($C$1="Yearly",Monthly!O1817*12,0)) -> 10.583333 | E32: =IF($C$1="APM",Monthly!O1740,IF($C$1="Yearly",Monthly!O1740*12,0)) -> 2 | F32: =IF($C$1="APM",Monthly!O1662,IF($C$1="Yearly",Monthly!O1662*12,0)) -> 8.1666667 | G32: =IF($C$1="APM",Monthly!O1584,IF($C$1="Yearly",Monthly!O1584*12,0)) -> 4.75 | H32: =IF($C$1="APM",Monthly!O1506,IF($C$1="Yearly",Monthly!O1506*12,0)) -> 3.5833333 | I32: =IF($C$1="APM",Monthly!O1429,IF($C$1="Yearly",Monthly!O1429*12,0)) -> 14 | J32: =IF($C$1="APM",Monthly!O1352,IF($C$1="Yearly",Monthly!O1352*12,0)) -> 25.5 | K32: =IF($C$1="APM",Monthly!O1275,IF($C$1="Yearly",Monthly!O1275*12,0)) -> 28 | L32: =IF($C$1="APM",Monthly!O1197,IF($C$1="Yearly",Monthly!O1197*12,0)) -> 24.666667 | M32: =IF($C$1="APM",Monthly!O1120,IF($C$1="Yearly",Monthly!O1120*12,0)) -> 20 | N32: =IF($C$1="APM",Monthly!O1043,IF($C$1="Yearly",Monthly!O1043*12,0)) -> 35.083333 | O32: =IF($C$1="APM",Monthly!O966,IF($C$1="Yearly",Monthly!O966*12,0)) -> 22.666667 | P32: =IF($C$1="APM",Monthly!$O890,IF($C$1="Yearly",Monthly!$O890*12,0)) -> 14.5 | Q32: =IF($C$1="APM",Monthly!$O813,IF($C$1="Yearly",Monthly!$O813*12,0)) -> 29.75 | R32: =IF($C$1="APM",Monthly!$O736,IF($C$1="Yearly",Monthly!$O736*12,0)) -> 61.583333 | S32: =IF($C$1="APM",Monthly!$O659,IF($C$1="Yearly",Monthly!$O659*12,0)) -> 47.083333 | T32: =IF($C$1="APM",Monthly!$O582,IF($C$1="Yearly",Monthly!$O582*12,0)) -> 5.5 | U32: =IF($C$1="APM",Monthly!$O582,IF($C$1="Yearly",Monthly!$O582*12,0)) -> 5.5 | Z32: =S32-P32 -> 32.583333 | AA32: =T32-Q32 -> -24.25 | AB32: 20
B33: EZPass | C33: =IF($C$1="APM",Monthly!O1895,IF($C$1="Yearly",Monthly!O1895*12,0)) -> 25.833333 | D33: =IF($C$1="APM",Monthly!O1818,IF($C$1="Yearly",Monthly!O1818*12,0)) -> 30.166667 | E33: =IF($C$1="APM",Monthly!O1741,IF($C$1="Yearly",Monthly!O1741*12,0)) -> 15.416667 | F33: =IF($C$1="APM",Monthly!O1663,IF($C$1="Yearly",Monthly!O1663*12,0)) -> 8.3333333 | G33: =IF($C$1="APM",Monthly!O1585,IF($C$1="Yearly",Monthly!O1585*12,0)) -> 5.4166667 | H33: =IF($C$1="APM",Monthly!O1507,IF($C$1="Yearly",Monthly!O1507*12,0)) -> 9.8333333 | I33: =IF($C$1="APM",Monthly!O1430,IF($C$1="Yearly",Monthly!O1430*12,0)) -> 17.083333 | J33: =IF($C$1="APM",Monthly!O1353,IF($C$1="Yearly",Monthly!O1353*12,0)) -> 26.25 | K33: =IF($C$1="APM",Monthly!O1276,IF($C$1="Yearly",Monthly!O1276*12,0)) -> 31.166667 | L33: =IF($C$1="APM",Monthly!O1198,IF($C$1="Yearly",Monthly!O1198*12,0)) -> 16.25 | M33: =IF($C$1="APM",Monthly!O1121,IF($C$1="Yearly",Monthly!O1121*12,0)) -> 15.833333 | N33: =IF($C$1="APM",Monthly!O1044,IF($C$1="Yearly",Monthly!O1044*12,0)) -> 15.416667 | O33: =IF($C$1="APM",Monthly!O967,IF($C$1="Yearly",Monthly!O967*12,0)) -> 33.416667 | P33: =IF($C$1="APM",Monthly!$O891,IF($C$1="Yearly",Monthly!$O891*12,0)) -> 23.75 | Q33: =IF($C$1="APM",Monthly!$O814,IF($C$1="Yearly",Monthly!$O814*12,0)) -> 17.916667 | R33: =IF($C$1="APM",Monthly!$O737,IF($C$1="Yearly",Monthly!$O737*12,0)) -> 10.083333 | S33: =IF($C$1="APM",Monthly!$O660,IF($C$1="Yearly",Monthly!$O660*12,0)) -> 2.0833333 | T33: =IF($C$1="APM",Monthly!$O583,IF($C$1="Yearly",Monthly!$O583*12,0)) -> 2.0833333 | U33: =IF($C$1="APM",Monthly!$O583,IF($C$1="Yearly",Monthly!$O583*12,0)) -> 2.0833333 | Z33: =S33-P33 -> -21.666667 | AA33: =T33-Q33 -> -15.833333 | AB33: 20
A34: Food | C34: =SUM(C36:C37) -> 478 | D34: =SUM(D36:D37) -> 517.91667 | E34: =SUM(E36:E37) -> 287.16667 | F34: =SUM(F36:F37) -> 273.75 | G34: =SUM(G36:G37) -> 271.25 | H34: =SUM(H36:H37) -> 324.66667 | I34: =SUM(I36:I37) -> 490.91667 | J34: =SUM(J36:J37) -> 509.58333 | ... U34: =SUM(U36:U37) -> 802.58333 | Z34: =S34-P34 -> -56.583333 | AA34: =(S34-P34)/P34 -> -0.060035367 | AB34: =SUM(AB36:AB37) -> 1000
B36: Grocery | C36: =IF($C$1="APM",Monthly!O1898,IF($C$1="Yearly",Monthly!O1898*12,0)) -> 358.66667 | D36: =IF($C$1="APM",Monthly!O1821,IF($C$1="Yearly",Monthly!O1821*12,0)) -> 349.16667 | E36: =IF($C$1="APM",Monthly!O1744,IF($C$1="Yearly",Monthly!O1744*12,0)) -> 227.25 | F36: =IF($C$1="APM",Monthly!O1666,IF($C$1="Yearly",Monthly!O1666*12,0)) -> 186.75 | G36: =IF($C$1="APM",Monthly!O1588,IF($C$1="Yearly",Monthly!O1588*12,0)) -> 193.41667 | H36: =IF($C$1="APM",Monthly!O1510,IF($C$1="Yearly",Monthly!O1510*12,0)) -> 234.41667 | I36: =IF($C$1="APM",Monthly!O1433,IF($C$1="Yearly",Monthly!O1433*12,0)) -> 377.5 | J36: =IF($C$1="APM",Monthly!O1356,IF($C$1="Yearly",Monthly!O1356*12,0)) -> 479.75 | K36: =IF($C$1="APM",Monthly!O1279,IF($C$1="Yearly",Monthly!O1279*12,0)) -> 435.16667 | L36: =IF($C$1="APM",Monthly!O1201,IF($C$1="Yearly",Monthly!O1201*12,0)) -> 504.25 | M36: =IF($C$1="APM",Monthly!O1124,IF($C$1="Yearly",Monthly!O1124*12,0)) -> 640.83333 | N36: =IF($C$1="APM",Monthly!O1047,IF($C$1="Yearly",Monthly!O1047*12,0)) -> 580.25 | O36: =IF($C$1="APM",Monthly!O970,IF($C$1="Yearly",Monthly!O970*12,0)) -> 689.75 | P36: =IF($C$1="APM",Monthly!$O894,IF($C$1="Yearly",Monthly!$O894*12,0)) -> 753.5 | Q36: =IF($C$1="APM",Monthly!$O817,IF($C$1="Yearly",Monthly!$O817*12,0)) -> 658.58333 | R36: =IF($C$1="APM",Monthly!$O740,IF($C$1="Yearly",Monthly!$O740*12,0)) -> 657.83333 | S36: =IF($C$1="APM",Monthly!$O663,IF($C$1="Yearly",Monthly!$O663*12,0)) -> 804.08333 | T36: =IF($C$1="APM",Monthly!$O586,IF($C$1="Yearly",Monthly!$O586*12,0)) -> 682.33333 | U36: =IF($C$1="APM",Monthly!$O586,IF($C$1="Yearly",Monthly!$O586*12,0)) -> 682.33333 | Z36: =S36-P36 -> 50.583333 | AA36: =T36-Q36 -> 23.75 | AB36: 800
B37: Food | C37: =IF($C$1="APM",Monthly!O1899,IF($C$1="Yearly",Monthly!O1899*12,0)) -> 119.33333 | D37: =IF($C$1="APM",Monthly!O1822,IF($C$1="Yearly",Monthly!O1822*12,0)) -> 168.75 | E37: =IF($C$1="APM",Monthly!O1745,IF($C$1="Yearly",Monthly!O1745*12,0)) -> 59.916667 | F37: =IF($C$1="APM",Monthly!O1667,IF($C$1="Yearly",Monthly!O1667*12,0)) -> 87 | G37: =IF($C$1="APM",Monthly!O1589,IF($C$1="Yearly",Monthly!O1589*12,0)) -> 77.833333 | H37: =IF($C$1="APM",Monthly!O1511,IF($C$1="Yearly",Monthly!O1511*12,0)) -> 90.25 | I37: =IF($C$1="APM",Monthly!O1434,IF($C$1="Yearly",Monthly!O1434*12,0)) -> 113.41667 | J37: =IF($C$1="APM",Monthly!O1357,IF($C$1="Yearly",Monthly!O1357*12,0)) -> 29.833333 | K37: =IF($C$1="APM",Monthly!O1280,IF($C$1="Yearly",Monthly!O1280*12,0)) -> 98.583333 | L37: =IF($C$1="APM",Monthly!O1202,IF($C$1="Yearly",Monthly!O1202*12,0)) -> 98.916667 | M37: =IF($C$1="APM",Monthly!O1125,IF($C$1="Yearly",Monthly!O1125*12,0)) -> 142.83333 | N37: =IF($C$1="APM",Monthly!O1048,IF($C$1="Yearly",Monthly!O1048*12,0)) -> 165.58333 | O37: =IF($C$1="APM",Monthly!O971,IF($C$1="Yearly",Monthly!O971*12,0)) -> 207.91667 | P37: =IF($C$1="APM",Monthly!$O895,IF($C$1="Yearly",Monthly!$O895*12,0)) -> 189 | Q37: =IF($C$1="APM",Monthly!$O818,IF($C$1="Yearly",Monthly!$O818*12,0)) -> 179.66667 | R37: =IF($C$1="APM",Monthly!$O741,IF($C$1="Yearly",Monthly!$O741*12,0)) -> 103.5 | S37: =IF($C$1="APM",Monthly!$O664,IF($C$1="Yearly",Monthly!$O664*12,0)) -> 81.833333 | T37: =IF($C$1="APM",Monthly!$O587,IF($C$1="Yearly",Monthly!$O587*12,0)) -> 120.25 | U37: =IF($C$1="APM",Monthly!$O587,IF($C$1="Yearly",Monthly!$O587*12,0)) -> 120.25 | Z37: =S37-P37 -> -107.16667 | AA37: =T37-Q37 -> -59.416667 | AB37: 200
A38: Utilities | C38: =SUM(C40:C47) -> 550.33333 | D38: =SUM(D40:D47) -> 421.08333 | E38: =SUM(E40:E47) -> 364.25 | F38: =SUM(F40:F47) -> 457.58333 | G38: =SUM(G40:G47) -> 428.91667 | H38: =SUM(H40:H47) -> 421.58333 | I38: =SUM(I40:I47) -> 456.91667 | J38: =SUM(J40:J47) -> 474.16667 | ... U38: =SUM(U40:U47) -> 511 | Z38: =S38-P38 -> 27 | AA38: =(S38-P38)/P38 -> 0.089207048 | AB38: =SUM(AB40:AB47) -> 1000
B40: Electricity | C40: =IF($C$1="APM",Monthly!O1902,IF($C$1="Yearly",Monthly!O1902*12,0)) -> 57.166667 | D40: =IF($C$1="APM",Monthly!O1825,IF($C$1="Yearly",Monthly!O1825*12,0)) -> 52.083333 | E40: =IF($C$1="APM",Monthly!O1748,IF($C$1="Yearly",Monthly!O1748*12,0)) -> 62.083333 | F40: =IF($C$1="APM",Monthly!O1670,IF($C$1="Yearly",Monthly!O1670*12,0)) -> 65.416667 | G40: =IF($C$1="APM",Monthly!O1592,IF($C$1="Yearly",Monthly!O1592*12,0)) -> 74.5 | H40: =IF($C$1="APM",Monthly!O1514,IF($C$1="Yearly",Monthly!O1514*12,0)) -> 93.083333 | I40: =IF($C$1="APM",Monthly!O1437,IF($C$1="Yearly",Monthly!O1437*12,0)) -> 112.41667 | J40: =IF($C$1="APM",Monthly!O1360,IF($C$1="Yearly",Monthly!O1360*12,0)) -> 146.33333 | K40: =IF($C$1="APM",Monthly!O1283,IF($C$1="Yearly",Monthly!O1283*12,0)) -> 121.08333 | L40: =IF($C$1="APM",Monthly!O1205,IF($C$1="Yearly",Monthly!O1205*12,0)) -> 110.5 | M40: =IF($C$1="APM",Monthly!O1128,IF($C$1="Yearly",Monthly!O1128*12,0)) -> 147.16667 | N40: =IF($C$1="APM",Monthly!O1051,IF($C$1="Yearly",Monthly!O1051*12,0)) -> 112.83333 | O40: =IF($C$1="APM",Monthly!O974,IF($C$1="Yearly",Monthly!O974*12,0)) -> 327.08333 | P40: =IF($C$1="APM",Monthly!$O898,IF($C$1="Yearly",Monthly!$O898*12,0)) -> 157.08333 | Q40: =IF($C$1="APM",Monthly!$O821,IF($C$1="Yearly",Monthly!$O821*12,0)) -> 130 | R40: =IF($C$1="APM",Monthly!$O744,IF($C$1="Yearly",Monthly!$O744*12,0)) -> 83.333333 | S40: =IF($C$1="APM",Monthly!$O667,IF($C$1="Yearly",Monthly!$O667*12,0)) -> 90.333333 | T40: =IF($C$1="APM",Monthly!$O590,IF($C$1="Yearly",Monthly!$O590*12,0)) -> 96.833333 | U40: =IF($C$1="APM",Monthly!$O590,IF($C$1="Yearly",Monthly!$O590*12,0)) -> 96.833333 | Z40: =S40-P40 -> -66.75 | AA40: =T40-Q40 -> -33.166667 | AB40: 250
B41: Water | C41: =IF($C$1="APM",Monthly!O1903,IF($C$1="Yearly",Monthly!O1903*12,0)) -> 0 | D41: =IF($C$1="APM",Monthly!O1826,IF($C$1="Yearly",Monthly!O1826*12,0)) -> 0 | E41: =IF($C$1="APM",Monthly!O1749,IF($C$1="Yearly",Monthly!O1749*12,0)) -> 0 | F41: =IF($C$1="APM",Monthly!O1671,IF($C$1="Yearly",Monthly!O1671*12,0)) -> 0 | G41: =IF($C$1="APM",Monthly!O1593,IF($C$1="Yearly",Monthly!O1593*12,0)) -> 0 | H41: =IF($C$1="APM",Monthly!O1515,IF($C$1="Yearly",Monthly!O1515*12,0)) -> 0 | I41: =IF($C$1="APM",Monthly!O1438,IF($C$1="Yearly",Monthly!O1438*12,0)) -> 0 | J41: =IF($C$1="APM",Monthly!O1361,IF($C$1="Yearly",Monthly!O1361*12,0)) -> 0 | K41: =IF($C$1="APM",Monthly!O1284,IF($C$1="Yearly",Monthly!O1284*12,0)) -> 0 | L41: =IF($C$1="APM",Monthly!O1206,IF($C$1="Yearly",Monthly!O1206*12,0)) -> 0 | M41: =IF($C$1="APM",Monthly!O1129,IF($C$1="Yearly",Monthly!O1129*12,0)) -> 0 | N41: =IF($C$1="APM",Monthly!O1052,IF($C$1="Yearly",Monthly!O1052*12,0)) -> 0 | O41: =IF($C$1="APM",Monthly!O975,IF($C$1="Yearly",Monthly!O975*12,0)) -> 0 | P41: =IF($C$1="APM",Monthly!$O899,IF($C$1="Yearly",Monthly!$O899*12,0)) -> 0 | Q41: =IF($C$1="APM",Monthly!$O822,IF($C$1="Yearly",Monthly!$O822*12,0)) -> 21.166667 | R41: =IF($C$1="APM",Monthly!$O745,IF($C$1="Yearly",Monthly!$O745*12,0)) -> 51.583333 | S41: =IF($C$1="APM",Monthly!$O668,IF($C$1="Yearly",Monthly!$O668*12,0)) -> 55 | T41: =IF($C$1="APM",Monthly!$O591,IF($C$1="Yearly",Monthly!$O591*12,0)) -> 70.5 | U41: =IF($C$1="APM",Monthly!$O591,IF($C$1="Yearly",Monthly!$O591*12,0)) -> 70.5 | Z41: =S41-P41 -> 55 | AA41: =T41-Q41 -> 49.333333 | AB41: 150
B42: Trash/Sewer | C42: =IF($C$1="APM",Monthly!O1904,IF($C$1="Yearly",Monthly!O1904*12,0)) -> 0 | D42: =IF($C$1="APM",Monthly!O1827,IF($C$1="Yearly",Monthly!O1827*12,0)) -> 0 | E42: =IF($C$1="APM",Monthly!O1750,IF($C$1="Yearly",Monthly!O1750*12,0)) -> 0 | F42: =IF($C$1="APM",Monthly!O1672,IF($C$1="Yearly",Monthly!O1672*12,0)) -> 0 | G42: =IF($C$1="APM",Monthly!O1594,IF($C$1="Yearly",Monthly!O1594*12,0)) -> 0 | H42: =IF($C$1="APM",Monthly!O1516,IF($C$1="Yearly",Monthly!O1516*12,0)) -> 0 | I42: =IF($C$1="APM",Monthly!O1439,IF($C$1="Yearly",Monthly!O1439*12,0)) -> 0 | J42: =IF($C$1="APM",Monthly!O1362,IF($C$1="Yearly",Monthly!O1362*12,0)) -> 0 | K42: =IF($C$1="APM",Monthly!O1285,IF($C$1="Yearly",Monthly!O1285*12,0)) -> 0 | L42: =IF($C$1="APM",Monthly!O1207,IF($C$1="Yearly",Monthly!O1207*12,0)) -> 0 | M42: =IF($C$1="APM",Monthly!O1130,IF($C$1="Yearly",Monthly!O1130*12,0)) -> 0 | N42: =IF($C$1="APM",Monthly!O1053,IF($C$1="Yearly",Monthly!O1053*12,0)) -> 0 | O42: =IF($C$1="APM",Monthly!O976,IF($C$1="Yearly",Monthly!O976*12,0)) -> 0 | P42: =IF($C$1="APM",Monthly!$O900,IF($C$1="Yearly",Monthly!$O900*12,0)) -> 0 | Q42: =IF($C$1="APM",Monthly!$O823,IF($C$1="Yearly",Monthly!$O823*12,0)) -> 24.083333 | R42: =IF($C$1="APM",Monthly!$O746,IF($C$1="Yearly",Monthly!$O746*12,0)) -> 56.666667 | S42: =IF($C$1="APM",Monthly!$O669,IF($C$1="Yearly",Monthly!$O669*12,0)) -> 65 | T42: =IF($C$1="APM",Monthly!$O592,IF($C$1="Yearly",Monthly!$O592*12,0)) -> 53.083333 | U42: =IF($C$1="APM",Monthly!$O592,IF($C$1="Yearly",Monthly!$O592*12,0)) -> 53.083333 | Z42: =S42-P42 -> 65 | AA42: =T42-Q42 -> 29 | AB42: 100
B43: Gas | C43: =IF($C$1="APM",Monthly!O1905,IF($C$1="Yearly",Monthly!O1905*12,0)) -> 0 | D43: =IF($C$1="APM",Monthly!O1828,IF($C$1="Yearly",Monthly!O1828*12,0)) -> 0 | E43: =IF($C$1="APM",Monthly!O1751,IF($C$1="Yearly",Monthly!O1751*12,0)) -> 65.416667 | F43: =IF($C$1="APM",Monthly!O1673,IF($C$1="Yearly",Monthly!O1673*12,0)) -> 92 | G43: =IF($C$1="APM",Monthly!O1595,IF($C$1="Yearly",Monthly!O1595*12,0)) -> 87.083333 | H43: =IF($C$1="APM",Monthly!O1517,IF($C$1="Yearly",Monthly!O1517*12,0)) -> 97.25 | I43: =IF($C$1="APM",Monthly!O1440,IF($C$1="Yearly",Monthly!O1440*12,0)) -> 96.333333 | J43: =IF($C$1="APM",Monthly!O1363,IF($C$1="Yearly",Monthly!O1363*12,0)) -> 85.666667 | K43: =IF($C$1="APM",Monthly!O1286,IF($C$1="Yearly",Monthly!O1286*12,0)) -> 79.583333 | L43: =IF($C$1="APM",Monthly!O1208,IF($C$1="Yearly",Monthly!O1208*12,0)) -> 73 | M43: =IF($C$1="APM",Monthly!O1131,IF($C$1="Yearly",Monthly!O1131*12,0)) -> 89 | N43: =IF($C$1="APM",Monthly!O1054,IF($C$1="Yearly",Monthly!O1054*12,0)) -> 97.083333 | O43: =IF($C$1="APM",Monthly!O977,IF($C$1="Yearly",Monthly!O977*12,0)) -> 59.333333 | P43: =IF($C$1="APM",Monthly!$O901,IF($C$1="Yearly",Monthly!$O901*12,0)) -> 75.75 | Q43: =IF($C$1="APM",Monthly!$O824,IF($C$1="Yearly",Monthly!$O824*12,0)) -> 56.333333 | R43: =IF($C$1="APM",Monthly!$O747,IF($C$1="Yearly",Monthly!$O747*12,0)) -> 30.916667 | S43: =IF($C$1="APM",Monthly!$O670,IF($C$1="Yearly",Monthly!$O670*12,0)) -> 35.5 | T43: =IF($C$1="APM",Monthly!$O593,IF($C$1="Yearly",Monthly!$O593*12,0)) -> 40.666667 | U43: =IF($C$1="APM",Monthly!$O593,IF($C$1="Yearly",Monthly!$O593*12,0)) -> 40.666667 | Z43: =S43-P43 -> -40.25 | AA43: =T43-Q43 -> -15.666667 | AB43: 100
B44: C/I/Sat | C44: =IF($C$1="APM",Monthly!O1906,IF($C$1="Yearly",Monthly!O1906*12,0)) -> 70.5 | D44: =IF($C$1="APM",Monthly!O1829,IF($C$1="Yearly",Monthly!O1829*12,0)) -> 67.5 | E44: =IF($C$1="APM",Monthly!O1752,IF($C$1="Yearly",Monthly!O1752*12,0)) -> 71.25 | F44: =IF($C$1="APM",Monthly!O1674,IF($C$1="Yearly",Monthly!O1674*12,0)) -> 105 | G44: =IF($C$1="APM",Monthly!O1596,IF($C$1="Yearly",Monthly!O1596*12,0)) -> 109.58333 | H44: =IF($C$1="APM",Monthly!O1518,IF($C$1="Yearly",Monthly!O1518*12,0)) -> 109.58333 | I44: =IF($C$1="APM",Monthly!O1441,IF($C$1="Yearly",Monthly!O1441*12,0)) -> 132.66667 | J44: =IF($C$1="APM",Monthly!O1364,IF($C$1="Yearly",Monthly!O1364*12,0)) -> 75.833333 | K44: =IF($C$1="APM",Monthly!O1287,IF($C$1="Yearly",Monthly!O1287*12,0)) -> 60 | L44: =IF($C$1="APM",Monthly!O1209,IF($C$1="Yearly",Monthly!O1209*12,0)) -> 60.833333 | M44: =IF($C$1="APM",Monthly!O1132,IF($C$1="Yearly",Monthly!O1132*12,0)) -> 75.416667 | N44: =IF($C$1="APM",Monthly!O1055,IF($C$1="Yearly",Monthly!O1055*12,0)) -> 62.333333 | O44: =IF($C$1="APM",Monthly!O978,IF($C$1="Yearly",Monthly!O978*12,0)) -> 22.666667 | P44: =IF($C$1="APM",Monthly!$O902,IF($C$1="Yearly",Monthly!$O902*12,0)) -> 50 | Q44: =IF($C$1="APM",Monthly!$O825,IF($C$1="Yearly",Monthly!$O825*12,0)) -> 60.833333 | R44: =IF($C$1="APM",Monthly!$O748,IF($C$1="Yearly",Monthly!$O748*12,0)) -> 59 | S44: =IF($C$1="APM",Monthly!$O671,IF($C$1="Yearly",Monthly!$O671*12,0)) -> 58 | T44: =IF($C$1="APM",Monthly!$O594,IF($C$1="Yearly",Monthly!$O594*12,0)) -> 63.666667 | U44: =IF($C$1="APM",Monthly!$O594,IF($C$1="Yearly",Monthly!$O594*12,0)) -> 63.666667 | Z44: =S44-P44 -> 8 | AA44: =T44-Q44 -> 2.8333333 | AB44: 100
B45: Phone | C45: =IF($C$1="APM",Monthly!O1907,IF($C$1="Yearly",Monthly!O1907*12,0)) -> 30 | D45: =IF($C$1="APM",Monthly!O1830,IF($C$1="Yearly",Monthly!O1830*12,0)) -> 33.333333 | E45: =IF($C$1="APM",Monthly!O1753,IF($C$1="Yearly",Monthly!O1753*12,0)) -> 28.416667 | F45: =IF($C$1="APM",Monthly!O1675,IF($C$1="Yearly",Monthly!O1675*12,0)) -> 31.5 | G45: =IF($C$1="APM",Monthly!O1597,IF($C$1="Yearly",Monthly!O1597*12,0)) -> 33.166667 | H45: =IF($C$1="APM",Monthly!O1519,IF($C$1="Yearly",Monthly!O1519*12,0)) -> 35.666667 | I45: =IF($C$1="APM",Monthly!O1442,IF($C$1="Yearly",Monthly!O1442*12,0)) -> 25.833333 | J45: =IF($C$1="APM",Monthly!O1365,IF($C$1="Yearly",Monthly!O1365*12,0)) -> 31.416667 | K45: =IF($C$1="APM",Monthly!O1288,IF($C$1="Yearly",Monthly!O1288*12,0)) -> 35 | L45: =IF($C$1="APM",Monthly!O1210,IF($C$1="Yearly",Monthly!O1210*12,0)) -> 35 | M45: =IF($C$1="APM",Monthly!O1133,IF($C$1="Yearly",Monthly!O1133*12,0)) -> 35.666667 | N45: =IF($C$1="APM",Monthly!O1056,IF($C$1="Yearly",Monthly!O1056*12,0)) -> 20.416667 | O45: =IF($C$1="APM",Monthly!O979,IF($C$1="Yearly",Monthly!O979*12,0)) -> 33.416667 | P45: =IF($C$1="APM",Monthly!$O903,IF($C$1="Yearly",Monthly!$O903*12,0)) -> 4 | Q45: =IF($C$1="APM",Monthly!$O826,IF($C$1="Yearly",Monthly!$O826*12,0)) -> 4.5 | R45: =IF($C$1="APM",Monthly!$O749,IF($C$1="Yearly",Monthly!$O749*12,0)) -> 0 | S45: =IF($C$1="APM",Monthly!$O672,IF($C$1="Yearly",Monthly!$O672*12,0)) -> 0 | T45: =IF($C$1="APM",Monthly!$O595,IF($C$1="Yearly",Monthly!$O595*12,0)) -> 0 | U45: =IF($C$1="APM",Monthly!$O595,IF($C$1="Yearly",Monthly!$O595*12,0)) -> 0 | Z45: =S45-P45 -> -4 | AA45: =T45-Q45 -> -4.5 | AB45: =IF($C$1="APM",Monthly!$O595,IF($C$1="Yearly",Monthly!$O595*12,0)) -> 0
B46: Security System | C46: =IF($C$1="APM",Monthly!O1908,IF($C$1="Yearly",Monthly!O1908*12,0)) -> 276.16667 | D46: =IF($C$1="APM",Monthly!O1831,IF($C$1="Yearly",Monthly!O1831*12,0)) -> 187.41667 | E46: =IF($C$1="APM",Monthly!O1754,IF($C$1="Yearly",Monthly!O1754*12,0)) -> 58.75 | F46: =IF($C$1="APM",Monthly!O1676,IF($C$1="Yearly",Monthly!O1676*12,0)) -> 76.333333 | G46: =IF($C$1="APM",Monthly!O1598,IF($C$1="Yearly",Monthly!O1598*12,0)) -> 57.25 | H46: =IF($C$1="APM",Monthly!O1520,IF($C$1="Yearly",Monthly!O1520*12,0)) -> 17.416667 | I46: =IF($C$1="APM",Monthly!O1443,IF($C$1="Yearly",Monthly!O1443*12,0)) -> 20.25 | J46: =IF($C$1="APM",Monthly!O1366,IF($C$1="Yearly",Monthly!O1366*12,0)) -> 14.583333 | K46: =IF($C$1="APM",Monthly!O1289,IF($C$1="Yearly",Monthly!O1289*12,0)) -> 4.3333333 | L46: =IF($C$1="APM",Monthly!O1211,IF($C$1="Yearly",Monthly!O1211*12,0)) -> 0.16666667 | M46: =IF($C$1="APM",Monthly!O1134,IF($C$1="Yearly",Monthly!O1134*12,0)) -> 0 | N46: =IF($C$1="APM",Monthly!O1057,IF($C$1="Yearly",Monthly!O1057*12,0)) -> 7.5 | O46: =IF($C$1="APM",Monthly!O980,IF($C$1="Yearly",Monthly!O980*12,0)) -> 13.25 | P46: =IF($C$1="APM",Monthly!$O904,IF($C$1="Yearly",Monthly!$O904*12,0)) -> 15.833333 | Q46: =IF($C$1="APM",Monthly!$O827,IF($C$1="Yearly",Monthly!$O827*12,0)) -> 2.75 | R46: =IF($C$1="APM",Monthly!$O750,IF($C$1="Yearly",Monthly!$O750*12,0)) -> 2.5 | S46: =IF($C$1="APM",Monthly!$O673,IF($C$1="Yearly",Monthly!$O673*12,0)) -> 0.83333333 | T46: =IF($C$1="APM",Monthly!$O596,IF($C$1="Yearly",Monthly!$O596*12,0)) -> 1.6666667 | U46: =IF($C$1="APM",Monthly!$O596,IF($C$1="Yearly",Monthly!$O596*12,0)) -> 1.6666667 | Z46: =S46-P46 -> -15 | AA46: =T46-Q46 -> -1.0833333 | AB46: 100
B47: Cell | C47: =IF($C$1="APM",Monthly!O1909,IF($C$1="Yearly",Monthly!O1909*12,0)) -> 116.5 | D47: =IF($C$1="APM",Monthly!O1832,IF($C$1="Yearly",Monthly!O1832*12,0)) -> 80.75 | E47: =IF($C$1="APM",Monthly!O1755,IF($C$1="Yearly",Monthly!O1755*12,0)) -> 78.333333 | F47: =IF($C$1="APM",Monthly!O1677,IF($C$1="Yearly",Monthly!O1677*12,0)) -> 87.333333 | G47: =IF($C$1="APM",Monthly!O1599,IF($C$1="Yearly",Monthly!O1599*12,0)) -> 67.333333 | H47: =IF($C$1="APM",Monthly!O1521,IF($C$1="Yearly",Monthly!O1521*12,0)) -> 68.583333 | I47: =IF($C$1="APM",Monthly!O1444,IF($C$1="Yearly",Monthly!O1444*12,0)) -> 69.416667 | J47: =IF($C$1="APM",Monthly!O1367,IF($C$1="Yearly",Monthly!O1367*12,0)) -> 120.33333 | K47: =IF($C$1="APM",Monthly!O1290,IF($C$1="Yearly",Monthly!O1290*12,0)) -> 109.58333 | L47: =IF($C$1="APM",Monthly!O1212,IF($C$1="Yearly",Monthly!O1212*12,0)) -> 109.5 | M47: =IF($C$1="APM",Monthly!O1135,IF($C$1="Yearly",Monthly!O1135*12,0)) -> 71.083333 | N47: =IF($C$1="APM",Monthly!O1058,IF($C$1="Yearly",Monthly!O1058*12,0)) -> 70.5 | O47: =IF($C$1="APM",Monthly!O981,IF($C$1="Yearly",Monthly!O981*12,0)) -> 7 | P47: =IF($C$1="APM",Monthly!$O905,IF($C$1="Yearly",Monthly!$O905*12,0)) -> 0 | Q47: =IF($C$1="APM",Monthly!$O828,IF($C$1="Yearly",Monthly!$O828*12,0)) -> 0 | R47: =IF($C$1="APM",Monthly!$O751,IF($C$1="Yearly",Monthly!$O751*12,0)) -> 73.166667 | S47: =IF($C$1="APM",Monthly!$O674,IF($C$1="Yearly",Monthly!$O674*12,0)) -> 25 | T47: =IF($C$1="APM",Monthly!$O597,IF($C$1="Yearly",Monthly!$O597*12,0)) -> 184.58333 | U47: =IF($C$1="APM",Monthly!$O597,IF($C$1="Yearly",Monthly!$O597*12,0)) -> 184.58333 | Z47: =S47-P47 -> 25 | AA47: =T47-Q47 -> 184.58333 | AB47: 200
A48: Misc | C48: =SUM(C50:C56) -> 1477.1667 | D48: =SUM(D50:D56) -> 923.66667 | E48: =SUM(E50:E56) -> 886.25 | F48: =SUM(F50:F56) -> 498.66667 | G48: =SUM(G50:G56) -> 669.41667 | H48: =SUM(H50:H56) -> 762.16667 | I48: =SUM(I50:I56) -> 602.5 | J48: =SUM(J50:J56) -> 419.83333 | ... U48: =SUM(U50:U56) -> 1384.25 | Z48: =S48-P48 -> -149 | AA48: =(S48-P48)/P48 -> -0.10213058 | AB48: =SUM(AB50:AB56) -> 1910
B50: Misc | C50: =IF($C$1="APM",Monthly!O1912,IF($C$1="Yearly",Monthly!O1912*12,0)) -> 617.5 | D50: =IF($C$1="APM",Monthly!O1835,IF($C$1="Yearly",Monthly!O1835*12,0)) -> 219.58333 | E50: =IF($C$1="APM",Monthly!O1758,IF($C$1="Yearly",Monthly!O1758*12,0)) -> 210.33333 | F50: =IF($C$1="APM",Monthly!O1680,IF($C$1="Yearly",Monthly!O1680*12,0)) -> 152.25 | G50: =IF($C$1="APM",Monthly!O1602,IF($C$1="Yearly",Monthly!O1602*12,0)) -> 124.5 | H50: =IF($C$1="APM",Monthly!O1524,IF($C$1="Yearly",Monthly!O1524*12,0)) -> 114.66667 | I50: =IF($C$1="APM",Monthly!O1447,IF($C$1="Yearly",Monthly!O1447*12,0)) -> 133.25 | J50: =IF($C$1="APM",Monthly!O1370,IF($C$1="Yearly",Monthly!O1370*12,0)) -> 194.66667 | K50: =IF($C$1="APM",Monthly!O1293,IF($C$1="Yearly",Monthly!O1293*12,0)) -> 421.16667 | L50: =IF($C$1="APM",Monthly!O1215,IF($C$1="Yearly",Monthly!O1215*12,0)) -> 272.41667 | M50: =IF($C$1="APM",Monthly!O1138,IF($C$1="Yearly",Monthly!O1138*12,0)) -> 303.66667 | N50: =IF($C$1="APM",Monthly!O1061,IF($C$1="Yearly",Monthly!O1061*12,0)) -> 352.83333 | O50: =IF($C$1="APM",Monthly!O984,IF($C$1="Yearly",Monthly!O984*12,0)) -> 250.16667 | P50: =IF($C$1="APM",Monthly!$O908,IF($C$1="Yearly",Monthly!$O908*12,0)) -> 446.16667 | Q50: =IF($C$1="APM",Monthly!$O831,IF($C$1="Yearly",Monthly!$O831*12,0)) -> 200.41667 | R50: =IF($C$1="APM",Monthly!$O754,IF($C$1="Yearly",Monthly!$O754*12,0)) -> 187.25 | S50: =IF($C$1="APM",Monthly!$O677,IF($C$1="Yearly",Monthly!$O677*12,0)) -> 153.91667 | T50: =IF($C$1="APM",Monthly!$O600,IF($C$1="Yearly",Monthly!$O600*12,0)) -> 371.66667 | U50: =IF($C$1="APM",Monthly!$O600,IF($C$1="Yearly",Monthly!$O600*12,0)) -> 371.66667 | Z50: =S50-P50 -> -292.25 | AA50: =T50-Q50 -> 171.25 | AB50: 400
B51: Apparel/Pers | C51: =IF($C$1="APM",Monthly!O1913,IF($C$1="Yearly",Monthly!O1913*12,0)) -> 280.5 | D51: =IF($C$1="APM",Monthly!O1836,IF($C$1="Yearly",Monthly!O1836*12,0)) -> 182.5 | E51: =IF($C$1="APM",Monthly!O1759,IF($C$1="Yearly",Monthly!O1759*12,0)) -> 43.583333 | F51: =IF($C$1="APM",Monthly!O1681,IF($C$1="Yearly",Monthly!O1681*12,0)) -> 125 | G51: =IF($C$1="APM",Monthly!O1603,IF($C$1="Yearly",Monthly!O1603*12,0)) -> 80 | H51: =IF($C$1="APM",Monthly!O1525,IF($C$1="Yearly",Monthly!O1525*12,0)) -> 220.75 | I51: =IF($C$1="APM",Monthly!O1448,IF($C$1="Yearly",Monthly!O1448*12,0)) -> 70.833333 | J51: =IF($C$1="APM",Monthly!O1371,IF($C$1="Yearly",Monthly!O1371*12,0)) -> 65.833333 | K51: =IF($C$1="APM",Monthly!O1294,IF($C$1="Yearly",Monthly!O1294*12,0)) -> 118.91667 | L51: =IF($C$1="APM",Monthly!O1216,IF($C$1="Yearly",Monthly!O1216*12,0)) -> 111.75 | M51: =IF($C$1="APM",Monthly!O1139,IF($C$1="Yearly",Monthly!O1139*12,0)) -> 211.91667 | N51: =IF($C$1="APM",Monthly!O1062,IF($C$1="Yearly",Monthly!O1062*12,0)) -> 190.08333 | O51: =IF($C$1="APM",Monthly!O985,IF($C$1="Yearly",Monthly!O985*12,0)) -> 227.08333 | P51: =IF($C$1="APM",Monthly!$O909,IF($C$1="Yearly",Monthly!$O909*12,0)) -> 227.91667 | Q51: =IF($C$1="APM",Monthly!$O832,IF($C$1="Yearly",Monthly!$O832*12,0)) -> 103.41667 | R51: =IF($C$1="APM",Monthly!$O755,IF($C$1="Yearly",Monthly!$O755*12,0)) -> 212.5 | S51: =IF($C$1="APM",Monthly!$O678,IF($C$1="Yearly",Monthly!$O678*12,0)) -> 180.58333 | T51: =IF($C$1="APM",Monthly!$O601,IF($C$1="Yearly",Monthly!$O601*12,0)) -> 201.91667 | U51: =IF($C$1="APM",Monthly!$O601,IF($C$1="Yearly",Monthly!$O601*12,0)) -> 201.91667 | Z51: =S51-P51 -> -47.333333 | AA51: =T51-Q51 -> 98.5 | AB51: 200
B52: Home Furn. | C52: =IF($C$1="APM",Monthly!O1914,IF($C$1="Yearly",Monthly!O1914*12,0)) -> 211.66667 | D52: =IF($C$1="APM",Monthly!O1837,IF($C$1="Yearly",Monthly!O1837*12,0)) -> 15.833333 | E52: =IF($C$1="APM",Monthly!O1760,IF($C$1="Yearly",Monthly!O1760*12,0)) -> 340.58333 | F52: =IF($C$1="APM",Monthly!O1682,IF($C$1="Yearly",Monthly!O1682*12,0)) -> 2.0833333 | G52: =IF($C$1="APM",Monthly!O1604,IF($C$1="Yearly",Monthly!O1604*12,0)) -> 0 | H52: =IF($C$1="APM",Monthly!O1526,IF($C$1="Yearly",Monthly!O1526*12,0)) -> 7.25 | I52: =IF($C$1="APM",Monthly!O1449,IF($C$1="Yearly",Monthly!O1449*12,0)) -> 71.333333 | J52: =IF($C$1="APM",Monthly!O1372,IF($C$1="Yearly",Monthly!O1372*12,0)) -> 16.25 | K52: =IF($C$1="APM",Monthly!O1295,IF($C$1="Yearly",Monthly!O1295*12,0)) -> 0 | L52: =IF($C$1="APM",Monthly!O1217,IF($C$1="Yearly",Monthly!O1217*12,0)) -> 39.583333 | M52: =IF($C$1="APM",Monthly!O1140,IF($C$1="Yearly",Monthly!O1140*12,0)) -> 0 | N52: =IF($C$1="APM",Monthly!O1063,IF($C$1="Yearly",Monthly!O1063*12,0)) -> 5.8333333 | O52: =IF($C$1="APM",Monthly!O986,IF($C$1="Yearly",Monthly!O986*12,0)) -> 23.083333 | P52: =IF($C$1="APM",Monthly!$O910,IF($C$1="Yearly",Monthly!$O910*12,0)) -> 0 | Q52: =IF($C$1="APM",Monthly!$O833,IF($C$1="Yearly",Monthly!$O833*12,0)) -> 109.91667 | R52: =IF($C$1="APM",Monthly!$O756,IF($C$1="Yearly",Monthly!$O756*12,0)) -> 0 | S52: =IF($C$1="APM",Monthly!$O679,IF($C$1="Yearly",Monthly!$O679*12,0)) -> 0 | T52: =IF($C$1="APM",Monthly!$O602,IF($C$1="Yearly",Monthly!$O602*12,0)) -> 0 | U52: =IF($C$1="APM",Monthly!$O602,IF($C$1="Yearly",Monthly!$O602*12,0)) -> 0 | Z52: =S52-P52 -> 0 | AA52: =T52-Q52 -> -109.91667 | AB52: 200
B53: Appliances/Kitch. | C53: =IF($C$1="APM",Monthly!O1915,IF($C$1="Yearly",Monthly!O1915*12,0)) -> 0 | D53: =IF($C$1="APM",Monthly!O1838,IF($C$1="Yearly",Monthly!O1838*12,0)) -> 6.9166667 | E53: =IF($C$1="APM",Monthly!O1761,IF($C$1="Yearly",Monthly!O1761*12,0)) -> 63.5 | F53: =IF($C$1="APM",Monthly!O1683,IF($C$1="Yearly",Monthly!O1683*12,0)) -> 6.1666667 | G53: =IF($C$1="APM",Monthly!O1605,IF($C$1="Yearly",Monthly!O1605*12,0)) -> 7.8333333 | H53: =IF($C$1="APM",Monthly!O1527,IF($C$1="Yearly",Monthly!O1527*12,0)) -> 0.83333333 | I53: =IF($C$1="APM",Monthly!O1450,IF($C$1="Yearly",Monthly!O1450*12,0)) -> 45.083333 | J53: =IF($C$1="APM",Monthly!O1373,IF($C$1="Yearly",Monthly!O1373*12,0)) -> 2.5833333 | K53: =IF($C$1="APM",Monthly!O1296,IF($C$1="Yearly",Monthly!O1296*12,0)) -> 18.666667 | L53: =IF($C$1="APM",Monthly!O1218,IF($C$1="Yearly",Monthly!O1218*12,0)) -> 37.333333 | M53: =IF($C$1="APM",Monthly!O1141,IF($C$1="Yearly",Monthly!O1141*12,0)) -> 28.333333 | N53: =IF($C$1="APM",Monthly!O1064,IF($C$1="Yearly",Monthly!O1064*12,0)) -> 5.8333333 | O53: =IF($C$1="APM",Monthly!O987,IF($C$1="Yearly",Monthly!O987*12,0)) -> 39.583333 | P53: =IF($C$1="APM",Monthly!$O911,IF($C$1="Yearly",Monthly!$O911*12,0)) -> 37.25 | Q53: =IF($C$1="APM",Monthly!$O834,IF($C$1="Yearly",Monthly!$O834*12,0)) -> 9.5 | R53: =IF($C$1="APM",Monthly!$O757,IF($C$1="Yearly",Monthly!$O757*12,0)) -> 23.083333 | S53: =IF($C$1="APM",Monthly!$O680,IF($C$1="Yearly",Monthly!$O680*12,0)) -> 63 | T53: =IF($C$1="APM",Monthly!$O603,IF($C$1="Yearly",Monthly!$O603*12,0)) -> 13.833333 | U53: =IF($C$1="APM",Monthly!$O603,IF($C$1="Yearly",Monthly!$O603*12,0)) -> 13.833333 | Z53: =S53-P53 -> 25.75 | AA53: =T53-Q53 -> 4.3333333 | AB53: 200
B54: Gifts | C54: =IF($C$1="APM",Monthly!O1916,IF($C$1="Yearly",Monthly!O1916*12,0)) -> 181.83333 | D54: =IF($C$1="APM",Monthly!O1839,IF($C$1="Yearly",Monthly!O1839*12,0)) -> 221.41667 | E54: =IF($C$1="APM",Monthly!O1762,IF($C$1="Yearly",Monthly!O1762*12,0)) -> 138.66667 | F54: =IF($C$1="APM",Monthly!O1684,IF($C$1="Yearly",Monthly!O1684*12,0)) -> 69.916667 | G54: =IF($C$1="APM",Monthly!O1606,IF($C$1="Yearly",Monthly!O1606*12,0)) -> 80.5 | H54: =IF($C$1="APM",Monthly!O1528,IF($C$1="Yearly",Monthly!O1528*12,0)) -> 122.75 | I54: =IF($C$1="APM",Monthly!O1451,IF($C$1="Yearly",Monthly!O1451*12,0)) -> 176.25 | J54: =IF($C$1="APM",Monthly!O1374,IF($C$1="Yearly",Monthly!O1374*12,0)) -> 123.33333 | K54: =IF($C$1="APM",Monthly!O1297,IF($C$1="Yearly",Monthly!O1297*12,0)) -> 152.66667 | L54: =IF($C$1="APM",Monthly!O1219,IF($C$1="Yearly",Monthly!O1219*12,0)) -> 339.66667 | M54: =IF($C$1="APM",Monthly!O1142,IF($C$1="Yearly",Monthly!O1142*12,0)) -> 174.5 | N54: =IF($C$1="APM",Monthly!O1065,IF($C$1="Yearly",Monthly!O1065*12,0)) -> 147 | O54: =IF($C$1="APM",Monthly!O988,IF($C$1="Yearly",Monthly!O988*12,0)) -> 222.25 | P54: =IF($C$1="APM",Monthly!$O912,IF($C$1="Yearly",Monthly!$O912*12,0)) -> 251.83333 | Q54: =IF($C$1="APM",Monthly!$O835,IF($C$1="Yearly",Monthly!$O835*12,0)) -> 93.416667 | R54: =IF($C$1="APM",Monthly!$O758,IF($C$1="Yearly",Monthly!$O758*12,0)) -> 126.33333 | S54: =IF($C$1="APM",Monthly!$O681,IF($C$1="Yearly",Monthly!$O681*12,0)) -> 272 | T54: =IF($C$1="APM",Monthly!$O604,IF($C$1="Yearly",Monthly!$O604*12,0)) -> 39.083333 | U54: =IF($C$1="APM",Monthly!$O604,IF($C$1="Yearly",Monthly!$O604*12,0)) -> 39.083333 | Z54: =S54-P54 -> 20.166667 | AA54: =T54-Q54 -> -54.333333 | AB54: 100
B55: Fitness | C55: =IF($C$1="APM",Monthly!O1917,IF($C$1="Yearly",Monthly!O1917*12,0)) -> 0 | D55: =IF($C$1="APM",Monthly!O1840,IF($C$1="Yearly",Monthly!O1840*12,0)) -> 0 | E55: =IF($C$1="APM",Monthly!O1763,IF($C$1="Yearly",Monthly!O1763*12,0)) -> 0 | F55: =IF($C$1="APM",Monthly!O1685,IF($C$1="Yearly",Monthly!O1685*12,0)) -> 0 | G55: =IF($C$1="APM",Monthly!O1607,IF($C$1="Yearly",Monthly!O1607*12,0)) -> 3.3333333 | H55: =IF($C$1="APM",Monthly!O1529,IF($C$1="Yearly",Monthly!O1529*12,0)) -> 7.5 | I55: =IF($C$1="APM",Monthly!O1452,IF($C$1="Yearly",Monthly!O1452*12,0)) -> 7.5 | J55: =IF($C$1="APM",Monthly!O1375,IF($C$1="Yearly",Monthly!O1375*12,0)) -> 16.666667 | K55: =IF($C$1="APM",Monthly!O1298,IF($C$1="Yearly",Monthly!O1298*12,0)) -> 25.583333 | L55: =IF($C$1="APM",Monthly!O1220,IF($C$1="Yearly",Monthly!O1220*12,0)) -> 0 | M55: =IF($C$1="APM",Monthly!O1143,IF($C$1="Yearly",Monthly!O1143*12,0)) -> 0 | N55: =IF($C$1="APM",Monthly!O1066,IF($C$1="Yearly",Monthly!O1066*12,0)) -> 27.083333 | O55: =IF($C$1="APM",Monthly!O989,IF($C$1="Yearly",Monthly!O989*12,0)) -> 0 | P55: =IF($C$1="APM",Monthly!$O913,IF($C$1="Yearly",Monthly!$O913*12,0)) -> 0 | Q55: =IF($C$1="APM",Monthly!$O836,IF($C$1="Yearly",Monthly!$O836*12,0)) -> 39 | R55: =IF($C$1="APM",Monthly!$O759,IF($C$1="Yearly",Monthly!$O759*12,0)) -> 94 | S55: =IF($C$1="APM",Monthly!$O682,IF($C$1="Yearly",Monthly!$O682*12,0)) -> 95 | T55: =IF($C$1="APM",Monthly!$O605,IF($C$1="Yearly",Monthly!$O605*12,0)) -> 110 | U55: =IF($C$1="APM",Monthly!$O605,IF($C$1="Yearly",Monthly!$O605*12,0)) -> 110 | Z55: =S55-P55 -> 95 | AA55: =T55-Q55 -> 71 | AB55: =IF($C$1="APM",Monthly!$O605,IF($C$1="Yearly",Monthly!$O605*12,0)) -> 110
B56: EET | C56: =IF($C$1="APM",Monthly!O1918,IF($C$1="Yearly",Monthly!O1918*12,0)) -> 185.66667 | D56: =IF($C$1="APM",Monthly!O1841,IF($C$1="Yearly",Monthly!O1841*12,0)) -> 277.41667 | E56: =IF($C$1="APM",Monthly!O1764,IF($C$1="Yearly",Monthly!O1764*12,0)) -> 89.583333 | F56: =IF($C$1="APM",Monthly!O1686,IF($C$1="Yearly",Monthly!O1686*12,0)) -> 143.25 | G56: =IF($C$1="APM",Monthly!O1608,IF($C$1="Yearly",Monthly!O1608*12,0)) -> 373.25 | H56: =IF($C$1="APM",Monthly!O1530,IF($C$1="Yearly",Monthly!O1530*12,0)) -> 288.41667 | I56: =IF($C$1="APM",Monthly!O1453,IF($C$1="Yearly",Monthly!O1453*12,0)) -> 98.25 | J56: =IF($C$1="APM",Monthly!O1376,IF($C$1="Yearly",Monthly!O1376*12,0)) -> 0.5 | K56: =IF($C$1="APM",Monthly!O1299,IF($C$1="Yearly",Monthly!O1299*12,0)) -> 428 | L56: =IF($C$1="APM",Monthly!O1221,IF($C$1="Yearly",Monthly!O1221*12,0)) -> 119.66667 | M56: =IF($C$1="APM",Monthly!O1144,IF($C$1="Yearly",Monthly!O1144*12,0)) -> 204 | N56: =IF($C$1="APM",Monthly!O1067,IF($C$1="Yearly",Monthly!O1067*12,0)) -> 577.58333 | O56: =IF($C$1="APM",Monthly!O990,IF($C$1="Yearly",Monthly!O990*12,0)) -> 630.08333 | P56: =IF($C$1="APM",Monthly!$O914,IF($C$1="Yearly",Monthly!$O914*12,0)) -> 495.75 | Q56: =IF($C$1="APM",Monthly!$O837,IF($C$1="Yearly",Monthly!$O837*12,0)) -> 1017.0833 | R56: =IF($C$1="APM",Monthly!$O760,IF($C$1="Yearly",Monthly!$O760*12,0)) -> 254.91667 | S56: =IF($C$1="APM",Monthly!$O683,IF($C$1="Yearly",Monthly!$O683*12,0)) -> 545.41667 | T56: =IF($C$1="APM",Monthly!$O606,IF($C$1="Yearly",Monthly!$O606*12,0)) -> 647.75 | U56: =IF($C$1="APM",Monthly!$O606,IF($C$1="Yearly",Monthly!$O606*12,0)) -> 647.75 | Z56: =S56-P56 -> 49.666667 | AA56: =T56-Q56 -> -369.33333 | AB56: 700
A57: Education | C57: =SUM(C59:C60) -> 0 | D57: =SUM(D59:D60) -> 0 | E57: =SUM(E59:E60) -> 0 | F57: =SUM(F59:F60) -> 0 | G57: =SUM(G59:G60) -> 0 | H57: =SUM(H59:H60) -> 632.75 | I57: =SUM(I59:I60) -> 347.83333 | J57: =SUM(J59:J60) -> 1224.25 | ... U57: =SUM(U59:U60) -> 2422.5833 | Z57: =S57-P57 -> -319 | AA57: =(S57-P57)/P57 -> -0.12925446 | AB57: =SUM(AB59:AB60) -> 2600
B59: School/Classes | C59: =IF($C$1="APM",Monthly!O1921,IF($C$1="Yearly",Monthly!O1921*12,0)) -> 0 | D59: =IF($C$1="APM",Monthly!O1844,IF($C$1="Yearly",Monthly!O1844*12,0)) -> 0 | E59: =IF($C$1="APM",Monthly!O1767,IF($C$1="Yearly",Monthly!O1767*12,0)) -> 0 | F59: =IF($C$1="APM",Monthly!O1689,IF($C$1="Yearly",Monthly!O1689*12,0)) -> 0 | G59: =IF($C$1="APM",Monthly!O1611,IF($C$1="Yearly",Monthly!O1611*12,0)) -> 0 | H59: =IF($C$1="APM",Monthly!O1533,IF($C$1="Yearly",Monthly!O1533*12,0)) -> 632.75 | I59: =IF($C$1="APM",Monthly!O1456,IF($C$1="Yearly",Monthly!O1456*12,0)) -> 347.83333 | J59: =IF($C$1="APM",Monthly!O1379,IF($C$1="Yearly",Monthly!O1379*12,0)) -> 1224.25 | K59: =IF($C$1="APM",Monthly!O1302,IF($C$1="Yearly",Monthly!O1302*12,0)) -> 1338.9167 | L59: =IF($C$1="APM",Monthly!O1224,IF($C$1="Yearly",Monthly!O1224*12,0)) -> 204.58333 | M59: =IF($C$1="APM",Monthly!O1147,IF($C$1="Yearly",Monthly!O1147*12,0)) -> 14.583333 | N59: =IF($C$1="APM",Monthly!O1070,IF($C$1="Yearly",Monthly!O1070*12,0)) -> 0 | O59: =IF($C$1="APM",Monthly!O993,IF($C$1="Yearly",Monthly!O993*12,0)) -> 208.16667 | P59: =IF($C$1="APM",Monthly!$O917,IF($C$1="Yearly",Monthly!$O917*12,0)) -> 576.58333 | Q59: =IF($C$1="APM",Monthly!$O840,IF($C$1="Yearly",Monthly!$O840*12,0)) -> 335.75 | R59: =IF($C$1="APM",Monthly!$O763,IF($C$1="Yearly",Monthly!$O763*12,0)) -> 321.33333 | S59: =IF($C$1="APM",Monthly!$O686,IF($C$1="Yearly",Monthly!$O686*12,0)) -> 613.75 | T59: =IF($C$1="APM",Monthly!$O609,IF($C$1="Yearly",Monthly!$O609*12,0)) -> 674.58333 | U59: =IF($C$1="APM",Monthly!$O609,IF($C$1="Yearly",Monthly!$O609*12,0)) -> 674.58333 | Z59: =S59-P59 -> 37.166667 | AA59: =T59-Q59 -> 338.83333 | AB59: 800
B60: Day Care/ After School | C60: =IF($C$1="APM",Monthly!O1922,IF($C$1="Yearly",Monthly!O1922*12,0)) -> 0 | D60: =IF($C$1="APM",Monthly!O1845,IF($C$1="Yearly",Monthly!O1845*12,0)) -> 0 | E60: =IF($C$1="APM",Monthly!O1768,IF($C$1="Yearly",Monthly!O1768*12,0)) -> 0 | F60: =IF($C$1="APM",Monthly!O1690,IF($C$1="Yearly",Monthly!O1690*12,0)) -> 0 | G60: =IF($C$1="APM",Monthly!O1612,IF($C$1="Yearly",Monthly!O1612*12,0)) -> 0 | H60: =IF($C$1="APM",Monthly!O1534,IF($C$1="Yearly",Monthly!O1534*12,0)) -> 0 | I60: =IF($C$1="APM",Monthly!O1457,IF($C$1="Yearly",Monthly!O1457*12,0)) -> 0 | J60: =IF($C$1="APM",Monthly!O1380,IF($C$1="Yearly",Monthly!O1380*12,0)) -> 0 | K60: =IF($C$1="APM",Monthly!O1303,IF($C$1="Yearly",Monthly!O1303*12,0)) -> 1366.5 | L60: =IF($C$1="APM",Monthly!O1225,IF($C$1="Yearly",Monthly!O1225*12,0)) -> 1370.25 | M60: =IF($C$1="APM",Monthly!O1148,IF($C$1="Yearly",Monthly!O1148*12,0)) -> 2886.5833 | N60: =IF($C$1="APM",Monthly!O1071,IF($C$1="Yearly",Monthly!O1071*12,0)) -> 2596.0833 | O60: =IF($C$1="APM",Monthly!O994,IF($C$1="Yearly",Monthly!O994*12,0)) -> 2182.8333 | P60: =IF($C$1="APM",Monthly!$O918,IF($C$1="Yearly",Monthly!$O918*12,0)) -> 1891.4167 | Q60: =IF($C$1="APM",Monthly!$O841,IF($C$1="Yearly",Monthly!$O841*12,0)) -> 1389.0833 | R60: =IF($C$1="APM",Monthly!$O764,IF($C$1="Yearly",Monthly!$O764*12,0)) -> 1618.9583 | S60: =IF($C$1="APM",Monthly!$O687,IF($C$1="Yearly",Monthly!$O687*12,0)) -> 1535.25 | T60: =IF($C$1="APM",Monthly!$O610,IF($C$1="Yearly",Monthly!$O610*12,0)) -> 1748 | U60: =IF($C$1="APM",Monthly!$O610,IF($C$1="Yearly",Monthly!$O610*12,0)) -> 1748 | Z60: =S60-P60 -> -356.16667 | AA60: =T60-Q60 -> 358.91667 | AB60: 1800
A61: Health & Life | C61: =SUM(C63:C66) -> 155.66667 | D61: =SUM(D63:D66) -> 170.60417 | E61: =SUM(E63:E66) -> 84.166667 | F61: =SUM(F63:F66) -> 151.5 | G61: =SUM(G63:G66) -> 196.5 | H61: =SUM(H63:H66) -> 211.75 | I61: =SUM(I63:I66) -> 310.33333 | J61: =SUM(J63:J66) -> 319.75 | ... U61: =SUM(U63:U66) -> 510.41667 | Z61: =S61-P61 -> -305.83333 | AA61: =(S61-P61)/P61 -> -0.44484848 | AB61: =SUM(AB63:AB66) -> 587
B63: Health Insurance | C63: =IF($C$1="APM",Monthly!O1925,IF($C$1="Yearly",Monthly!O1925*12,0)) -> 72.25 | D63: =IF($C$1="APM",Monthly!O1848,IF($C$1="Yearly",Monthly!O1848*12,0)) -> 78.4375 | E63: =IF($C$1="APM",Monthly!O1771,IF($C$1="Yearly",Monthly!O1771*12,0)) -> 26.833333 | F63: =IF($C$1="APM",Monthly!O1693,IF($C$1="Yearly",Monthly!O1693*12,0)) -> 120.75 | G63: =IF($C$1="APM",Monthly!O1615,IF($C$1="Yearly",Monthly!O1615*12,0)) -> 132 | H63: =IF($C$1="APM",Monthly!O1537,IF($C$1="Yearly",Monthly!O1537*12,0)) -> 141.16667 | I63: =IF($C$1="APM",Monthly!O1460,IF($C$1="Yearly",Monthly!O1460*12,0)) -> 148.16667 | J63: =IF($C$1="APM",Monthly!O1383,IF($C$1="Yearly",Monthly!O1383*12,0)) -> 165.91667 | K63: =IF($C$1="APM",Monthly!O1306,IF($C$1="Yearly",Monthly!O1306*12,0)) -> 239.58333 | L63: =IF($C$1="APM",Monthly!O1228,IF($C$1="Yearly",Monthly!O1228*12,0)) -> 78.576389 | M63: =IF($C$1="APM",Monthly!O1151,IF($C$1="Yearly",Monthly!O1151*12,0)) -> 290.66667 | N63: =IF($C$1="APM",Monthly!O1074,IF($C$1="Yearly",Monthly!O1074*12,0)) -> 305.08333 | O63: =IF($C$1="APM",Monthly!O997,IF($C$1="Yearly",Monthly!O997*12,0)) -> 290.08333 | P63: =IF($C$1="APM",Monthly!$O921,IF($C$1="Yearly",Monthly!$O921*12,0)) -> 295.91667 | Q63: =IF($C$1="APM",Monthly!$O844,IF($C$1="Yearly",Monthly!$O844*12,0)) -> 331.08333 | R63: =IF($C$1="APM",Monthly!$O767,IF($C$1="Yearly",Monthly!$O767*12,0)) -> 78.166667 | S63: =IF($C$1="APM",Monthly!$O690,IF($C$1="Yearly",Monthly!$O690*12,0)) -> 83.166667 | T63: =IF($C$1="APM",Monthly!$O613,IF($C$1="Yearly",Monthly!$O613*12,0)) -> 78.166667 | U63: =IF($C$1="APM",Monthly!$O613,IF($C$1="Yearly",Monthly!$O613*12,0)) -> 78.166667 | Z63: =S63-P63 -> -212.75 | AA63: =T63-Q63 -> -252.91667 | AB63: 100
B64: Medical | C64: =IF($C$1="APM",Monthly!O1926,IF($C$1="Yearly",Monthly!O1926*12,0)) -> 37.833333 | D64: =IF($C$1="APM",Monthly!O1849,IF($C$1="Yearly",Monthly!O1849*12,0)) -> 70.166667 | E64: =IF($C$1="APM",Monthly!O1772,IF($C$1="Yearly",Monthly!O1772*12,0)) -> 25 | F64: =IF($C$1="APM",Monthly!O1694,IF($C$1="Yearly",Monthly!O1694*12,0)) -> 17.416667 | G64: =IF($C$1="APM",Monthly!O1616,IF($C$1="Yearly",Monthly!O1616*12,0)) -> 37.916667 | H64: =IF($C$1="APM",Monthly!O1538,IF($C$1="Yearly",Monthly!O1538*12,0)) -> 23.083333 | I64: =IF($C$1="APM",Monthly!O1461,IF($C$1="Yearly",Monthly!O1461*12,0)) -> 113.16667 | J64: =IF($C$1="APM",Monthly!O1384,IF($C$1="Yearly",Monthly!O1384*12,0)) -> 110.91667 | K64: =IF($C$1="APM",Monthly!O1307,IF($C$1="Yearly",Monthly!O1307*12,0)) -> 130.25 | L64: =IF($C$1="APM",Monthly!O1229,IF($C$1="Yearly",Monthly!O1229*12,0)) -> 52.5 | M64: =IF($C$1="APM",Monthly!O1152,IF($C$1="Yearly",Monthly!O1152*12,0)) -> 46 | N64: =IF($C$1="APM",Monthly!O1075,IF($C$1="Yearly",Monthly!O1075*12,0)) -> 52.5 | O64: =IF($C$1="APM",Monthly!O998,IF($C$1="Yearly",Monthly!O998*12,0)) -> 105.33333 | P64: =IF($C$1="APM",Monthly!$O922,IF($C$1="Yearly",Monthly!$O922*12,0)) -> 78.083333 | Q64: =IF($C$1="APM",Monthly!$O845,IF($C$1="Yearly",Monthly!$O845*12,0)) -> 44.166667 | R64: =IF($C$1="APM",Monthly!$O768,IF($C$1="Yearly",Monthly!$O768*12,0)) -> 17.583333 | S64: =IF($C$1="APM",Monthly!$O691,IF($C$1="Yearly",Monthly!$O691*12,0)) -> 32.833333 | T64: =IF($C$1="APM",Monthly!$O614,IF($C$1="Yearly",Monthly!$O614*12,0)) -> 166.58333 | U64: =IF($C$1="APM",Monthly!$O614,IF($C$1="Yearly",Monthly!$O614*12,0)) -> 166.58333 | Z64: =S64-P64 -> -45.25 | AA64: =T64-Q64 -> 122.41667 | AB64: 200
B65: Insurance (LTD/STD/ADD) | C65: =IF($C$1="APM",Monthly!O1927,IF($C$1="Yearly",Monthly!O1927*12,0)) -> 45.583333 | D65: =IF($C$1="APM",Monthly!O1850,IF($C$1="Yearly",Monthly!O1850*12,0)) -> 22 | E65: =IF($C$1="APM",Monthly!O1773,IF($C$1="Yearly",Monthly!O1773*12,0)) -> 32.333333 | F65: =IF($C$1="APM",Monthly!O1695,IF($C$1="Yearly",Monthly!O1695*12,0)) -> 13.333333 | G65: =IF($C$1="APM",Monthly!O1617,IF($C$1="Yearly",Monthly!O1617*12,0)) -> 26.583333 | H65: =IF($C$1="APM",Monthly!O1539,IF($C$1="Yearly",Monthly!O1539*12,0)) -> 47.5 | I65: =IF($C$1="APM",Monthly!O1462,IF($C$1="Yearly",Monthly!O1462*12,0)) -> 49 | J65: =IF($C$1="APM",Monthly!O1385,IF($C$1="Yearly",Monthly!O1385*12,0)) -> 42.916667 | K65: =IF($C$1="APM",Monthly!O1308,IF($C$1="Yearly",Monthly!O1308*12,0)) -> 76 | L65: =IF($C$1="APM",Monthly!O1230,IF($C$1="Yearly",Monthly!O1230*12,0)) -> 24.25 | M65: =IF($C$1="APM",Monthly!O1153,IF($C$1="Yearly",Monthly!O1153*12,0)) -> 92.416667 | N65: =IF($C$1="APM",Monthly!O1076,IF($C$1="Yearly",Monthly!O1076*12,0)) -> 102.16667 | O65: =IF($C$1="APM",Monthly!O999,IF($C$1="Yearly",Monthly!O999*12,0)) -> 106.08333 | P65: =IF($C$1="APM",Monthly!$O923,IF($C$1="Yearly",Monthly!$O923*12,0)) -> 110.5 | Q65: =IF($C$1="APM",Monthly!$O846,IF($C$1="Yearly",Monthly!$O846*12,0)) -> 145.83333 | R65: =IF($C$1="APM",Monthly!$O769,IF($C$1="Yearly",Monthly!$O769*12,0)) -> 229 | S65: =IF($C$1="APM",Monthly!$O692,IF($C$1="Yearly",Monthly!$O692*12,0)) -> 28.666667 | T65: =IF($C$1="APM",Monthly!$O615,IF($C$1="Yearly",Monthly!$O615*12,0)) -> 28.666667 | U65: =IF($C$1="APM",Monthly!$O615,IF($C$1="Yearly",Monthly!$O615*12,0)) -> 28.666667 | Z65: =S65-P65 -> -81.833333 | AA65: =T65-Q65 -> -117.16667 | AB65: 50
B66: Life Insurance | C66: =IF($C$1="APM",Monthly!O1928,IF($C$1="Yearly",Monthly!O1928*12,0)) -> 0 | D66: =IF($C$1="APM",Monthly!O1851,IF($C$1="Yearly",Monthly!O1851*12,0)) -> 0 | E66: =IF($C$1="APM",Monthly!O1774,IF($C$1="Yearly",Monthly!O1774*12,0)) -> 0 | F66: =IF($C$1="APM",Monthly!O1696,IF($C$1="Yearly",Monthly!O1696*12,0)) -> 0 | G66: =IF($C$1="APM",Monthly!O1618,IF($C$1="Yearly",Monthly!O1618*12,0)) -> 0 | H66: =IF($C$1="APM",Monthly!O1540,IF($C$1="Yearly",Monthly!O1540*12,0)) -> 0 | I66: =IF($C$1="APM",Monthly!O1463,IF($C$1="Yearly",Monthly!O1463*12,0)) -> 0 | J66: =IF($C$1="APM",Monthly!O1386,IF($C$1="Yearly",Monthly!O1386*12,0)) -> 0 | K66: =IF($C$1="APM",Monthly!O1309,IF($C$1="Yearly",Monthly!O1309*12,0)) -> 0 | L66: =IF($C$1="APM",Monthly!O1231,IF($C$1="Yearly",Monthly!O1231*12,0)) -> 0 | M66: =IF($C$1="APM",Monthly!O1154,IF($C$1="Yearly",Monthly!O1154*12,0)) -> 0 | N66: =IF($C$1="APM",Monthly!O1077,IF($C$1="Yearly",Monthly!O1077*12,0)) -> 0 | O66: =IF($C$1="APM",Monthly!O1000,IF($C$1="Yearly",Monthly!O1000*12,0)) -> 0 | P66: =IF($C$1="APM",Monthly!$O924,IF($C$1="Yearly",Monthly!$O924*12,0)) -> 203 | Q66: =IF($C$1="APM",Monthly!$O847,IF($C$1="Yearly",Monthly!$O847*12,0)) -> 235 | R66: =IF($C$1="APM",Monthly!$O770,IF($C$1="Yearly",Monthly!$O770*12,0)) -> 203 | S66: =IF($C$1="APM",Monthly!$O693,IF($C$1="Yearly",Monthly!$O693*12,0)) -> 237 | T66: =IF($C$1="APM",Monthly!$O616,IF($C$1="Yearly",Monthly!$O616*12,0)) -> 237 | U66: =IF($C$1="APM",Monthly!$O616,IF($C$1="Yearly",Monthly!$O616*12,0)) -> 237 | Z66: =S66-P66 -> 34 | AA66: =T66-Q66 -> 2 | AB66: =IF($C$1="APM",Monthly!$O616,IF($C$1="Yearly",Monthly!$O616*12,0)) -> 237
A67: Gen Ex | C67: =SUM(C69:C71) -> 614 | D67: =SUM(D69:D71) -> 403.41667 | E67: =SUM(E69:E71) -> 884 | F67: =SUM(F69:F71) -> 406.25 | G67: =SUM(G69:G71) -> 21.333333 | H67: =SUM(H69:H71) -> 236 | I67: =SUM(I69:I71) -> 431 | J67: =SUM(J69:J71) -> 403.41667 | ... U67: =SUM(U69:U71) -> 200.08333 | Z67: =S67-P67 -> -27.25 | AA67: =(S67-P67)/P67 -> -0.2059194 | AB67: =SUM(AB69:AB71) -> 200.08333
B69: Loans | C69: =IF($C$1="APM",Monthly!O1931,IF($C$1="Yearly",Monthly!O1931*12,0)) -> 194 | D69: =IF($C$1="APM",Monthly!O1854,IF($C$1="Yearly",Monthly!O1854*12,0)) -> 66.666667 | E69: =IF($C$1="APM",Monthly!O1777,IF($C$1="Yearly",Monthly!O1777*12,0)) -> 551.5 | F69: =IF($C$1="APM",Monthly!O1699,IF($C$1="Yearly",Monthly!O1699*12,0)) -> 0 | G69: =IF($C$1="APM",Monthly!O1621,IF($C$1="Yearly",Monthly!O1621*12,0)) -> 1.5833333 | H69: =IF($C$1="APM",Monthly!O1543,IF($C$1="Yearly",Monthly!O1543*12,0)) -> 0 | I69: =IF($C$1="APM",Monthly!O1466,IF($C$1="Yearly",Monthly!O1466*12,0)) -> 0 | J69: =IF($C$1="APM",Monthly!O1389,IF($C$1="Yearly",Monthly!O1389*12,0)) -> 66.666667 | K69: =IF($C$1="APM",Monthly!O1312,IF($C$1="Yearly",Monthly!O1312*12,0)) -> 66.666667 | L69: =IF($C$1="APM",Monthly!O1234,IF($C$1="Yearly",Monthly!O1234*12,0)) -> 0 | M69: =IF($C$1="APM",Monthly!O1157,IF($C$1="Yearly",Monthly!O1157*12,0)) -> 0 | N69: =IF($C$1="APM",Monthly!O1080,IF($C$1="Yearly",Monthly!O1080*12,0)) -> 0 | O69: =IF($C$1="APM",Monthly!O1003,IF($C$1="Yearly",Monthly!O1003*12,0)) -> 0 | P69: =IF($C$1="APM",Monthly!$O927,IF($C$1="Yearly",Monthly!$O927*12,0)) -> 0 | Q69: =IF($C$1="APM",Monthly!$O850,IF($C$1="Yearly",Monthly!$O850*12,0)) -> 0 | R69: =IF($C$1="APM",Monthly!$O773,IF($C$1="Yearly",Monthly!$O773*12,0)) -> 0 | S69: =IF($C$1="APM",Monthly!$O696,IF($C$1="Yearly",Monthly!$O696*12,0)) -> 0 | T69: =IF($C$1="APM",Monthly!$O696,IF($C$1="Yearly",Monthly!$O696*12,0)) -> 0 | U69: =IF($C$1="APM",Monthly!$O696,IF($C$1="Yearly",Monthly!$O696*12,0)) -> 0 | Z69: =S69-P69 -> 0 | AA69: =T69-Q69 -> 0 | AB69: =IF($C$1="APM",Monthly!$O696,IF($C$1="Yearly",Monthly!$O696*12,0)) -> 0
B70: Fees | C70: =IF($C$1="APM",Monthly!O1932,IF($C$1="Yearly",Monthly!O1932*12,0)) -> 0 | D70: =IF($C$1="APM",Monthly!O1855,IF($C$1="Yearly",Monthly!O1855*12,0)) -> 4.3333333 | E70: =IF($C$1="APM",Monthly!O1778,IF($C$1="Yearly",Monthly!O1778*12,0)) -> 1.3333333 | F70: =IF($C$1="APM",Monthly!O1700,IF($C$1="Yearly",Monthly!O1700*12,0)) -> 4.1666667 | G70: =IF($C$1="APM",Monthly!O1622,IF($C$1="Yearly",Monthly!O1622*12,0)) -> 0 | H70: =IF($C$1="APM",Monthly!O1544,IF($C$1="Yearly",Monthly!O1544*12,0)) -> 18.5 | I70: =IF($C$1="APM",Monthly!O1467,IF($C$1="Yearly",Monthly!O1467*12,0)) -> 21.5 | J70: =IF($C$1="APM",Monthly!O1390,IF($C$1="Yearly",Monthly!O1390*12,0)) -> 4.3333333 | K70: =IF($C$1="APM",Monthly!O1313,IF($C$1="Yearly",Monthly!O1313*12,0)) -> 4.3333333 | L70: =IF($C$1="APM",Monthly!O1235,IF($C$1="Yearly",Monthly!O1235*12,0)) -> 27.166667 | M70: =IF($C$1="APM",Monthly!O1158,IF($C$1="Yearly",Monthly!O1158*12,0)) -> 11.25 | N70: =IF($C$1="APM",Monthly!O1081,IF($C$1="Yearly",Monthly!O1081*12,0)) -> 5.75 | O70: =IF($C$1="APM",Monthly!O1004,IF($C$1="Yearly",Monthly!O1004*12,0)) -> 76.166667 | P70: =IF($C$1="APM",Monthly!$O928,IF($C$1="Yearly",Monthly!$O928*12,0)) -> 79.166667 | Q70: =IF($C$1="APM",Monthly!$O851,IF($C$1="Yearly",Monthly!$O851*12,0)) -> 55 | R70: =IF($C$1="APM",Monthly!$O774,IF($C$1="Yearly",Monthly!$O774*12,0)) -> 64.833333 | S70: =IF($C$1="APM",Monthly!$O697,IF($C$1="Yearly",Monthly!$O697*12,0)) -> 31.25 | T70: =IF($C$1="APM",Monthly!$O620,IF($C$1="Yearly",Monthly!$O620*12,0)) -> 200.08333 | U70: =IF($C$1="APM",Monthly!$O620,IF($C$1="Yearly",Monthly!$O620*12,0)) -> 200.08333 | Z70: =S70-P70 -> -47.916667 | AA70: =T70-Q70 -> 145.08333 | AB70: =IF($C$1="APM",Monthly!$O620,IF($C$1="Yearly",Monthly!$O620*12,0)) -> 200.08333
B71: OTE | C71: =IF($C$1="APM",Monthly!O1933,IF($C$1="Yearly",Monthly!O1933*12,0)) -> 420 | D71: =IF($C$1="APM",Monthly!O1856,IF($C$1="Yearly",Monthly!O1856*12,0)) -> 332.41667 | E71: =IF($C$1="APM",Monthly!O1779,IF($C$1="Yearly",Monthly!O1779*12,0)) -> 331.16667 | F71: =IF($C$1="APM",Monthly!O1701,IF($C$1="Yearly",Monthly!O1701*12,0)) -> 402.08333 | G71: =IF($C$1="APM",Monthly!O1623,IF($C$1="Yearly",Monthly!O1623*12,0)) -> 19.75 | H71: =IF($C$1="APM",Monthly!O1545,IF($C$1="Yearly",Monthly!O1545*12,0)) -> 217.5 | I71: =IF($C$1="APM",Monthly!O1468,IF($C$1="Yearly",Monthly!O1468*12,0)) -> 409.5 | J71: =IF($C$1="APM",Monthly!O1391,IF($C$1="Yearly",Monthly!O1391*12,0)) -> 332.41667 | K71: =IF($C$1="APM",Monthly!O1314,IF($C$1="Yearly",Monthly!O1314*12,0)) -> 332.41667 | L71: =IF($C$1="APM",Monthly!O1236,IF($C$1="Yearly",Monthly!O1236*12,0)) -> 12.833333 | M71: =IF($C$1="APM",Monthly!O1159,IF($C$1="Yearly",Monthly!O1159*12,0)) -> 12.833333 | N71: =IF($C$1="APM",Monthly!O1082,IF($C$1="Yearly",Monthly!O1082*12,0)) -> 0 | O71: =IF($C$1="APM",Monthly!O1005,IF($C$1="Yearly",Monthly!O1005*12,0)) -> 542.08333 | P71: =IF($C$1="APM",Monthly!$O929,IF($C$1="Yearly",Monthly!$O929*12,0)) -> 53.166667 | Q71: =IF($C$1="APM",Monthly!$O852,IF($C$1="Yearly",Monthly!$O852*12,0)) -> 89.083333 | R71: =IF($C$1="APM",Monthly!$O775,IF($C$1="Yearly",Monthly!$O775*12,0)) -> 20.166667 | S71: =IF($C$1="APM",Monthly!$O698,IF($C$1="Yearly",Monthly!$O698*12,0)) -> 73.833333 | T71: =IF($C$1="APM",Monthly!$O621,IF($C$1="Yearly",Monthly!$O621*12,0)) -> 0 | U71: =IF($C$1="APM",Monthly!$O621,IF($C$1="Yearly",Monthly!$O621*12,0)) -> 0 | Z71: =S71-P71 -> 20.666667 | AA71: =T71-Q71 -> -89.083333 | AB71: =IF($C$1="APM",Monthly!$O621,IF($C$1="Yearly",Monthly!$O621*12,0)) -> 0
A72: India | C72: =SUM(C74:C75) -> 916.66667 | D72: =SUM(D74:D75) -> 671.5 | E72: =SUM(E74:E75) -> 230 | F72: =SUM(F74:F75) -> 1752.1667 | G72: =SUM(G74:G75) -> 1788.3333 | H72: =SUM(H74:H75) -> 1712.75 | I72: =SUM(I74:I75) -> 891.66667 | J72: =SUM(J74:J75) -> 413.41667 | ... U72: =SUM(U74:U75) -> 416.66667 | Z72: =S72-P72 -> 138.91667 | AA72: =(S72-P72)/P72 -> 0.18522222 | AB72: =SUM(AB74:AB75) -> 500
B74: R | C74: =IF($C$1="APM",Monthly!O1936,IF($C$1="Yearly",Monthly!O1936*12,0)) -> 500 | D74: =IF($C$1="APM",Monthly!O1859,IF($C$1="Yearly",Monthly!O1859*12,0)) -> 416.66667 | E74: =IF($C$1="APM",Monthly!O1782,IF($C$1="Yearly",Monthly!O1782*12,0)) -> 125 | F74: =IF($C$1="APM",Monthly!O1704,IF($C$1="Yearly",Monthly!O1704*12,0)) -> 1502.1667 | G74: =IF($C$1="APM",Monthly!O1626,IF($C$1="Yearly",Monthly!O1626*12,0)) -> 1788.3333 | H74: =IF($C$1="APM",Monthly!O1548,IF($C$1="Yearly",Monthly!O1548*12,0)) -> 1671.0833 | I74: =IF($C$1="APM",Monthly!O1471,IF($C$1="Yearly",Monthly!O1471*12,0)) -> 850 | J74: =IF($C$1="APM",Monthly!O1394,IF($C$1="Yearly",Monthly!O1394*12,0)) -> 308.41667 | K74: =IF($C$1="APM",Monthly!O1317,IF($C$1="Yearly",Monthly!O1317*12,0)) -> 416.66667 | L74: =IF($C$1="APM",Monthly!O1239,IF($C$1="Yearly",Monthly!O1239*12,0)) -> 739.58333 | M74: =IF($C$1="APM",Monthly!O1162,IF($C$1="Yearly",Monthly!O1162*12,0)) -> 820.41667 | N74: =IF($C$1="APM",Monthly!O1085,IF($C$1="Yearly",Monthly!O1085*12,0)) -> 958.33333 | O74: =IF($C$1="APM",Monthly!O1008,IF($C$1="Yearly",Monthly!O1008*12,0)) -> 639.16667 | P74: =IF($C$1="APM",Monthly!$O932,IF($C$1="Yearly",Monthly!$O932*12,0)) -> 750 | Q74: =IF($C$1="APM",Monthly!$O855,IF($C$1="Yearly",Monthly!$O855*12,0)) -> 583.33333 | R74: =IF($C$1="APM",Monthly!$O778,IF($C$1="Yearly",Monthly!$O778*12,0)) -> 708.33333 | S74: =IF($C$1="APM",Monthly!$O701,IF($C$1="Yearly",Monthly!$O701*12,0)) -> 888.91667 | T74: =IF($C$1="APM",Monthly!$O624,IF($C$1="Yearly",Monthly!$O624*12,0)) -> 416.66667 | U74: =IF($C$1="APM",Monthly!$O624,IF($C$1="Yearly",Monthly!$O624*12,0)) -> 416.66667 | Z74: =S74-P74 -> 138.91667 | AA74: =T74-Q74 -> -166.66667 | AB74: 500
B75: S | C75: =IF($C$1="APM",Monthly!O1937,IF($C$1="Yearly",Monthly!O1937*12,0)) -> 416.66667 | D75: =IF($C$1="APM",Monthly!O1860,IF($C$1="Yearly",Monthly!O1860*12,0)) -> 254.83333 | E75: =IF($C$1="APM",Monthly!O1783,IF($C$1="Yearly",Monthly!O1783*12,0)) -> 105 | F75: =IF($C$1="APM",Monthly!O1705,IF($C$1="Yearly",Monthly!O1705*12,0)) -> 250 | G75: =IF($C$1="APM",Monthly!O1627,IF($C$1="Yearly",Monthly!O1627*12,0)) -> 0 | H75: =IF($C$1="APM",Monthly!O1549,IF($C$1="Yearly",Monthly!O1549*12,0)) -> 41.666667 | I75: =IF($C$1="APM",Monthly!O1472,IF($C$1="Yearly",Monthly!O1472*12,0)) -> 41.666667 | J75: =IF($C$1="APM",Monthly!O1395,IF($C$1="Yearly",Monthly!O1395*12,0)) -> 105 | K75: =IF($C$1="APM",Monthly!O1318,IF($C$1="Yearly",Monthly!O1318*12,0)) -> 254.83333 | L75: =IF($C$1="APM",Monthly!O1240,IF($C$1="Yearly",Monthly!O1240*12,0)) -> 0 | M75: =IF($C$1="APM",Monthly!O1163,IF($C$1="Yearly",Monthly!O1163*12,0)) -> 0 | N75: =IF($C$1="APM",Monthly!O1086,IF($C$1="Yearly",Monthly!O1086*12,0)) -> 0 | O75: =IF($C$1="APM",Monthly!O1009,IF($C$1="Yearly",Monthly!O1009*12,0)) -> 0 | P75: =IF($C$1="APM",Monthly!$O933,IF($C$1="Yearly",Monthly!$O933*12,0)) -> 0 | Q75: =IF($C$1="APM",Monthly!$O856,IF($C$1="Yearly",Monthly!$O856*12,0)) -> 0 | R75: =IF($C$1="APM",Monthly!$O779,IF($C$1="Yearly",Monthly!$O779*12,0)) -> 0 | S75: =IF($C$1="APM",Monthly!$O702,IF($C$1="Yearly",Monthly!$O702*12,0)) -> 0 | T75: =IF($C$1="APM",Monthly!$O625,IF($C$1="Yearly",Monthly!$O625*12,0)) -> 0 | U75: =IF($C$1="APM",Monthly!$O625,IF($C$1="Yearly",Monthly!$O625*12,0)) -> 0 | Z75: =S75-P75 -> 0 | AA75: =T75-Q75 -> 0 | AB75: =IF($C$1="APM",Monthly!$O625,IF($C$1="Yearly",Monthly!$O625*12,0)) -> 0
A76: Total EXP. | C76: =C6+C20+C28+C34+C38+C48+C57+C61+ C68+ C67+C72 -> 6509 | D76: =D6+D20+D28+D34+D38+D48+D57+D61+ D68+ D67+D72 -> 6155.0208 | E76: =E6+E20+E28+E34+E38+E48+E57+E61+ E68+ E67+E72 -> 6597.5 | F76: =F6+F20+F28+F34+F38+F48+F57+F61+ F68+ F67+F72 -> 6847.75 | G76: =G6+G20+G28+G34+G38+G48+G57+G61+ G68+ G67+G72 -> 6795.6667 | H76: =H6+H20+H28+H34+H38+H48+H57+H61+ H68+ H67+H72 -> 7497.5833 | I76: =I6+I20+I28+I34+I38+I48+I57+I61+ I68+ I67+I72 -> 6875.5472 | J76: =J6+J20+J28+J34+J38+J48+J57+J61+ J68+ J67+J72 -> 6919.1406 | ... U76: =U6+U20+U28+U34+U38+U48+U57+U61+ U68+ U67+U72 -> 12486.292 | Z76: =S76-P76 -> 3556.0278 | AA76: =(S76-P76)/P76 -> 0.3964688 | AB76: =AB6+AB20+AB28+AB34+AB38+AB48+AB57+AB61+ AB68+ AB67+AB72 -> 22652.417
B77: Taxes | D77: =FinSnapshot!C85/FinSnapshot!C64 -> 0.30604665 | E77: =FinSnapshot!D85/FinSnapshot!D64 -> 0.2891699 | F77: =FinSnapshot!E85/FinSnapshot!E64 -> 0.34158235 | G77: =FinSnapshot!F85/FinSnapshot!F64 -> 0.29203606 | H77: =FinSnapshot!G85/FinSnapshot!G64 -> 0.2719882 | I77: =FinSnapshot!H85/FinSnapshot!H64 -> 0.28007505 | J77: =FinSnapshot!I85/FinSnapshot!I64 -> 0.29657563 | K77: =FinSnapshot!J85/FinSnapshot!J64 -> 0.27638324 | ... U77: =FinSnapshot!T85/FinSnapshot!T64 -> 0.35006651 | AB77: =FinSnapshot!X85/FinSnapshot!X64 -> 0
A78: Percent Change | D78: =(D76-C76)/C76 -> -0.054383034 | E78: =(E76-D76)/D76 -> 0.071889142 | F78: =(F76-E76)/E76 -> 0.037931034 | G78: =(G76-F76)/F76 -> -0.0076059046 | H78: =(H76-G76)/G76 -> 0.10328886 | I78: =(I76-H76)/H76 -> -0.082964886 | J78: =(J76-I76)/I76 -> 0.0063403496 | K78: =(K76-J76)/J76 -> 0.43525049 | ... U78: =(U76-T76)/T76 -> 0 | AB78: =(AB76-AA76)/AA76 -> 57134.433
B79: IPM | C79: =M!B18 -> 7157.6533 | D79: =M!C18 -> 7849.6667 | E79: =M!D18 -> 8553.75 | F79: =M!E18 -> 8587.1667 | G79: =M!F18 -> 10583.583 | H79: =M!G18 -> 11583.333 | I79: =M!H18 -> 11994.618 | J79: =M!I18 -> 12089.167 | ... T79: =M!S18 -> 29229.333 | U79: =M!X18 -> 13449.524 | Z79: =S79-P79 -> 8605.3333 | AA79: =(S79-P79)/P79 -> 0.43898229 | AB79: 24021
B80: Income after Exp | C80: =C79-C76 -> 648.65333 | D80: =D79-D76 -> 1694.6458 | E80: =E79-E76 -> 1956.25 | F80: =F79-F76 -> 1739.4167 | G80: =G79-G76 -> 3787.9167 | H80: =H79-H76 -> 4085.75 | I80: =I79-I76 -> 5119.0711 | J80: =J79-J76 -> 5170.0261 | ... U80: =U79-U76 -> 963.23205 | Z80: =S80-P80 -> 5049.3056 | AA80: =(S80-P80)/P80 -> 0.47484144 | AB80: =AB79-AB76 -> 1368.5833
B81: =12*(YEAR(TODAY())-2002+1)+MONTH(TODAY()) -> 303
T82: =T76-T6+T19 -> 7744.2917 | AB82: =AB76-AB6 -> 9460.4167 | AC82: Non Housing Expenses
T83: =T6 -> 4746.1667 | AB83: =AB6 -> 13192 | AC83: Housing Expenses
T84: =T82+T83 -> 12490.458 | AB84: =AB82+AB83 -> 22652.417 | AC84: Total
AB85: =AB84-T84 -> 10161.958 | AC85: Extra
S86: Income | T86: =9100*2 -> 18200 | AB86: =9100*2 -> 18200
S87: Delta | T87: =T86-T84 -> 5709.5417 | AB87: =AB86-AB84 -> -4452.4167
B93: India R Expense | C93: =C74*12 -> 6000 | D93: =D74*12 -> 5000 | E93: =E74*12 -> 1500 | F93: =F74*12 -> 18026 | G93: =G74*12 -> 21460 | H93: =H74*12 -> 20053 | I93: =I74*12 -> 10200 | J93: =J74*12 -> 3701 | ... Z93: =Z74*12 -> 1667
G96: =173000 -> 173000

Sheet M-Comparison
C1: Nov | D1: Monthly Comparison
C3: 2003 | D3: 2004 | E3: 2005 | F3: 2006 | G3: 2007 | H3: 2008 | I3: 2009 | J3: 2010 | K3: 2011 | L3: 2012 | M3: 2013 | N3: 2014 | O3: 2015 | P3: 2016 | Q3: 2017 | R3: 2018 | S3: 2019 | T3: 2020 | U3: 2021 | V3: 2022 | W3: 2023 | X3: APM | Y3: % Total | AA3: Max | AB3: Min
A4: Home | C4: =C6+ SUM(C12:C17) -> 1075 | D4: =SUM(D7:D17) -> 2370 | E4: =SUM(E7:E17) -> 2662 | F4: =SUM(F7:F17) -> 2782 | G4: =SUM(G7:G17) -> 2519 | H4: =SUM(H7:H17) -> 2456.8677 | I4: =SUM(I7:I17) -> 2564.8189 | J4: =SUM(J7:J17) -> 2439.4499 | K4: =K6+ SUM(K12:K17) -> 2397.4499 | L4: =L6+ SUM(L12:L17) -> 2604.4499 | M4: =M6+ SUM(M12:M17) -> 1649 | N4: =N6+ SUM(N12:N17) -> 1649 | O4: =O6+ SUM(O12:O17) -> 1675 | P4: =P6+ SUM(P12:P17) -> 4387 | Q4: =Q6+ SUM(Q12:Q17) -> 4387 | R4: =R6+ SUM(R12:R17) -> 0 | ... X4: =X6+ SUM(X12:X17) -> 2507.8691 | Y4: =X4/7000 -> 0.35826701 | AA4: =AA6+ SUM(AA12:AA17) -> 5341 | AB4: =AB6+ SUM(AB12:AB17) -> 1057
B6: Mortagage | C6: =IF(ISNUMBER(FIND("Jan",$C$1)),Monthly!$C1793,(IF(ISNUMBER(FIND("Feb",$C$1)),Monthly!$D1793,((IF(ISNUMBER(FIND("Mar",$C$1)),Monthly!$E1793,(IF(ISNUMBER(FIND("Apr",$C$1)),Monthly!$F1793,((IF(ISNUMBER(FIND("May",$C$1)),Monthly!$G1793,((IF(ISNUMBER(FIND("Jun",$C$1)),Monthly!$H1793,(IF(ISNUMBER(FIND("Jul",$C$1)),Monthly!$I1793,(IF(ISNUMBER(FIND("Aug",$C$1)),Monthly!$J1793,(IF(ISNUMBER(FIND("Sep",$C$1)),Monthly!$K1793,(IF(ISNUMBER(FIND("Oct",$C$1)),Monthly!$L1793,(IF(ISNUMBER(FIND("Nov",$C$1)),Monthly!$M1793,(IF(ISNUMBER(FIND("Dec",$C$1)),Monthly!$N1793,)))))))))))))))))))))))))) -> 1075 | D6: =SUM(D7:D11) -> 1804 | E6: =SUM(E7:E11) -> 2003 | F6: =SUM(F7:F11) -> 2172 | G6: =SUM(G7:G11) -> 1894 | H6: =SUM(H7:H11) -> 1753.8677 | I6: =SUM(I7:I11) -> 1895.8189 | J6: =SUM(J7:J11) -> 1755.4499 | K6: =SUM(K7:K11) -> 1755.4499 | ... O6: =SUM(O7:O11) -> 1057 | P6: =IF(ISNUMBER(FIND("Jan",$C$1)),Monthly!$C712,(IF(ISNUMBER(FIND("Feb",$C$1)),Monthly!$D712,((IF(ISNUMBER(FIND("Mar",$C$1)),Monthly!$E712,(IF(ISNUMBER(FIND("Apr",$C$1)),Monthly!$F712,((IF(ISNUMBER(FIND("May",$C$1)),Monthly!$G712,((IF(ISNUMBER(FIND("Jun",$C$1)),Monthly!$H712,(IF(ISNUMBER(FIND("Jul",$C$1)),Monthly!$I712,(IF(ISNUMBER(FIND("Aug",$C$1)),Monthly!$J712,(IF(ISNUMBER(FIND("Sep",$C$1)),Monthly!$K712,(IF(ISNUMBER(FIND("Oct",$C$1)),Monthly!$L712,(IF(ISNUMBER(FIND("Nov",$C$1)),Monthly!$M712,(IF(ISNUMBER(FIND("Dec",$C$1)),Monthly!$N712,)))))))))))))))))))))))))) -> 4384 | Q6: =IF(ISNUMBER(FIND("Jan",$C$1)),Monthly!$C712,(IF(ISNUMBER(FIND("Feb",$C$1)),Monthly!$D712,((IF(ISNUMBER(FIND("Mar",$C$1)),Monthly!$E712,(IF(ISNUMBER(FIND("Apr",$C$1)),Monthly!$F712,((IF(ISNUMBER(FIND("May",$C$1)),Monthly!$G712,((IF(ISNUMBER(FIND("Jun",$C$1)),Monthly!$H712,(IF(ISNUMBER(FIND("Jul",$C$1)),Monthly!$I712,(IF(ISNUMBER(FIND("Aug",$C$1)),Monthly!$J712,(IF(ISNUMBER(FIND("Sep",$C$1)),Monthly!$K712,(IF(ISNUMBER(FIND("Oct",$C$1)),Monthly!$L712,(IF(ISNUMBER(FIND("Nov",$C$1)),Monthly!$M712,(IF(ISNUMBER(FIND("Dec",$C$1)),Monthly!$N712,)))))))))))))))))))))))))) -> 4384 | U6: =Monthly!O405 -> 9419.6271 | V6: =Monthly!O320 -> 9422.8271 | X6: =SUM(C6:Q6)/$E$77 -> 1986.8691 | Y6: =X6/7000 -> 0.28383844 | AA6: =MAX(C6:Q6) -> 4384 | AB6: =MIN(C6:Q6) -> 1057
B7: Mortgage I | C7: =IF(ISNUMBER(FIND("Jan",$C$1)),Monthly!$C1794,(IF(ISNUMBER(FIND("Feb",$C$1)),Monthly!$D1794,((IF(ISNUMBER(FIND("Mar",$C$1)),Monthly!$E1794,(IF(ISNUMBER(FIND("Apr",$C$1)),Monthly!$F1794,((IF(ISNUMBER(FIND("May",$C$1)),Monthly!$G1794,((IF(ISNUMBER(FIND("Jun",$C$1)),Monthly!$H1794,(IF(ISNUMBER(FIND("Jul",$C$1)),Monthly!$I1794,(IF(ISNUMBER(FIND("Aug",$C$1)),Monthly!$J1794,(IF(ISNUMBER(FIND("Sep",$C$1)),Monthly!$K1794,(IF(ISNUMBER(FIND("Oct",$C$1)),Monthly!$L1794,(IF(ISNUMBER(FIND("Nov",$C$1)),Monthly!$M1794,(IF(ISNUMBER(FIND("Dec",$C$1)),Monthly!$N1794,)))))))))))))))))))))))))) -> 0 | D7: =IF(ISNUMBER(FIND("Jan",$C$1)),Monthly!$C1717,(IF(ISNUMBER(FIND("Feb",$C$1)),Monthly!$D1717,((IF(ISNUMBER(FIND("Mar",$C$1)),Monthly!$E1717,(IF(ISNUMBER(FIND("Apr",$C$1)),Monthly!$F1717,((IF(ISNUMBER(FIND("May",$C$1)),Monthly!$G1717,((IF(ISNUMBER(FIND("Jun",$C$1)),Monthly!$H1717,(IF(ISNUMBER(FIND("Jul",$C$1)),Monthly!$I1717,(IF(ISNUMBER(FIND("Aug",$C$1)),Monthly!$J1717,(IF(ISNUMBER(FIND("Sep",$C$1)),Monthly!$K1717,(IF(ISNUMBER(FIND("Oct",$C$1)),Monthly!$L1717,(IF(ISNUMBER(FIND("Nov",$C$1)),Monthly!$M1717,(IF(ISNUMBER(FIND("Dec",$C$1)),Monthly!$N1717,)))))))))))))))))))))))))) -> 867 | E7: =IF(ISNUMBER(FIND("Jan",$C$1)),Monthly!$C1639,(IF(ISNUMBER(FIND("Feb",$C$1)),Monthly!$D1639,((IF(ISNUMBER(FIND("Mar",$C$1)),Monthly!$E1639,(IF(ISNUMBER(FIND("Apr",$C$1)),Monthly!$F1639,((IF(ISNUMBER(FIND("May",$C$1)),Monthly!$G1639,((IF(ISNUMBER(FIND("Jun",$C$1)),Monthly!$H1639,(IF(ISNUMBER(FIND("Jul",$C$1)),Monthly!$I1639,(IF(ISNUMBER(FIND("Aug",$C$1)),Monthly!$J1639,(IF(ISNUMBER(FIND("Sep",$C$1)),Monthly!$K1639,(IF(ISNUMBER(FIND("Oct",$C$1)),Monthly!$L1639,(IF(ISNUMBER(FIND("Nov",$C$1)),Monthly!$M1639,(IF(ISNUMBER(FIND("Dec",$C$1)),Monthly!$N1639,)))))))))))))))))))))))))) -> 850 | F7: =IF(ISNUMBER(FIND("Jan",$C$1)),Monthly!$C1561,(IF(ISNUMBER(FIND("Feb",$C$1)),Monthly!$D1561,((IF(ISNUMBER(FIND("Mar",$C$1)),Monthly!$E1561,(IF(ISNUMBER(FIND("Apr",$C$1)),Monthly!$F1561,((IF(ISNUMBER(FIND("May",$C$1)),Monthly!$G1561,((IF(ISNUMBER(FIND("Jun",$C$1)),Monthly!$H1561,(IF(ISNUMBER(FIND("Jul",$C$1)),Monthly!$I1561,(IF(ISNUMBER(FIND("Aug",$C$1)),Monthly!$J1561,(IF(ISNUMBER(FIND("Sep",$C$1)),Monthly!$K1561,(IF(ISNUMBER(FIND("Oct",$C$1)),Monthly!$L1561,(IF(ISNUMBER(FIND("Nov",$C$1)),Monthly!$M1561,(IF(ISNUMBER(FIND("Dec",$C$1)),Monthly!$N1561,)))))))))))))))))))))))))) -> 830 | G7: =IF(ISNUMBER(FIND("Jan",$C$1)),Monthly!$C1483,(IF(ISNUMBER(FIND("Feb",$C$1)),Monthly!$D1483,((IF(ISNUMBER(FIND("Mar",$C$1)),Monthly!$E1483,(IF(ISNUMBER(FIND("Apr",$C$1)),Monthly!$F1483,((IF(ISNUMBER(FIND("May",$C$1)),Monthly!$G1483,((IF(ISNUMBER(FIND("Jun",$C$1)),Monthly!$H1483,(IF(ISNUMBER(FIND("Jul",$C$1)),Monthly!$I1483,(IF(ISNUMBER(FIND("Aug",$C$1)),Monthly!$J1483,(IF(ISNUMBER(FIND("Sep",$C$1)),Monthly!$K1483,(IF(ISNUMBER(FIND("Oct",$C$1)),Monthly!$L1483,(IF(ISNUMBER(FIND("Nov",$C$1)),Monthly!$M1483,(IF(ISNUMBER(FIND("Dec",$C$1)),Monthly!$N1483,)))))))))))))))))))))))))) -> 816 | H7: =IF(ISNUMBER(FIND("Jan",$C$1)),Monthly!$C1406,(IF(ISNUMBER(FIND("Feb",$C$1)),Monthly!$D1406,((IF(ISNUMBER(FIND("Mar",$C$1)),Monthly!$E1406,(IF(ISNUMBER(FIND("Apr",$C$1)),Monthly!$F1406,((IF(ISNUMBER(FIND("May",$C$1)),Monthly!$G1406,((IF(ISNUMBER(FIND("Jun",$C$1)),Monthly!$H1406,(IF(ISNUMBER(FIND("Jul",$C$1)),Monthly!$I1406,(IF(ISNUMBER(FIND("Aug",$C$1)),Monthly!$J1406,(IF(ISNUMBER(FIND("Sep",$C$1)),Monthly!$K1406,(IF(ISNUMBER(FIND("Oct",$C$1)),Monthly!$L1406,(IF(ISNUMBER(FIND("Nov",$C$1)),Monthly!$M1406,(IF(ISNUMBER(FIND("Dec",$C$1)),Monthly!$N1406,)))))))))))))))))))))))))) -> 1006.1209 | I7: =IF(ISNUMBER(FIND("Jan",$C$1)),Monthly!$C1329,(IF(ISNUMBER(FIND("Feb",$C$1)),Monthly!$D1329,((IF(ISNUMBER(FIND("Mar",$C$1)),Monthly!$E1329,(IF(ISNUMBER(FIND("Apr",$C$1)),Monthly!$F1329,((IF(ISNUMBER(FIND("May",$C$1)),Monthly!$G1329,((IF(ISNUMBER(FIND("Jun",$C$1)),Monthly!$H1329,(IF(ISNUMBER(FIND("Jul",$C$1)),Monthly!$I1329,(IF(ISNUMBER(FIND("Aug",$C$1)),Monthly!$J1329,(IF(ISNUMBER(FIND("Sep",$C$1)),Monthly!$K1329,(IF(ISNUMBER(FIND("Oct",$C$1)),Monthly!$L1329,(IF(ISNUMBER(FIND("Nov",$C$1)),Monthly!$M1329,(IF(ISNUMBER(FIND("Dec",$C$1)),Monthly!$N1329,)))))))))))))))))))))))))) -> 895.56019 | J7: =IF(ISNUMBER(FIND("Jan",$C$1)),Monthly!$C1252,(IF(ISNUMBER(FIND("Feb",$C$1)),Monthly!$D1252,((IF(ISNUMBER(FIND("Mar",$C$1)),Monthly!$E1252,(IF(ISNUMBER(FIND("Apr",$C$1)),Monthly!$F1252,((IF(ISNUMBER(FIND("May",$C$1)),Monthly!$G1252,((IF(ISNUMBER(FIND("Jun",$C$1)),Monthly!$H1252,(IF(ISNUMBER(FIND("Jul",$C$1)),Monthly!$I1252,(IF(ISNUMBER(FIND("Aug",$C$1)),Monthly!$J1252,(IF(ISNUMBER(FIND("Sep",$C$1)),Monthly!$K1252,(IF(ISNUMBER(FIND("Oct",$C$1)),Monthly!$L1252,(IF(ISNUMBER(FIND("Nov",$C$1)),Monthly!$M1252,(IF(ISNUMBER(FIND("Dec",$C$1)),Monthly!$N1252,)))))))))))))))))))))))))) -> 976.68876 | K7: =IF(ISNUMBER(FIND("Jan",$C$1)),Monthly!$C1174,(IF(ISNUMBER(FIND("Feb",$C$1)),Monthly!$D1174,((IF(ISNUMBER(FIND("Mar",$C$1)),Monthly!$E1174,(IF(ISNUMBER(FIND("Apr",$C$1)),Monthly!$F1174,((IF(ISNUMBER(FIND("May",$C$1)),Monthly!$G1174,((IF(ISNUMBER(FIND("Jun",$C$1)),Monthly!$H1174,(IF(ISNUMBER(FIND("Jul",$C$1)),Monthly!$I1174,(IF(ISNUMBER(FIND("Aug",$C$1)),Monthly!$J1174,(IF(ISNUMBER(FIND("Sep",$C$1)),Monthly!$K1174,(IF(ISNUMBER(FIND("Oct",$C$1)),Monthly!$L1174,(IF(ISNUMBER(FIND("Nov",$C$1)),Monthly!$M1174,(IF(ISNUMBER(FIND("Dec",$C$1)),Monthly!$N1174,)))))))))))))))))))))))))) -> 961.32061 | L7: =IF(ISNUMBER(FIND("Jan",$C$1)),Monthly!$C1097,(IF(ISNUMBER(FIND("Feb",$C$1)),Monthly!$D1097,((IF(ISNUMBER(FIND("Mar",$C$1)),Monthly!$E1097,(IF(ISNUMBER(FIND("Apr",$C$1)),Monthly!$F1097,((IF(ISNUMBER(FIND("May",$C$1)),Monthly!$G1097,((IF(ISNUMBER(FIND("Jun",$C$1)),Monthly!$H1097,(IF(ISNUMBER(FIND("Jul",$C$1)),Monthly!$I1097,(IF(ISNUMBER(FIND("Aug",$C$1)),Monthly!$J1097,(IF(ISNUMBER(FIND("Sep",$C$1)),Monthly!$K1097,(IF(ISNUMBER(FIND("Oct",$C$1)),Monthly!$L1097,(IF(ISNUMBER(FIND("Nov",$C$1)),Monthly!$M1097,(IF(ISNUMBER(FIND("Dec",$C$1)),Monthly!$N1097,)))))))))))))))))))))))))) -> 945.08557 | M7: =IF(ISNUMBER(FIND("Jan",$C$1)),Monthly!$C1020,(IF(ISNUMBER(FIND("Feb",$C$1)),Monthly!$D1020,((IF(ISNUMBER(FIND("Mar",$C$1)),Monthly!$E1020,(IF(ISNUMBER(FIND("Apr",$C$1)),Monthly!$F1020,((IF(ISNUMBER(FIND("May",$C$1)),Monthly!$G1020,((IF(ISNUMBER(FIND("Jun",$C$1)),Monthly!$H1020,(IF(ISNUMBER(FIND("Jul",$C$1)),Monthly!$I1020,(IF(ISNUMBER(FIND("Aug",$C$1)),Monthly!$J1020,(IF(ISNUMBER(FIND("Sep",$C$1)),Monthly!$K1020,(IF(ISNUMBER(FIND("Oct",$C$1)),Monthly!$L1020,(IF(ISNUMBER(FIND("Nov",$C$1)),Monthly!$M1020,(IF(ISNUMBER(FIND("Dec",$C$1)),Monthly!$N1020,)))))))))))))))))))))))))) -> 657 | N7: =IF(ISNUMBER(FIND("Jan",$C$1)),Monthly!$C943,(IF(ISNUMBER(FIND("Feb",$C$1)),Monthly!$D943,((IF(ISNUMBER(FIND("Mar",$C$1)),Monthly!$E943,(IF(ISNUMBER(FIND("Apr",$C$1)),Monthly!$F943,((IF(ISNUMBER(FIND("May",$C$1)),Monthly!$G943,((IF(ISNUMBER(FIND("Jun",$C$1)),Monthly!$H943,(IF(ISNUMBER(FIND("Jul",$C$1)),Monthly!$I943,(IF(ISNUMBER(FIND("Aug",$C$1)),Monthly!$J943,(IF(ISNUMBER(FIND("Sep",$C$1)),Monthly!$K943,(IF(ISNUMBER(FIND("Oct",$C$1)),Monthly!$L943,(IF(ISNUMBER(FIND("Nov",$C$1)),Monthly!$M943,(IF(ISNUMBER(FIND("Dec",$C$1)),Monthly!$N943,)))))))))))))))))))))))))) -> 657 | O7: =IF(ISNUMBER(FIND("Jan",$C$1)),Monthly!$C867,(IF(ISNUMBER(FIND("Feb",$C$1)),Monthly!$D867,((IF(ISNUMBER(FIND("Mar",$C$1)),Monthly!$E867,(IF(ISNUMBER(FIND("Apr",$C$1)),Monthly!$F867,((IF(ISNUMBER(FIND("May",$C$1)),Monthly!$G867,((IF(ISNUMBER(FIND("Jun",$C$1)),Monthly!$H867,(IF(ISNUMBER(FIND("Jul",$C$1)),Monthly!$I867,(IF(ISNUMBER(FIND("Aug",$C$1)),Monthly!$J867,(IF(ISNUMBER(FIND("Sep",$C$1)),Monthly!$K867,(IF(ISNUMBER(FIND("Oct",$C$1)),Monthly!$L867,(IF(ISNUMBER(FIND("Nov",$C$1)),Monthly!$M867,(IF(ISNUMBER(FIND("Dec",$C$1)),Monthly!$N867,)))))))))))))))))))))))))) -> 657 | P7: =IF(ISNUMBER(FIND("Jan",$C$1)),Monthly!$C790,(IF(ISNUMBER(FIND("Feb",$C$1)),Monthly!$D790,((IF(ISNUMBER(FIND("Mar",$C$1)),Monthly!$E790,(IF(ISNUMBER(FIND("Apr",$C$1)),Monthly!$F790,((IF(ISNUMBER(FIND("May",$C$1)),Monthly!$G790,((IF(ISNUMBER(FIND("Jun",$C$1)),Monthly!$H790,(IF(ISNUMBER(FIND("Jul",$C$1)),Monthly!$I790,(IF(ISNUMBER(FIND("Aug",$C$1)),Monthly!$J790,(IF(ISNUMBER(FIND("Sep",$C$1)),Monthly!$K790,(IF(ISNUMBER(FIND("Oct",$C$1)),Monthly!$L790,(IF(ISNUMBER(FIND("Nov",$C$1)),Monthly!$M790,(IF(ISNUMBER(FIND("Dec",$C$1)),Monthly!$N790,)))))))))))))))))))))))))) -> 0 | Q7: =IF(ISNUMBER(FIND("Jan",$C$1)),Monthly!$C713,(IF(ISNUMBER(FIND("Feb",$C$1)),Monthly!$D713,((IF(ISNUMBER(FIND("Mar",$C$1)),Monthly!$E713,(IF(ISNUMBER(FIND("Apr",$C$1)),Monthly!$F713,((IF(ISNUMBER(FIND("May",$C$1)),Monthly!$G713,((IF(ISNUMBER(FIND("Jun",$C$1)),Monthly!$H713,(IF(ISNUMBER(FIND("Jul",$C$1)),Monthly!$I713,(IF(ISNUMBER(FIND("Aug",$C$1)),Monthly!$J713,(IF(ISNUMBER(FIND("Sep",$C$1)),Monthly!$K713,(IF(ISNUMBER(FIND("Oct",$C$1)),Monthly!$L713,(IF(ISNUMBER(FIND("Nov",$C$1)),Monthly!$M713,(IF(ISNUMBER(FIND("Dec",$C$1)),Monthly!$N713,)))))))))))))))))))))))))) -> 0 | U7: =Monthly!O406 -> 4837.6873 | V7: =Monthly!O321 -> 4733.9793 | X7: =SUM(C7:Q7)/$E$77 -> 674.58507 | Y7: =X7/7000 -> 0.096369296 | AA7: =MAX(C7:Q7) -> 1006.1209 | AB7: =MIN(C7:Q7) -> 0
B8: P | C8: =IF(ISNUMBER(FIND("Jan",$C$1)),Monthly!$C1795,(IF(ISNUMBER(FIND("Feb",$C$1)),Monthly!$D1795,((IF(ISNUMBER(FIND("Mar",$C$1)),Monthly!$E1795,(IF(ISNUMBER(FIND("Apr",$C$1)),Monthly!$F1795,((IF(ISNUMBER(FIND("May",$C$1)),Monthly!$G1795,((IF(ISNUMBER(FIND("Jun",$C$1)),Monthly!$H1795,(IF(ISNUMBER(FIND("Jul",$C$1)),Monthly!$I1795,(IF(ISNUMBER(FIND("Aug",$C$1)),Monthly!$J1795,(IF(ISNUMBER(FIND("Sep",$C$1)),Monthly!$K1795,(IF(ISNUMBER(FIND("Oct",$C$1)),Monthly!$L1795,(IF(ISNUMBER(FIND("Nov",$C$1)),Monthly!$M1795,(IF(ISNUMBER(FIND("Dec",$C$1)),Monthly!$N1795,)))))))))))))))))))))))))) -> 0 | D8: =IF(ISNUMBER(FIND("Jan",$C$1)),Monthly!$C1718,(IF(ISNUMBER(FIND("Feb",$C$1)),Monthly!$D1718,((IF(ISNUMBER(FIND("Mar",$C$1)),Monthly!$E1718,(IF(ISNUMBER(FIND("Apr",$C$1)),Monthly!$F1718,((IF(ISNUMBER(FIND("May",$C$1)),Monthly!$G1718,((IF(ISNUMBER(FIND("Jun",$C$1)),Monthly!$H1718,(IF(ISNUMBER(FIND("Jul",$C$1)),Monthly!$I1718,(IF(ISNUMBER(FIND("Aug",$C$1)),Monthly!$J1718,(IF(ISNUMBER(FIND("Sep",$C$1)),Monthly!$K1718,(IF(ISNUMBER(FIND("Oct",$C$1)),Monthly!$L1718,(IF(ISNUMBER(FIND("Nov",$C$1)),Monthly!$M1718,(IF(ISNUMBER(FIND("Dec",$C$1)),Monthly!$N1718,)))))))))))))))))))))))))) -> 427 | E8: =IF(ISNUMBER(FIND("Jan",$C$1)),Monthly!$C1640,(IF(ISNUMBER(FIND("Feb",$C$1)),Monthly!$D1640,((IF(ISNUMBER(FIND("Mar",$C$1)),Monthly!$E1640,(IF(ISNUMBER(FIND("Apr",$C$1)),Monthly!$F1640,((IF(ISNUMBER(FIND("May",$C$1)),Monthly!$G1640,((IF(ISNUMBER(FIND("Jun",$C$1)),Monthly!$H1640,(IF(ISNUMBER(FIND("Jul",$C$1)),Monthly!$I1640,(IF(ISNUMBER(FIND("Aug",$C$1)),Monthly!$J1640,(IF(ISNUMBER(FIND("Sep",$C$1)),Monthly!$K1640,(IF(ISNUMBER(FIND("Oct",$C$1)),Monthly!$L1640,(IF(ISNUMBER(FIND("Nov",$C$1)),Monthly!$M1640,(IF(ISNUMBER(FIND("Dec",$C$1)),Monthly!$N1640,)))))))))))))))))))))))))) -> 444 | F8: =IF(ISNUMBER(FIND("Jan",$C$1)),Monthly!$C1562,(IF(ISNUMBER(FIND("Feb",$C$1)),Monthly!$D1562,((IF(ISNUMBER(FIND("Mar",$C$1)),Monthly!$E1562,(IF(ISNUMBER(FIND("Apr",$C$1)),Monthly!$F1562,((IF(ISNUMBER(FIND("May",$C$1)),Monthly!$G1562,((IF(ISNUMBER(FIND("Jun",$C$1)),Monthly!$H1562,(IF(ISNUMBER(FIND("Jul",$C$1)),Monthly!$I1562,(IF(ISNUMBER(FIND("Aug",$C$1)),Monthly!$J1562,(IF(ISNUMBER(FIND("Sep",$C$1)),Monthly!$K1562,(IF(ISNUMBER(FIND("Oct",$C$1)),Monthly!$L1562,(IF(ISNUMBER(FIND("Nov",$C$1)),Monthly!$M1562,(IF(ISNUMBER(FIND("Dec",$C$1)),Monthly!$N1562,)))))))))))))))))))))))))) -> 630 | G8: =IF(ISNUMBER(FIND("Jan",$C$1)),Monthly!$C1484,(IF(ISNUMBER(FIND("Feb",$C$1)),Monthly!$D1484,((IF(ISNUMBER(FIND("Mar",$C$1)),Monthly!$E1484,(IF(ISNUMBER(FIND("Apr",$C$1)),Monthly!$F1484,((IF(ISNUMBER(FIND("May",$C$1)),Monthly!$G1484,((IF(ISNUMBER(FIND("Jun",$C$1)),Monthly!$H1484,(IF(ISNUMBER(FIND("Jul",$C$1)),Monthly!$I1484,(IF(ISNUMBER(FIND("Aug",$C$1)),Monthly!$J1484,(IF(ISNUMBER(FIND("Sep",$C$1)),Monthly!$K1484,(IF(ISNUMBER(FIND("Oct",$C$1)),Monthly!$L1484,(IF(ISNUMBER(FIND("Nov",$C$1)),Monthly!$M1484,(IF(ISNUMBER(FIND("Dec",$C$1)),Monthly!$N1484,)))))))))))))))))))))))))) -> 368 | H8: =IF(ISNUMBER(FIND("Jan",$C$1)),Monthly!$C1407,(IF(ISNUMBER(FIND("Feb",$C$1)),Monthly!$D1407,((IF(ISNUMBER(FIND("Mar",$C$1)),Monthly!$E1407,(IF(ISNUMBER(FIND("Apr",$C$1)),Monthly!$F1407,((IF(ISNUMBER(FIND("May",$C$1)),Monthly!$G1407,((IF(ISNUMBER(FIND("Jun",$C$1)),Monthly!$H1407,(IF(ISNUMBER(FIND("Jul",$C$1)),Monthly!$I1407,(IF(ISNUMBER(FIND("Aug",$C$1)),Monthly!$J1407,(IF(ISNUMBER(FIND("Sep",$C$1)),Monthly!$K1407,(IF(ISNUMBER(FIND("Oct",$C$1)),Monthly!$L1407,(IF(ISNUMBER(FIND("Nov",$C$1)),Monthly!$M1407,(IF(ISNUMBER(FIND("Dec",$C$1)),Monthly!$N1407,)))))))))))))))))))))))))) -> 243.01488 | I8: =IF(ISNUMBER(FIND("Jan",$C$1)),Monthly!$C1330,(IF(ISNUMBER(FIND("Feb",$C$1)),Monthly!$D1330,((IF(ISNUMBER(FIND("Mar",$C$1)),Monthly!$E1330,(IF(ISNUMBER(FIND("Apr",$C$1)),Monthly!$F1330,((IF(ISNUMBER(FIND("May",$C$1)),Monthly!$G1330,((IF(ISNUMBER(FIND("Jun",$C$1)),Monthly!$H1330,(IF(ISNUMBER(FIND("Jul",$C$1)),Monthly!$I1330,(IF(ISNUMBER(FIND("Aug",$C$1)),Monthly!$J1330,(IF(ISNUMBER(FIND("Sep",$C$1)),Monthly!$K1330,(IF(ISNUMBER(FIND("Oct",$C$1)),Monthly!$L1330,(IF(ISNUMBER(FIND("Nov",$C$1)),Monthly!$M1330,(IF(ISNUMBER(FIND("Dec",$C$1)),Monthly!$N1330,)))))))))))))))))))))))))) -> 353.57561 | J8: =IF(ISNUMBER(FIND("Jan",$C$1)),Monthly!$C1253,(IF(ISNUMBER(FIND("Feb",$C$1)),Monthly!$D1253,((IF(ISNUMBER(FIND("Mar",$C$1)),Monthly!$E1253,(IF(ISNUMBER(FIND("Apr",$C$1)),Monthly!$F1253,((IF(ISNUMBER(FIND("May",$C$1)),Monthly!$G1253,((IF(ISNUMBER(FIND("Jun",$C$1)),Monthly!$H1253,(IF(ISNUMBER(FIND("Jul",$C$1)),Monthly!$I1253,(IF(ISNUMBER(FIND("Aug",$C$1)),Monthly!$J1253,(IF(ISNUMBER(FIND("Sep",$C$1)),Monthly!$K1253,(IF(ISNUMBER(FIND("Oct",$C$1)),Monthly!$L1253,(IF(ISNUMBER(FIND("Nov",$C$1)),Monthly!$M1253,(IF(ISNUMBER(FIND("Dec",$C$1)),Monthly!$N1253,)))))))))))))))))))))))))) -> 272.44704 | K8: =IF(ISNUMBER(FIND("Jan",$C$1)),Monthly!$C1175,(IF(ISNUMBER(FIND("Feb",$C$1)),Monthly!$D1175,((IF(ISNUMBER(FIND("Mar",$C$1)),Monthly!$E1175,(IF(ISNUMBER(FIND("Apr",$C$1)),Monthly!$F1175,((IF(ISNUMBER(FIND("May",$C$1)),Monthly!$G1175,((IF(ISNUMBER(FIND("Jun",$C$1)),Monthly!$H1175,(IF(ISNUMBER(FIND("Jul",$C$1)),Monthly!$I1175,(IF(ISNUMBER(FIND("Aug",$C$1)),Monthly!$J1175,(IF(ISNUMBER(FIND("Sep",$C$1)),Monthly!$K1175,(IF(ISNUMBER(FIND("Oct",$C$1)),Monthly!$L1175,(IF(ISNUMBER(FIND("Nov",$C$1)),Monthly!$M1175,(IF(ISNUMBER(FIND("Dec",$C$1)),Monthly!$N1175,)))))))))))))))))))))))))) -> 287.81519 | L8: =IF(ISNUMBER(FIND("Jan",$C$1)),Monthly!$C1098,(IF(ISNUMBER(FIND("Feb",$C$1)),Monthly!$D1098,((IF(ISNUMBER(FIND("Mar",$C$1)),Monthly!$E1098,(IF(ISNUMBER(FIND("Apr",$C$1)),Monthly!$F1098,((IF(ISNUMBER(FIND("May",$C$1)),Monthly!$G1098,((IF(ISNUMBER(FIND("Jun",$C$1)),Monthly!$H1098,(IF(ISNUMBER(FIND("Jul",$C$1)),Monthly!$I1098,(IF(ISNUMBER(FIND("Aug",$C$1)),Monthly!$J1098,(IF(ISNUMBER(FIND("Sep",$C$1)),Monthly!$K1098,(IF(ISNUMBER(FIND("Oct",$C$1)),Monthly!$L1098,(IF(ISNUMBER(FIND("Nov",$C$1)),Monthly!$M1098,(IF(ISNUMBER(FIND("Dec",$C$1)),Monthly!$N1098,)))))))))))))))))))))))))) -> 304.05023 | M8: =IF(ISNUMBER(FIND("Jan",$C$1)),Monthly!$C1021,(IF(ISNUMBER(FIND("Feb",$C$1)),Monthly!$D1021,((IF(ISNUMBER(FIND("Mar",$C$1)),Monthly!$E1021,(IF(ISNUMBER(FIND("Apr",$C$1)),Monthly!$F1021,((IF(ISNUMBER(FIND("May",$C$1)),Monthly!$G1021,((IF(ISNUMBER(FIND("Jun",$C$1)),Monthly!$H1021,(IF(ISNUMBER(FIND("Jul",$C$1)),Monthly!$I1021,(IF(ISNUMBER(FIND("Aug",$C$1)),Monthly!$J1021,(IF(ISNUMBER(FIND("Sep",$C$1)),Monthly!$K1021,(IF(ISNUMBER(FIND("Oct",$C$1)),Monthly!$L1021,(IF(ISNUMBER(FIND("Nov",$C$1)),Monthly!$M1021,(IF(ISNUMBER(FIND("Dec",$C$1)),Monthly!$N1021,)))))))))))))))))))))))))) -> 400 | N8: =IF(ISNUMBER(FIND("Jan",$C$1)),Monthly!$C944,(IF(ISNUMBER(FIND("Feb",$C$1)),Monthly!$D944,((IF(ISNUMBER(FIND("Mar",$C$1)),Monthly!$E944,(IF(ISNUMBER(FIND("Apr",$C$1)),Monthly!$F944,((IF(ISNUMBER(FIND("May",$C$1)),Monthly!$G944,((IF(ISNUMBER(FIND("Jun",$C$1)),Monthly!$H944,(IF(ISNUMBER(FIND("Jul",$C$1)),Monthly!$I944,(IF(ISNUMBER(FIND("Aug",$C$1)),Monthly!$J944,(IF(ISNUMBER(FIND("Sep",$C$1)),Monthly!$K944,(IF(ISNUMBER(FIND("Oct",$C$1)),Monthly!$L944,(IF(ISNUMBER(FIND("Nov",$C$1)),Monthly!$M944,(IF(ISNUMBER(FIND("Dec",$C$1)),Monthly!$N944,)))))))))))))))))))))))))) -> 400 | O8: =IF(ISNUMBER(FIND("Jan",$C$1)),Monthly!$C868,(IF(ISNUMBER(FIND("Feb",$C$1)),Monthly!$D868,((IF(ISNUMBER(FIND("Mar",$C$1)),Monthly!$E868,(IF(ISNUMBER(FIND("Apr",$C$1)),Monthly!$F868,((IF(ISNUMBER(FIND("May",$C$1)),Monthly!$G868,((IF(ISNUMBER(FIND("Jun",$C$1)),Monthly!$H868,(IF(ISNUMBER(FIND("Jul",$C$1)),Monthly!$I868,(IF(ISNUMBER(FIND("Aug",$C$1)),Monthly!$J868,(IF(ISNUMBER(FIND("Sep",$C$1)),Monthly!$K868,(IF(ISNUMBER(FIND("Oct",$C$1)),Monthly!$L868,(IF(ISNUMBER(FIND("Nov",$C$1)),Monthly!$M868,(IF(ISNUMBER(FIND("Dec",$C$1)),Monthly!$N868,)))))))))))))))))))))))))) -> 400 | P8: =IF(ISNUMBER(FIND("Jan",$C$1)),Monthly!$C791,(IF(ISNUMBER(FIND("Feb",$C$1)),Monthly!$D791,((IF(ISNUMBER(FIND("Mar",$C$1)),Monthly!$E791,(IF(ISNUMBER(FIND("Apr",$C$1)),Monthly!$F791,((IF(ISNUMBER(FIND("May",$C$1)),Monthly!$G791,((IF(ISNUMBER(FIND("Jun",$C$1)),Monthly!$H791,(IF(ISNUMBER(FIND("Jul",$C$1)),Monthly!$I791,(IF(ISNUMBER(FIND("Aug",$C$1)),Monthly!$J791,(IF(ISNUMBER(FIND("Sep",$C$1)),Monthly!$K791,(IF(ISNUMBER(FIND("Oct",$C$1)),Monthly!$L791,(IF(ISNUMBER(FIND("Nov",$C$1)),Monthly!$M791,(IF(ISNUMBER(FIND("Dec",$C$1)),Monthly!$N791,)))))))))))))))))))))))))) -> 0 | Q8: =IF(ISNUMBER(FIND("Jan",$C$1)),Monthly!$C714,(IF(ISNUMBER(FIND("Feb",$C$1)),Monthly!$D714,((IF(ISNUMBER(FIND("Mar",$C$1)),Monthly!$E714,(IF(ISNUMBER(FIND("Apr",$C$1)),Monthly!$F714,((IF(ISNUMBER(FIND("May",$C$1)),Monthly!$G714,((IF(ISNUMBER(FIND("Jun",$C$1)),Monthly!$H714,(IF(ISNUMBER(FIND("Jul",$C$1)),Monthly!$I714,(IF(ISNUMBER(FIND("Aug",$C$1)),Monthly!$J714,(IF(ISNUMBER(FIND("Sep",$C$1)),Monthly!$K714,(IF(ISNUMBER(FIND("Oct",$C$1)),Monthly!$L714,(IF(ISNUMBER(FIND("Nov",$C$1)),Monthly!$M714,(IF(ISNUMBER(FIND("Dec",$C$1)),Monthly!$N714,)))))))))))))))))))))))))) -> 0 | U8: =Monthly!O407 -> 4581.9398 | V8: =Monthly!O322 -> 4688.8478 | X8: =SUM(C8:Q8)/$E$77 -> 301.99353 | Y8: =X8/7000 -> 0.043141933 | AA8: =MAX(C8:Q8) -> 630 | AB8: =MIN(C8:Q8) -> 0
